{
  "updatedAt": "2026-05-04T12:40:31.639580+09:00",
  "updatedLabel": "2026-05-04 12:40:31 KST",
  "groups": [
    "국내 지수",
    "해외 지수",
    "거시 자산"
  ],
  "cards": [
    {
      "id": "kospi",
      "label": "KOSPI",
      "symbol": "^KS11",
      "group": "국내 지수",
      "kind": "equity",
      "decimals": 2,
      "price": 6870.68,
      "previousClose": 6598.87,
      "change": 271.81,
      "changePercent": 4.119,
      "tone": "up",
      "direction": "상승",
      "series": [
        [
          1777852800000,
          6749.180176
        ],
        [
          1777853100000,
          6768.029785
        ],
        [
          1777853400000,
          6757.149902
        ],
        [
          1777853700000,
          6760.140137
        ],
        [
          1777854000000,
          6755.919922
        ],
        [
          1777854300000,
          6768.47998
        ],
        [
          1777854600000,
          6768.810059
        ],
        [
          1777854900000,
          6757.290039
        ],
        [
          1777855200000,
          6765.0
        ],
        [
          1777855500000,
          6763.02002
        ],
        [
          1777855800000,
          6774.290039
        ],
        [
          1777856100000,
          6782.850098
        ],
        [
          1777856400000,
          6784.459961
        ],
        [
          1777856700000,
          6787.549805
        ],
        [
          1777857000000,
          6795.649902
        ],
        [
          1777857300000,
          6799.069824
        ],
        [
          1777857600000,
          6803.52002
        ],
        [
          1777857900000,
          6812.450195
        ],
        [
          1777858200000,
          6810.399902
        ],
        [
          1777858500000,
          6823.209961
        ],
        [
          1777858800000,
          6826.390137
        ],
        [
          1777859100000,
          6831.160156
        ],
        [
          1777859400000,
          6838.790039
        ],
        [
          1777859700000,
          6850.450195
        ],
        [
          1777860000000,
          6851.02002
        ],
        [
          1777860300000,
          6857.410156
        ],
        [
          1777860600000,
          6857.680176
        ],
        [
          1777860900000,
          6857.72998
        ],
        [
          1777861200000,
          6859.919922
        ],
        [
          1777861500000,
          6848.910156
        ],
        [
          1777861800000,
          6853.410156
        ],
        [
          1777862100000,
          6868.52002
        ],
        [
          1777862400000,
          6873.569824
        ],
        [
          1777862700000,
          6886.939941
        ],
        [
          1777863000000,
          6891.240234
        ],
        [
          1777863300000,
          6874.100098
        ],
        [
          1777863600000,
          6874.689941
        ],
        [
          1777863900000,
          6878.459961
        ],
        [
          1777864200000,
          6863.72998
        ],
        [
          1777864500000,
          6869.689941
        ],
        [
          1777864830000,
          6870.680176
        ]
      ],
      "marketState": "UNKNOWN",
      "marketTime": "2026-05-04 12:20 KST",
      "marketTimestamp": 1777864830
    },
    {
      "id": "kosdaq",
      "label": "KOSDAQ",
      "symbol": "^KQ11",
      "group": "국내 지수",
      "kind": "equity",
      "decimals": 2,
      "price": 1214.76,
      "previousClose": 1192.35,
      "change": 22.41,
      "changePercent": 1.8795,
      "tone": "up",
      "direction": "상승",
      "series": [
        [
          1777852800000,
          1216.47998
        ],
        [
          1777853100000,
          1216.699951
        ],
        [
          1777853400000,
          1215.560059
        ],
        [
          1777853700000,
          1217.180054
        ],
        [
          1777854000000,
          1218.859985
        ],
        [
          1777854300000,
          1220.540039
        ],
        [
          1777854600000,
          1221.599976
        ],
        [
          1777854900000,
          1221.439941
        ],
        [
          1777855200000,
          1220.290039
        ],
        [
          1777855500000,
          1221.51001
        ],
        [
          1777855800000,
          1221.079956
        ],
        [
          1777856100000,
          1220.72998
        ],
        [
          1777856400000,
          1219.339966
        ],
        [
          1777856700000,
          1219.420044
        ],
        [
          1777857000000,
          1217.349976
        ],
        [
          1777857300000,
          1216.829956
        ],
        [
          1777857600000,
          1218.77002
        ],
        [
          1777857900000,
          1216.709961
        ],
        [
          1777858200000,
          1215.310059
        ],
        [
          1777858500000,
          1215.369995
        ],
        [
          1777858800000,
          1215.640015
        ],
        [
          1777859100000,
          1215.01001
        ],
        [
          1777859400000,
          1216.369995
        ],
        [
          1777859700000,
          1217.01001
        ],
        [
          1777860000000,
          1216.72998
        ],
        [
          1777860300000,
          1215.910034
        ],
        [
          1777860600000,
          1215.01001
        ],
        [
          1777860900000,
          1214.819946
        ],
        [
          1777861200000,
          1214.089966
        ],
        [
          1777861500000,
          1214.27002
        ],
        [
          1777861800000,
          1214.52002
        ],
        [
          1777862100000,
          1213.660034
        ],
        [
          1777862400000,
          1212.380005
        ],
        [
          1777862700000,
          1212.280029
        ],
        [
          1777863000000,
          1212.359985
        ],
        [
          1777863300000,
          1212.869995
        ],
        [
          1777863600000,
          1214.27002
        ],
        [
          1777863900000,
          1214.550049
        ],
        [
          1777864200000,
          1215.079956
        ],
        [
          1777864500000,
          1214.949951
        ],
        [
          1777864830000,
          1214.76001
        ]
      ],
      "marketState": "UNKNOWN",
      "marketTime": "2026-05-04 12:20 KST",
      "marketTimestamp": 1777864830
    },
    {
      "id": "sp500",
      "label": "S&P 500",
      "symbol": "^GSPC",
      "group": "해외 지수",
      "kind": "equity",
      "decimals": 2,
      "price": 7230.12,
      "previousClose": 7209.01,
      "change": 21.11,
      "changePercent": 0.2928,
      "tone": "up",
      "direction": "상승",
      "series": [
        [
          1777642200000,
          7247.700195
        ],
        [
          1777642500000,
          7245.080078
        ],
        [
          1777642800000,
          7249.310059
        ],
        [
          1777643100000,
          7246.680176
        ],
        [
          1777643400000,
          7250.509766
        ],
        [
          1777643700000,
          7265.080078
        ],
        [
          1777644000000,
          7267.149902
        ],
        [
          1777644300000,
          7264.509766
        ],
        [
          1777644600000,
          7267.879883
        ],
        [
          1777644900000,
          7268.100098
        ],
        [
          1777645200000,
          7269.600098
        ],
        [
          1777645500000,
          7265.930176
        ],
        [
          1777645800000,
          7255.350098
        ],
        [
          1777646100000,
          7251.47998
        ],
        [
          1777646400000,
          7252.720215
        ],
        [
          1777646700000,
          7254.589844
        ],
        [
          1777647000000,
          7252.660156
        ],
        [
          1777647300000,
          7250.890137
        ],
        [
          1777647600000,
          7248.819824
        ],
        [
          1777647900000,
          7249.540039
        ],
        [
          1777648200000,
          7253.47998
        ],
        [
          1777648500000,
          7253.830078
        ],
        [
          1777648800000,
          7255.919922
        ],
        [
          1777649100000,
          7256.629883
        ],
        [
          1777649400000,
          7256.399902
        ],
        [
          1777649700000,
          7261.490234
        ],
        [
          1777650000000,
          7263.580078
        ],
        [
          1777650300000,
          7266.22998
        ],
        [
          1777650600000,
          7257.5
        ],
        [
          1777650900000,
          7257.290039
        ],
        [
          1777651200000,
          7256.759766
        ],
        [
          1777651500000,
          7248.620117
        ],
        [
          1777651800000,
          7248.310059
        ],
        [
          1777652100000,
          7253.029785
        ],
        [
          1777652400000,
          7249.149902
        ],
        [
          1777652700000,
          7245.529785
        ],
        [
          1777653000000,
          7243.419922
        ],
        [
          1777653300000,
          7245.569824
        ],
        [
          1777653600000,
          7240.660156
        ],
        [
          1777653900000,
          7239.720215
        ],
        [
          1777654200000,
          7244.540039
        ],
        [
          1777654500000,
          7242.310059
        ],
        [
          1777654800000,
          7244.950195
        ],
        [
          1777655100000,
          7245.060059
        ],
        [
          1777655400000,
          7247.870117
        ],
        [
          1777655700000,
          7250.040039
        ],
        [
          1777656000000,
          7250.640137
        ],
        [
          1777656300000,
          7253.080078
        ],
        [
          1777656600000,
          7253.029785
        ],
        [
          1777656900000,
          7251.25
        ],
        [
          1777657200000,
          7252.109863
        ],
        [
          1777657500000,
          7251.790039
        ],
        [
          1777657800000,
          7253.029785
        ],
        [
          1777658100000,
          7251.410156
        ],
        [
          1777658400000,
          7248.310059
        ],
        [
          1777658700000,
          7248.089844
        ],
        [
          1777659000000,
          7241.450195
        ],
        [
          1777659300000,
          7241.77002
        ],
        [
          1777659600000,
          7244.129883
        ],
        [
          1777659900000,
          7245.049805
        ],
        [
          1777660200000,
          7238.77002
        ],
        [
          1777660500000,
          7236.450195
        ],
        [
          1777660800000,
          7235.490234
        ],
        [
          1777661100000,
          7234.160156
        ],
        [
          1777661400000,
          7233.759766
        ],
        [
          1777661700000,
          7234.870117
        ],
        [
          1777662000000,
          7237.310059
        ],
        [
          1777662300000,
          7240.910156
        ],
        [
          1777662600000,
          7243.879883
        ],
        [
          1777662900000,
          7244.740234
        ],
        [
          1777663200000,
          7245.640137
        ],
        [
          1777663500000,
          7247.549805
        ],
        [
          1777663800000,
          7245.600098
        ],
        [
          1777664100000,
          7246.419922
        ],
        [
          1777664400000,
          7244.399902
        ],
        [
          1777664700000,
          7242.509766
        ],
        [
          1777665000000,
          7236.180176
        ],
        [
          1777665300000,
          7229.319824
        ],
        [
          1777665600000,
          7230.120117
        ]
      ],
      "marketState": "UNKNOWN",
      "marketTime": "2026-05-02 06:07 KST",
      "marketTimestamp": 1777669643
    },
    {
      "id": "nasdaq",
      "label": "NASDAQ",
      "symbol": "^IXIC",
      "group": "해외 지수",
      "kind": "equity",
      "decimals": 2,
      "price": 25114.443,
      "previousClose": 24892.3,
      "change": 222.143,
      "changePercent": 0.8924,
      "tone": "up",
      "direction": "상승",
      "series": [
        [
          1777642200000,
          25064.373047
        ],
        [
          1777642500000,
          25069.226562
        ],
        [
          1777642800000,
          25077.726562
        ],
        [
          1777643100000,
          25075.818359
        ],
        [
          1777643400000,
          25085.289062
        ],
        [
          1777643700000,
          25142.177734
        ],
        [
          1777644000000,
          25163.867188
        ],
        [
          1777644300000,
          25168.978516
        ],
        [
          1777644600000,
          25182.501953
        ],
        [
          1777644900000,
          25167.738281
        ],
        [
          1777645200000,
          25175.882812
        ],
        [
          1777645500000,
          25167.675781
        ],
        [
          1777645800000,
          25092.064453
        ],
        [
          1777646100000,
          25086.591797
        ],
        [
          1777646400000,
          25116.888672
        ],
        [
          1777646700000,
          25134.001953
        ],
        [
          1777647000000,
          25133.125
        ],
        [
          1777647300000,
          25130.630859
        ],
        [
          1777647600000,
          25108.900391
        ],
        [
          1777647900000,
          25107.892578
        ],
        [
          1777648200000,
          25139.220703
        ],
        [
          1777648500000,
          25148.681641
        ],
        [
          1777648800000,
          25158.347656
        ],
        [
          1777649100000,
          25164.279297
        ],
        [
          1777649400000,
          25167.566406
        ],
        [
          1777649700000,
          25197.925781
        ],
        [
          1777650000000,
          25200.658203
        ],
        [
          1777650300000,
          25218.355469
        ],
        [
          1777650600000,
          25179.199219
        ],
        [
          1777650900000,
          25185.853516
        ],
        [
          1777651200000,
          25182.644531
        ],
        [
          1777651500000,
          25141.099609
        ],
        [
          1777651800000,
          25146.367188
        ],
        [
          1777652100000,
          25167.072266
        ],
        [
          1777652400000,
          25151.697266
        ],
        [
          1777652700000,
          25137.884766
        ],
        [
          1777653000000,
          25132.591797
        ],
        [
          1777653300000,
          25141.480469
        ],
        [
          1777653600000,
          25118.902344
        ],
        [
          1777653900000,
          25113.179688
        ],
        [
          1777654200000,
          25137.490234
        ],
        [
          1777654500000,
          25133.181641
        ],
        [
          1777654800000,
          25141.220703
        ],
        [
          1777655100000,
          25143.734375
        ],
        [
          1777655400000,
          25157.904297
        ],
        [
          1777655700000,
          25176.955078
        ],
        [
          1777656000000,
          25179.447266
        ],
        [
          1777656300000,
          25186.455078
        ],
        [
          1777656600000,
          25175.71875
        ],
        [
          1777656900000,
          25174.287109
        ],
        [
          1777657200000,
          25180.757812
        ],
        [
          1777657500000,
          25177.505859
        ],
        [
          1777657800000,
          25176.435547
        ],
        [
          1777658100000,
          25174.408203
        ],
        [
          1777658400000,
          25160.015625
        ],
        [
          1777658700000,
          25167.289062
        ],
        [
          1777659000000,
          25141.570312
        ],
        [
          1777659300000,
          25145.386719
        ],
        [
          1777659600000,
          25159.285156
        ],
        [
          1777659900000,
          25161.439453
        ],
        [
          1777660200000,
          25137.736328
        ],
        [
          1777660500000,
          25126.953125
        ],
        [
          1777660800000,
          25115.130859
        ],
        [
          1777661100000,
          25100.867188
        ],
        [
          1777661400000,
          25101.216797
        ],
        [
          1777661700000,
          25110.396484
        ],
        [
          1777662000000,
          25127.761719
        ],
        [
          1777662300000,
          25139.835938
        ],
        [
          1777662600000,
          25151.960938
        ],
        [
          1777662900000,
          25149.027344
        ],
        [
          1777663200000,
          25156.527344
        ],
        [
          1777663500000,
          25174.601562
        ],
        [
          1777663800000,
          25166.960938
        ],
        [
          1777664100000,
          25161.21875
        ],
        [
          1777664400000,
          25157.013672
        ],
        [
          1777664700000,
          25147.626953
        ],
        [
          1777665000000,
          25122.818359
        ],
        [
          1777665300000,
          25109.980469
        ],
        [
          1777665600000,
          25114.443359
        ]
      ],
      "marketState": "UNKNOWN",
      "marketTime": "2026-05-02 06:15 KST",
      "marketTimestamp": 1777670159
    },
    {
      "id": "dow",
      "label": "DOW",
      "symbol": "^DJI",
      "group": "해외 지수",
      "kind": "equity",
      "decimals": 2,
      "price": 49499.27,
      "previousClose": 49652.1,
      "change": -152.83,
      "changePercent": -0.3078,
      "tone": "down",
      "direction": "하락",
      "series": [
        [
          1777642200000,
          49829.230469
        ],
        [
          1777642500000,
          49815.230469
        ],
        [
          1777642800000,
          49807.921875
        ],
        [
          1777643100000,
          49757.070312
        ],
        [
          1777643400000,
          49812.730469
        ],
        [
          1777643700000,
          49929.148438
        ],
        [
          1777644000000,
          49976.109375
        ],
        [
          1777644300000,
          49915.25
        ],
        [
          1777644600000,
          49924.71875
        ],
        [
          1777644900000,
          49968.039062
        ],
        [
          1777645200000,
          49953.660156
        ],
        [
          1777645500000,
          49896.351562
        ],
        [
          1777645800000,
          49876.039062
        ],
        [
          1777646100000,
          49841.761719
        ],
        [
          1777646400000,
          49803.828125
        ],
        [
          1777646700000,
          49823.550781
        ],
        [
          1777647000000,
          49773.210938
        ],
        [
          1777647300000,
          49770.519531
        ],
        [
          1777647600000,
          49749.871094
        ],
        [
          1777647900000,
          49773.179688
        ],
        [
          1777648200000,
          49765.261719
        ],
        [
          1777648500000,
          49718.121094
        ],
        [
          1777648800000,
          49738.550781
        ],
        [
          1777649100000,
          49725.648438
        ],
        [
          1777649400000,
          49695.808594
        ],
        [
          1777649700000,
          49713.921875
        ],
        [
          1777650000000,
          49739.851562
        ],
        [
          1777650300000,
          49743.671875
        ],
        [
          1777650600000,
          49688.398438
        ],
        [
          1777650900000,
          49672.609375
        ],
        [
          1777651200000,
          49667.648438
        ],
        [
          1777651500000,
          49658.851562
        ],
        [
          1777651800000,
          49632.691406
        ],
        [
          1777652100000,
          49657.769531
        ],
        [
          1777652400000,
          49617.808594
        ],
        [
          1777652700000,
          49593.589844
        ],
        [
          1777653000000,
          49576.378906
        ],
        [
          1777653300000,
          49599.410156
        ],
        [
          1777653600000,
          49588.769531
        ],
        [
          1777653900000,
          49580.5
        ],
        [
          1777654200000,
          49602.160156
        ],
        [
          1777654500000,
          49601.589844
        ],
        [
          1777654800000,
          49623.300781
        ],
        [
          1777655100000,
          49618.089844
        ],
        [
          1777655400000,
          49641.589844
        ],
        [
          1777655700000,
          49623.921875
        ],
        [
          1777656000000,
          49630.449219
        ],
        [
          1777656300000,
          49647.871094
        ],
        [
          1777656600000,
          49674.808594
        ],
        [
          1777656900000,
          49659.828125
        ],
        [
          1777657200000,
          49654.691406
        ],
        [
          1777657500000,
          49659.308594
        ],
        [
          1777657800000,
          49688.890625
        ],
        [
          1777658100000,
          49674.058594
        ],
        [
          1777658400000,
          49651.039062
        ],
        [
          1777658700000,
          49628.398438
        ],
        [
          1777659000000,
          49590.539062
        ],
        [
          1777659300000,
          49586.898438
        ],
        [
          1777659600000,
          49593.109375
        ],
        [
          1777659900000,
          49610.910156
        ],
        [
          1777660200000,
          49561.480469
        ],
        [
          1777660500000,
          49544.921875
        ],
        [
          1777660800000,
          49559.53125
        ],
        [
          1777661100000,
          49571.851562
        ],
        [
          1777661400000,
          49569.828125
        ],
        [
          1777661700000,
          49563.78125
        ],
        [
          1777662000000,
          49557.46875
        ],
        [
          1777662300000,
          49574.320312
        ],
        [
          1777662600000,
          49581.261719
        ],
        [
          1777662900000,
          49613.53125
        ],
        [
          1777663200000,
          49603.828125
        ],
        [
          1777663500000,
          49610.738281
        ],
        [
          1777663800000,
          49604.230469
        ],
        [
          1777664100000,
          49629.898438
        ],
        [
          1777664400000,
          49604.140625
        ],
        [
          1777664700000,
          49585.5
        ],
        [
          1777665000000,
          49539.480469
        ],
        [
          1777665300000,
          49496.46875
        ],
        [
          1777665600000,
          49499.269531
        ]
      ],
      "marketState": "UNKNOWN",
      "marketTime": "2026-05-02 06:09 KST",
      "marketTimestamp": 1777669798
    },
    {
      "id": "usdkrw",
      "label": "USD/KRW",
      "symbol": "KRW=X",
      "group": "거시 자산",
      "kind": "fx",
      "decimals": 2,
      "price": 1471.22,
      "previousClose": 1473.22,
      "change": -2.0,
      "changePercent": -0.1358,
      "tone": "flat",
      "direction": "보합",
      "series": [],
      "marketState": "UNKNOWN",
      "marketTime": "2026-05-02 11:45 KST",
      "marketTimestamp": 1777689926
    },
    {
      "id": "us10y",
      "label": "미국 10Y",
      "symbol": "^TNX",
      "group": "거시 자산",
      "kind": "yield",
      "decimals": 3,
      "price": 4.378,
      "previousClose": 4.39,
      "change": -0.012,
      "changePercent": -0.2733,
      "tone": "down",
      "direction": "하락",
      "series": [
        [
          1777638000000,
          4.366
        ],
        [
          1777638300000,
          4.366
        ],
        [
          1777638600000,
          4.366
        ],
        [
          1777638900000,
          4.37
        ],
        [
          1777639200000,
          4.38
        ],
        [
          1777639500000,
          4.388
        ],
        [
          1777639800000,
          4.384
        ],
        [
          1777640100000,
          4.39
        ],
        [
          1777640400000,
          4.39
        ],
        [
          1777640700000,
          4.386
        ],
        [
          1777641000000,
          4.39
        ],
        [
          1777641300000,
          4.388
        ],
        [
          1777641600000,
          4.392
        ],
        [
          1777641900000,
          4.392
        ],
        [
          1777642200000,
          4.392
        ],
        [
          1777642500000,
          4.394
        ],
        [
          1777642800000,
          4.396
        ],
        [
          1777643100000,
          4.402
        ],
        [
          1777643400000,
          4.396
        ],
        [
          1777643700000,
          4.386
        ],
        [
          1777644000000,
          4.364
        ],
        [
          1777644300000,
          4.36
        ],
        [
          1777644600000,
          4.352
        ],
        [
          1777644900000,
          4.348
        ],
        [
          1777645200000,
          4.344
        ],
        [
          1777645500000,
          4.35
        ],
        [
          1777645800000,
          4.36
        ],
        [
          1777646100000,
          4.366
        ],
        [
          1777646400000,
          4.366
        ],
        [
          1777646700000,
          4.366
        ],
        [
          1777647000000,
          4.374
        ],
        [
          1777647300000,
          4.368
        ],
        [
          1777647600000,
          4.372
        ],
        [
          1777647900000,
          4.38
        ],
        [
          1777648200000,
          4.376
        ],
        [
          1777648500000,
          4.378
        ],
        [
          1777648800000,
          4.374
        ],
        [
          1777649100000,
          4.376
        ],
        [
          1777649400000,
          4.378
        ],
        [
          1777649700000,
          4.376
        ],
        [
          1777650000000,
          4.376
        ],
        [
          1777650300000,
          4.37
        ],
        [
          1777650600000,
          4.374
        ],
        [
          1777650900000,
          4.38
        ],
        [
          1777651200000,
          4.376
        ],
        [
          1777651500000,
          4.374
        ],
        [
          1777651800000,
          4.37
        ],
        [
          1777652100000,
          4.366
        ],
        [
          1777652400000,
          4.372
        ],
        [
          1777652700000,
          4.372
        ],
        [
          1777653000000,
          4.376
        ],
        [
          1777653300000,
          4.368
        ],
        [
          1777653600000,
          4.37
        ],
        [
          1777653900000,
          4.37
        ],
        [
          1777654200000,
          4.372
        ],
        [
          1777654500000,
          4.378
        ],
        [
          1777654800000,
          4.382
        ],
        [
          1777655100000,
          4.376
        ],
        [
          1777655400000,
          4.378
        ],
        [
          1777655700000,
          4.376
        ],
        [
          1777656000000,
          4.374
        ],
        [
          1777656300000,
          4.378
        ],
        [
          1777656600000,
          4.376
        ],
        [
          1777656900000,
          4.376
        ],
        [
          1777657200000,
          4.378
        ],
        [
          1777657500000,
          4.376
        ],
        [
          1777657800000,
          4.374
        ],
        [
          1777658100000,
          4.376
        ],
        [
          1777658400000,
          4.376
        ],
        [
          1777658700000,
          4.378
        ],
        [
          1777659000000,
          4.382
        ],
        [
          1777659300000,
          4.38
        ],
        [
          1777659600000,
          4.38
        ],
        [
          1777659900000,
          4.38
        ],
        [
          1777660200000,
          4.376
        ],
        [
          1777660500000,
          4.374
        ],
        [
          1777660800000,
          4.376
        ],
        [
          1777661100000,
          4.376
        ],
        [
          1777661400000,
          4.376
        ],
        [
          1777661700000,
          4.378
        ]
      ],
      "marketState": "UNKNOWN",
      "marketTime": "2026-05-02 03:59 KST",
      "marketTimestamp": 1777661994
    },
    {
      "id": "wti",
      "label": "WTI",
      "symbol": "CL=F",
      "group": "거시 자산",
      "kind": "commodity",
      "decimals": 2,
      "price": 101.83,
      "previousClose": 101.94,
      "change": -0.11,
      "changePercent": -0.1079,
      "tone": "flat",
      "direction": "보합",
      "series": [
        [
          1777846200000,
          100.199997
        ],
        [
          1777846500000,
          100.739998
        ],
        [
          1777846800000,
          101.330002
        ],
        [
          1777847100000,
          101.25
        ],
        [
          1777847400000,
          101.300003
        ],
        [
          1777847700000,
          101.269997
        ],
        [
          1777848000000,
          101.029999
        ],
        [
          1777848300000,
          100.949997
        ],
        [
          1777848600000,
          101.190002
        ],
        [
          1777848900000,
          101.059998
        ],
        [
          1777849200000,
          101.18
        ],
        [
          1777849500000,
          101.099998
        ],
        [
          1777849800000,
          101.209999
        ],
        [
          1777850100000,
          101.260002
        ],
        [
          1777850400000,
          101.389999
        ],
        [
          1777850700000,
          101.550003
        ],
        [
          1777851000000,
          101.419998
        ],
        [
          1777851300000,
          101.489998
        ],
        [
          1777851600000,
          101.620003
        ],
        [
          1777851900000,
          101.730003
        ],
        [
          1777852200000,
          101.68
        ],
        [
          1777852500000,
          101.730003
        ],
        [
          1777852800000,
          102.110001
        ],
        [
          1777853100000,
          101.959999
        ],
        [
          1777853400000,
          102.010002
        ],
        [
          1777853700000,
          102.040001
        ],
        [
          1777854000000,
          102.260002
        ],
        [
          1777854300000,
          102.169998
        ],
        [
          1777854600000,
          101.970001
        ],
        [
          1777854900000,
          102.029999
        ],
        [
          1777855200000,
          101.709999
        ],
        [
          1777855500000,
          101.199997
        ],
        [
          1777855800000,
          101.25
        ],
        [
          1777856100000,
          101.160004
        ],
        [
          1777856400000,
          101.190002
        ],
        [
          1777856700000,
          101.68
        ],
        [
          1777857000000,
          101.610001
        ],
        [
          1777857300000,
          101.599998
        ],
        [
          1777857600000,
          101.610001
        ],
        [
          1777857900000,
          101.940002
        ],
        [
          1777858200000,
          101.739998
        ],
        [
          1777858500000,
          101.730003
        ],
        [
          1777858800000,
          101.790001
        ],
        [
          1777859100000,
          101.839996
        ],
        [
          1777859400000,
          101.760002
        ],
        [
          1777859700000,
          101.629997
        ],
        [
          1777860000000,
          101.650002
        ],
        [
          1777860300000,
          101.620003
        ],
        [
          1777860600000,
          101.5
        ],
        [
          1777860900000,
          101.660004
        ],
        [
          1777861200000,
          101.910004
        ],
        [
          1777861500000,
          102.019997
        ],
        [
          1777861800000,
          101.739998
        ],
        [
          1777862100000,
          101.75
        ],
        [
          1777862400000,
          101.839996
        ],
        [
          1777862700000,
          101.839996
        ],
        [
          1777863000000,
          101.769997
        ],
        [
          1777863300000,
          101.82
        ],
        [
          1777863600000,
          101.809998
        ],
        [
          1777863900000,
          101.800003
        ],
        [
          1777864200000,
          101.849998
        ],
        [
          1777864500000,
          101.940002
        ],
        [
          1777864800000,
          101.910004
        ],
        [
          1777865100000,
          101.849998
        ],
        [
          1777865400000,
          101.849998
        ],
        [
          1777865411000,
          101.830002
        ]
      ],
      "marketState": "UNKNOWN",
      "marketTime": "2026-05-04 12:30 KST",
      "marketTimestamp": 1777865411
    },
    {
      "id": "gold",
      "label": "Gold",
      "symbol": "GC=F",
      "group": "거시 자산",
      "kind": "commodity",
      "decimals": 2,
      "price": 4621.7,
      "previousClose": 4644.5,
      "change": -22.8,
      "changePercent": -0.4909,
      "tone": "down",
      "direction": "하락",
      "series": [
        [
          1777846200000,
          4634.600098
        ],
        [
          1777846500000,
          4633.100098
        ],
        [
          1777846800000,
          4629.0
        ],
        [
          1777847100000,
          4632.299805
        ],
        [
          1777847400000,
          4634.899902
        ],
        [
          1777847700000,
          4637.0
        ],
        [
          1777848000000,
          4639.899902
        ],
        [
          1777848300000,
          4637.700195
        ],
        [
          1777848600000,
          4631.5
        ],
        [
          1777848900000,
          4630.700195
        ],
        [
          1777849200000,
          4631.0
        ],
        [
          1777849500000,
          4627.0
        ],
        [
          1777849800000,
          4626.100098
        ],
        [
          1777850100000,
          4627.600098
        ],
        [
          1777850400000,
          4626.899902
        ],
        [
          1777850700000,
          4628.200195
        ],
        [
          1777851000000,
          4628.5
        ],
        [
          1777851300000,
          4626.299805
        ],
        [
          1777851600000,
          4625.100098
        ],
        [
          1777851900000,
          4626.200195
        ],
        [
          1777852200000,
          4627.899902
        ],
        [
          1777852500000,
          4625.0
        ],
        [
          1777852800000,
          4620.0
        ],
        [
          1777853100000,
          4627.100098
        ],
        [
          1777853400000,
          4623.399902
        ],
        [
          1777853700000,
          4618.899902
        ],
        [
          1777854000000,
          4615.600098
        ],
        [
          1777854300000,
          4617.0
        ],
        [
          1777854600000,
          4619.600098
        ],
        [
          1777854900000,
          4617.299805
        ],
        [
          1777855200000,
          4617.5
        ],
        [
          1777855500000,
          4620.899902
        ],
        [
          1777855800000,
          4620.600098
        ],
        [
          1777856100000,
          4623.600098
        ],
        [
          1777856400000,
          4612.100098
        ],
        [
          1777856700000,
          4609.799805
        ],
        [
          1777857000000,
          4611.700195
        ],
        [
          1777857300000,
          4610.700195
        ],
        [
          1777857600000,
          4609.299805
        ],
        [
          1777857900000,
          4605.700195
        ],
        [
          1777858200000,
          4610.700195
        ],
        [
          1777858500000,
          4611.100098
        ],
        [
          1777858800000,
          4612.399902
        ],
        [
          1777859100000,
          4612.299805
        ],
        [
          1777859400000,
          4616.899902
        ],
        [
          1777859700000,
          4624.200195
        ],
        [
          1777860000000,
          4624.299805
        ],
        [
          1777860300000,
          4619.899902
        ],
        [
          1777860600000,
          4619.200195
        ],
        [
          1777860900000,
          4616.5
        ],
        [
          1777861200000,
          4609.200195
        ],
        [
          1777861500000,
          4603.799805
        ],
        [
          1777861800000,
          4606.299805
        ],
        [
          1777862100000,
          4611.700195
        ],
        [
          1777862400000,
          4614.799805
        ],
        [
          1777862700000,
          4615.5
        ],
        [
          1777863000000,
          4620.5
        ],
        [
          1777863300000,
          4616.899902
        ],
        [
          1777863600000,
          4616.200195
        ],
        [
          1777863900000,
          4619.100098
        ],
        [
          1777864200000,
          4620.5
        ],
        [
          1777864500000,
          4619.899902
        ],
        [
          1777864800000,
          4620.799805
        ],
        [
          1777865100000,
          4620.899902
        ],
        [
          1777865400000,
          4620.100098
        ],
        [
          1777865427000,
          4621.700195
        ]
      ],
      "marketState": "UNKNOWN",
      "marketTime": "2026-05-04 12:30 KST",
      "marketTimestamp": 1777865427
    },
    {
      "id": "bitcoin",
      "label": "Bitcoin",
      "symbol": "BTC-USD",
      "group": "거시 자산",
      "kind": "crypto",
      "decimals": 0,
      "price": 79982.55,
      "previousClose": 78543.43,
      "change": 1439.12,
      "changePercent": 1.8323,
      "tone": "up",
      "direction": "상승",
      "series": [
        [
          1777852800000,
          78488.007812
        ],
        [
          1777853100000,
          78458.953125
        ],
        [
          1777853400000,
          78506.039062
        ],
        [
          1777853700000,
          78431.257812
        ],
        [
          1777854000000,
          78332.648438
        ],
        [
          1777854300000,
          78351.703125
        ],
        [
          1777854600000,
          78414.429688
        ],
        [
          1777854900000,
          78319.351562
        ],
        [
          1777855200000,
          78380.617188
        ],
        [
          1777855500000,
          78452.460938
        ],
        [
          1777855800000,
          78418.453125
        ],
        [
          1777856100000,
          78537.429688
        ],
        [
          1777856400000,
          78417.4375
        ],
        [
          1777856700000,
          78465.882812
        ],
        [
          1777857000000,
          78444.039062
        ],
        [
          1777857300000,
          78440.15625
        ],
        [
          1777857600000,
          78415.382812
        ],
        [
          1777857900000,
          78592.023438
        ],
        [
          1777858200000,
          78953.742188
        ],
        [
          1777858500000,
          78862.320312
        ],
        [
          1777858800000,
          78799.640625
        ],
        [
          1777859100000,
          78974.007812
        ],
        [
          1777859400000,
          79237.460938
        ],
        [
          1777859700000,
          79756.453125
        ],
        [
          1777860000000,
          79721.859375
        ],
        [
          1777860300000,
          79939.84375
        ],
        [
          1777860600000,
          79935.210938
        ],
        [
          1777860900000,
          79869.890625
        ],
        [
          1777861200000,
          79710.296875
        ],
        [
          1777861500000,
          79684.570312
        ],
        [
          1777861800000,
          79738.703125
        ],
        [
          1777862100000,
          79938.046875
        ],
        [
          1777862400000,
          80154.140625
        ],
        [
          1777862700000,
          80129.710938
        ],
        [
          1777863000000,
          80240.859375
        ],
        [
          1777863300000,
          80171.726562
        ],
        [
          1777863600000,
          80098.992188
        ],
        [
          1777863900000,
          80209.726562
        ],
        [
          1777864200000,
          80368.867188
        ],
        [
          1777864500000,
          80188.21875
        ],
        [
          1777864800000,
          80107.976562
        ],
        [
          1777865100000,
          80098.992188
        ],
        [
          1777865400000,
          80043.226562
        ],
        [
          1777865700000,
          79995.203125
        ],
        [
          1777866025000,
          79982.546875
        ]
      ],
      "marketState": "UNKNOWN",
      "marketTime": "2026-05-04 12:40 KST",
      "marketTimestamp": 1777866025
    }
  ],
  "mainCharts": [
    {
      "id": "kospi",
      "label": "KOSPI",
      "symbol": "^KS11",
      "group": "국내 지수",
      "kind": "equity",
      "decimals": 2,
      "price": 6870.68,
      "previousClose": 6598.87,
      "change": 271.81,
      "changePercent": 4.119,
      "tone": "up",
      "direction": "상승",
      "series": [
        [
          1777852800000,
          6749.180176
        ],
        [
          1777853100000,
          6768.029785
        ],
        [
          1777853400000,
          6757.149902
        ],
        [
          1777853700000,
          6760.140137
        ],
        [
          1777854000000,
          6755.919922
        ],
        [
          1777854300000,
          6768.47998
        ],
        [
          1777854600000,
          6768.810059
        ],
        [
          1777854900000,
          6757.290039
        ],
        [
          1777855200000,
          6765.0
        ],
        [
          1777855500000,
          6763.02002
        ],
        [
          1777855800000,
          6774.290039
        ],
        [
          1777856100000,
          6782.850098
        ],
        [
          1777856400000,
          6784.459961
        ],
        [
          1777856700000,
          6787.549805
        ],
        [
          1777857000000,
          6795.649902
        ],
        [
          1777857300000,
          6799.069824
        ],
        [
          1777857600000,
          6803.52002
        ],
        [
          1777857900000,
          6812.450195
        ],
        [
          1777858200000,
          6810.399902
        ],
        [
          1777858500000,
          6823.209961
        ],
        [
          1777858800000,
          6826.390137
        ],
        [
          1777859100000,
          6831.160156
        ],
        [
          1777859400000,
          6838.790039
        ],
        [
          1777859700000,
          6850.450195
        ],
        [
          1777860000000,
          6851.02002
        ],
        [
          1777860300000,
          6857.410156
        ],
        [
          1777860600000,
          6857.680176
        ],
        [
          1777860900000,
          6857.72998
        ],
        [
          1777861200000,
          6859.919922
        ],
        [
          1777861500000,
          6848.910156
        ],
        [
          1777861800000,
          6853.410156
        ],
        [
          1777862100000,
          6868.52002
        ],
        [
          1777862400000,
          6873.569824
        ],
        [
          1777862700000,
          6886.939941
        ],
        [
          1777863000000,
          6891.240234
        ],
        [
          1777863300000,
          6874.100098
        ],
        [
          1777863600000,
          6874.689941
        ],
        [
          1777863900000,
          6878.459961
        ],
        [
          1777864200000,
          6863.72998
        ],
        [
          1777864500000,
          6869.689941
        ],
        [
          1777864830000,
          6870.680176
        ]
      ],
      "marketState": "UNKNOWN",
      "marketTime": "2026-05-04 12:20 KST",
      "marketTimestamp": 1777864830
    },
    {
      "id": "kosdaq",
      "label": "KOSDAQ",
      "symbol": "^KQ11",
      "group": "국내 지수",
      "kind": "equity",
      "decimals": 2,
      "price": 1214.76,
      "previousClose": 1192.35,
      "change": 22.41,
      "changePercent": 1.8795,
      "tone": "up",
      "direction": "상승",
      "series": [
        [
          1777852800000,
          1216.47998
        ],
        [
          1777853100000,
          1216.699951
        ],
        [
          1777853400000,
          1215.560059
        ],
        [
          1777853700000,
          1217.180054
        ],
        [
          1777854000000,
          1218.859985
        ],
        [
          1777854300000,
          1220.540039
        ],
        [
          1777854600000,
          1221.599976
        ],
        [
          1777854900000,
          1221.439941
        ],
        [
          1777855200000,
          1220.290039
        ],
        [
          1777855500000,
          1221.51001
        ],
        [
          1777855800000,
          1221.079956
        ],
        [
          1777856100000,
          1220.72998
        ],
        [
          1777856400000,
          1219.339966
        ],
        [
          1777856700000,
          1219.420044
        ],
        [
          1777857000000,
          1217.349976
        ],
        [
          1777857300000,
          1216.829956
        ],
        [
          1777857600000,
          1218.77002
        ],
        [
          1777857900000,
          1216.709961
        ],
        [
          1777858200000,
          1215.310059
        ],
        [
          1777858500000,
          1215.369995
        ],
        [
          1777858800000,
          1215.640015
        ],
        [
          1777859100000,
          1215.01001
        ],
        [
          1777859400000,
          1216.369995
        ],
        [
          1777859700000,
          1217.01001
        ],
        [
          1777860000000,
          1216.72998
        ],
        [
          1777860300000,
          1215.910034
        ],
        [
          1777860600000,
          1215.01001
        ],
        [
          1777860900000,
          1214.819946
        ],
        [
          1777861200000,
          1214.089966
        ],
        [
          1777861500000,
          1214.27002
        ],
        [
          1777861800000,
          1214.52002
        ],
        [
          1777862100000,
          1213.660034
        ],
        [
          1777862400000,
          1212.380005
        ],
        [
          1777862700000,
          1212.280029
        ],
        [
          1777863000000,
          1212.359985
        ],
        [
          1777863300000,
          1212.869995
        ],
        [
          1777863600000,
          1214.27002
        ],
        [
          1777863900000,
          1214.550049
        ],
        [
          1777864200000,
          1215.079956
        ],
        [
          1777864500000,
          1214.949951
        ],
        [
          1777864830000,
          1214.76001
        ]
      ],
      "marketState": "UNKNOWN",
      "marketTime": "2026-05-04 12:20 KST",
      "marketTimestamp": 1777864830
    },
    {
      "id": "sp500",
      "label": "S&P 500",
      "symbol": "^GSPC",
      "group": "해외 지수",
      "kind": "equity",
      "decimals": 2,
      "price": 7230.12,
      "previousClose": 7209.01,
      "change": 21.11,
      "changePercent": 0.2928,
      "tone": "up",
      "direction": "상승",
      "series": [
        [
          1777642200000,
          7247.700195
        ],
        [
          1777642500000,
          7245.080078
        ],
        [
          1777642800000,
          7249.310059
        ],
        [
          1777643100000,
          7246.680176
        ],
        [
          1777643400000,
          7250.509766
        ],
        [
          1777643700000,
          7265.080078
        ],
        [
          1777644000000,
          7267.149902
        ],
        [
          1777644300000,
          7264.509766
        ],
        [
          1777644600000,
          7267.879883
        ],
        [
          1777644900000,
          7268.100098
        ],
        [
          1777645200000,
          7269.600098
        ],
        [
          1777645500000,
          7265.930176
        ],
        [
          1777645800000,
          7255.350098
        ],
        [
          1777646100000,
          7251.47998
        ],
        [
          1777646400000,
          7252.720215
        ],
        [
          1777646700000,
          7254.589844
        ],
        [
          1777647000000,
          7252.660156
        ],
        [
          1777647300000,
          7250.890137
        ],
        [
          1777647600000,
          7248.819824
        ],
        [
          1777647900000,
          7249.540039
        ],
        [
          1777648200000,
          7253.47998
        ],
        [
          1777648500000,
          7253.830078
        ],
        [
          1777648800000,
          7255.919922
        ],
        [
          1777649100000,
          7256.629883
        ],
        [
          1777649400000,
          7256.399902
        ],
        [
          1777649700000,
          7261.490234
        ],
        [
          1777650000000,
          7263.580078
        ],
        [
          1777650300000,
          7266.22998
        ],
        [
          1777650600000,
          7257.5
        ],
        [
          1777650900000,
          7257.290039
        ],
        [
          1777651200000,
          7256.759766
        ],
        [
          1777651500000,
          7248.620117
        ],
        [
          1777651800000,
          7248.310059
        ],
        [
          1777652100000,
          7253.029785
        ],
        [
          1777652400000,
          7249.149902
        ],
        [
          1777652700000,
          7245.529785
        ],
        [
          1777653000000,
          7243.419922
        ],
        [
          1777653300000,
          7245.569824
        ],
        [
          1777653600000,
          7240.660156
        ],
        [
          1777653900000,
          7239.720215
        ],
        [
          1777654200000,
          7244.540039
        ],
        [
          1777654500000,
          7242.310059
        ],
        [
          1777654800000,
          7244.950195
        ],
        [
          1777655100000,
          7245.060059
        ],
        [
          1777655400000,
          7247.870117
        ],
        [
          1777655700000,
          7250.040039
        ],
        [
          1777656000000,
          7250.640137
        ],
        [
          1777656300000,
          7253.080078
        ],
        [
          1777656600000,
          7253.029785
        ],
        [
          1777656900000,
          7251.25
        ],
        [
          1777657200000,
          7252.109863
        ],
        [
          1777657500000,
          7251.790039
        ],
        [
          1777657800000,
          7253.029785
        ],
        [
          1777658100000,
          7251.410156
        ],
        [
          1777658400000,
          7248.310059
        ],
        [
          1777658700000,
          7248.089844
        ],
        [
          1777659000000,
          7241.450195
        ],
        [
          1777659300000,
          7241.77002
        ],
        [
          1777659600000,
          7244.129883
        ],
        [
          1777659900000,
          7245.049805
        ],
        [
          1777660200000,
          7238.77002
        ],
        [
          1777660500000,
          7236.450195
        ],
        [
          1777660800000,
          7235.490234
        ],
        [
          1777661100000,
          7234.160156
        ],
        [
          1777661400000,
          7233.759766
        ],
        [
          1777661700000,
          7234.870117
        ],
        [
          1777662000000,
          7237.310059
        ],
        [
          1777662300000,
          7240.910156
        ],
        [
          1777662600000,
          7243.879883
        ],
        [
          1777662900000,
          7244.740234
        ],
        [
          1777663200000,
          7245.640137
        ],
        [
          1777663500000,
          7247.549805
        ],
        [
          1777663800000,
          7245.600098
        ],
        [
          1777664100000,
          7246.419922
        ],
        [
          1777664400000,
          7244.399902
        ],
        [
          1777664700000,
          7242.509766
        ],
        [
          1777665000000,
          7236.180176
        ],
        [
          1777665300000,
          7229.319824
        ],
        [
          1777665600000,
          7230.120117
        ]
      ],
      "marketState": "UNKNOWN",
      "marketTime": "2026-05-02 06:07 KST",
      "marketTimestamp": 1777669643
    },
    {
      "id": "nasdaq",
      "label": "NASDAQ",
      "symbol": "^IXIC",
      "group": "해외 지수",
      "kind": "equity",
      "decimals": 2,
      "price": 25114.443,
      "previousClose": 24892.3,
      "change": 222.143,
      "changePercent": 0.8924,
      "tone": "up",
      "direction": "상승",
      "series": [
        [
          1777642200000,
          25064.373047
        ],
        [
          1777642500000,
          25069.226562
        ],
        [
          1777642800000,
          25077.726562
        ],
        [
          1777643100000,
          25075.818359
        ],
        [
          1777643400000,
          25085.289062
        ],
        [
          1777643700000,
          25142.177734
        ],
        [
          1777644000000,
          25163.867188
        ],
        [
          1777644300000,
          25168.978516
        ],
        [
          1777644600000,
          25182.501953
        ],
        [
          1777644900000,
          25167.738281
        ],
        [
          1777645200000,
          25175.882812
        ],
        [
          1777645500000,
          25167.675781
        ],
        [
          1777645800000,
          25092.064453
        ],
        [
          1777646100000,
          25086.591797
        ],
        [
          1777646400000,
          25116.888672
        ],
        [
          1777646700000,
          25134.001953
        ],
        [
          1777647000000,
          25133.125
        ],
        [
          1777647300000,
          25130.630859
        ],
        [
          1777647600000,
          25108.900391
        ],
        [
          1777647900000,
          25107.892578
        ],
        [
          1777648200000,
          25139.220703
        ],
        [
          1777648500000,
          25148.681641
        ],
        [
          1777648800000,
          25158.347656
        ],
        [
          1777649100000,
          25164.279297
        ],
        [
          1777649400000,
          25167.566406
        ],
        [
          1777649700000,
          25197.925781
        ],
        [
          1777650000000,
          25200.658203
        ],
        [
          1777650300000,
          25218.355469
        ],
        [
          1777650600000,
          25179.199219
        ],
        [
          1777650900000,
          25185.853516
        ],
        [
          1777651200000,
          25182.644531
        ],
        [
          1777651500000,
          25141.099609
        ],
        [
          1777651800000,
          25146.367188
        ],
        [
          1777652100000,
          25167.072266
        ],
        [
          1777652400000,
          25151.697266
        ],
        [
          1777652700000,
          25137.884766
        ],
        [
          1777653000000,
          25132.591797
        ],
        [
          1777653300000,
          25141.480469
        ],
        [
          1777653600000,
          25118.902344
        ],
        [
          1777653900000,
          25113.179688
        ],
        [
          1777654200000,
          25137.490234
        ],
        [
          1777654500000,
          25133.181641
        ],
        [
          1777654800000,
          25141.220703
        ],
        [
          1777655100000,
          25143.734375
        ],
        [
          1777655400000,
          25157.904297
        ],
        [
          1777655700000,
          25176.955078
        ],
        [
          1777656000000,
          25179.447266
        ],
        [
          1777656300000,
          25186.455078
        ],
        [
          1777656600000,
          25175.71875
        ],
        [
          1777656900000,
          25174.287109
        ],
        [
          1777657200000,
          25180.757812
        ],
        [
          1777657500000,
          25177.505859
        ],
        [
          1777657800000,
          25176.435547
        ],
        [
          1777658100000,
          25174.408203
        ],
        [
          1777658400000,
          25160.015625
        ],
        [
          1777658700000,
          25167.289062
        ],
        [
          1777659000000,
          25141.570312
        ],
        [
          1777659300000,
          25145.386719
        ],
        [
          1777659600000,
          25159.285156
        ],
        [
          1777659900000,
          25161.439453
        ],
        [
          1777660200000,
          25137.736328
        ],
        [
          1777660500000,
          25126.953125
        ],
        [
          1777660800000,
          25115.130859
        ],
        [
          1777661100000,
          25100.867188
        ],
        [
          1777661400000,
          25101.216797
        ],
        [
          1777661700000,
          25110.396484
        ],
        [
          1777662000000,
          25127.761719
        ],
        [
          1777662300000,
          25139.835938
        ],
        [
          1777662600000,
          25151.960938
        ],
        [
          1777662900000,
          25149.027344
        ],
        [
          1777663200000,
          25156.527344
        ],
        [
          1777663500000,
          25174.601562
        ],
        [
          1777663800000,
          25166.960938
        ],
        [
          1777664100000,
          25161.21875
        ],
        [
          1777664400000,
          25157.013672
        ],
        [
          1777664700000,
          25147.626953
        ],
        [
          1777665000000,
          25122.818359
        ],
        [
          1777665300000,
          25109.980469
        ],
        [
          1777665600000,
          25114.443359
        ]
      ],
      "marketState": "UNKNOWN",
      "marketTime": "2026-05-02 06:15 KST",
      "marketTimestamp": 1777670159
    }
  ],
  "headlines": [
    {
      "title": "그동안 너무 올랐는데…진짜 5월엔 안 팔아도 될까? [마켓무버 : 개장 전 증시 힌트]",
      "source": "v.daum.net",
      "link": "https://news.google.com/rss/articles/CBMiVEFVX3lxTFBvRTVoejFUTDdxdTQ5YjcwYkp5MzFqd2V4UzhWVVlwSEFaMlBRMmxLWUhvZmZlWEdMYnFLTnI1NTROYzloTnpQM282TzNCRUpZT2Z1MA?oc=5",
      "publishedAt": "Sun, 03 May 2026 22:19:58 GMT"
    },
    {
      "title": "출발증시 2부",
      "source": "한국경제TV",
      "link": "https://news.google.com/rss/articles/CBMiowFBVV95cUxPSEs5czFFTDBEaTVpNEF0UElHb1pDcF9qb2NSMjBvVGlTR1RqOVMxd2l2MkEwREc5c1poc1lYbGdQeUpFcWtfX0hJdjNhZURNUDFWTUp4al9FY0Jzd01aMDYyNGVfY3hLaERyMzZvbTFvQkdqOENpcTRNMXhEUWhXM2hTWGhzaXFIMzFPaGxlMG4wTUV5VG14QkJsRUV5cnhkWjF3?oc=5",
      "publishedAt": "Mon, 04 May 2026 02:35:33 GMT"
    },
    {
      "title": "[증시 포인트] 실적 모멘텀 여전히 강력...상승 출발 전망",
      "source": "오피니언뉴스",
      "link": "https://news.google.com/rss/articles/CBMickFVX3lxTFAtSHFRNWUwWmQxTjFSeEdkYTFOak1zODg3b25yWXFaajd3RzhmVUhmWHZfLXNLRkVjLW5jNTlhdWtheXNUVnFEbEtaaDNxRjdxTmJuOGtxN004UV9pcmtNQm9YcEcwa1NUNzM4MVNkNHczUQ?oc=5",
      "publishedAt": "Sun, 03 May 2026 23:31:02 GMT"
    },
    {
      "title": "아시아 증시 상승, 한국 사상 최고치 경신, 홍콩 기술주 강세로 상승",
      "source": "Investing.com 한국어",
      "link": "https://news.google.com/rss/articles/CBMicEFVX3lxTE0zV1FXTVFmSGp6dzZPUW00eF9NdWxrakI3cFM2MjRhcUV4Y3ZaQ3VRaEszdWxrQTExcHZkQUIzOUY3VEo0VFE0dHNuUXZkV0FxelBkOFlYOWdCZUl4d29PY09nTXBJMGVSVkZKdldKWE8?oc=5",
      "publishedAt": "Mon, 04 May 2026 02:06:00 GMT"
    },
    {
      "title": "다가가면 도망가는…내외금리차 축소 기대 꺾이며 원화 압박 |",
      "source": "연합인포맥스",
      "link": "https://news.google.com/rss/articles/CBMidEFVX3lxTE5mWEFyaThiS0FQM1JMTmJOb0Zia2tPZFFLWDF2aHI3U25SN05EanR3YmZSVm9rOVU5TUtQMXFFV1RmM2lXVzZ2Y3ppbUk3dV9ndGpHYUhBVWNiSHljVERPQlNNa3kwSUJ6SzhBNVphWjN3cFc3?oc=5",
      "publishedAt": "Mon, 04 May 2026 00:43:08 GMT"
    },
    {
      "title": "[증시전망대] 7000피 넘보는 韓증시…호실적 타고 상승 이어갈까",
      "source": "dt.co.kr",
      "link": "https://news.google.com/rss/articles/CBMiTkFVX3lxTE94eERXS1FlX0ktTDBpSHBkNWVWUmxibXAtRXlObWN3N3YzRGZheGZhUU9rMG1LVXlwWGpjQUg4anU5cDFEc25IMVV3aFM0dw?oc=5",
      "publishedAt": "Sun, 03 May 2026 21:30:00 GMT"
    },
    {
      "title": "상승 출발하는 국내 증시",
      "source": "뉴시스",
      "link": "https://news.google.com/rss/articles/CBMiYEFVX3lxTE5GV3lLWkNwUTBxcTlxdVBCbWtTOFJJWWk3OXk3YTdZYVh4RGdNanI3QzNLLU5DcjFCN3ViU2I1WmlhTkhsb0NONlhrbDdpN2FacFAxS3I0NzNPUGFPRkk1Yw?oc=5",
      "publishedAt": "Mon, 04 May 2026 00:18:26 GMT"
    },
    {
      "title": "[외신 에스프레소] 미국 증시 36% 장악한 개미들, 월가도 떤다",
      "source": "한국경제",
      "link": "https://news.google.com/rss/articles/CBMiWkFVX3lxTE5vUExER091eWRnaWFuM2taQ3RnV3E3OHFlNWVuUHpRY3FiUUZUWkowQVNkNlIycDl0OXkzRU85UkhvcnJrLWNuMHFvTThqYmRlY2YxQ2Fhcm1IZw?oc=5",
      "publishedAt": "Sun, 03 May 2026 22:55:27 GMT"
    }
  ],
  "summary": {
    "signal": {
      "label": "Risk-On",
      "tone": "up",
      "message": "주식과 위험자산 강세가 우세합니다."
    },
    "overview": [
      "국내장은 KOSPI 상승, KOSDAQ 상승 흐름입니다.",
      "해외는 S&P 500 +0.29%, NASDAQ +0.89%로 확인됩니다.",
      "매크로 변수는 USD/KRW -0.14%, 미 10년물 -0.27%입니다."
    ],
    "checkpoints": [
      "KOSPI +4.12% 상승",
      "KOSDAQ +1.88% 상승",
      "미국 증시 상승 / 나스닥 +0.89%",
      "원달러 -0.14% (-2.00)",
      "미 10년물 -0.012p (-0.27%)"
    ],
    "leaders": [
      {
        "label": "KOSPI",
        "changePercent": 4.119,
        "direction": "상승"
      },
      {
        "label": "KOSDAQ",
        "changePercent": 1.8795,
        "direction": "상승"
      },
      {
        "label": "Bitcoin",
        "changePercent": 1.8323,
        "direction": "상승"
      }
    ],
    "laggards": [
      {
        "label": "Gold",
        "changePercent": -0.4909,
        "direction": "하락"
      },
      {
        "label": "DOW",
        "changePercent": -0.3078,
        "direction": "하락"
      },
      {
        "label": "USD/KRW",
        "changePercent": -0.1358,
        "direction": "보합"
      }
    ]
  },
  "errors": []
}