{
  "updatedAt": "2026-03-24T14:16:22.455881+09:00",
  "updatedLabel": "2026-03-24 14:16:22 KST",
  "groups": [
    "국내 지수",
    "해외 지수",
    "거시 자산"
  ],
  "cards": [
    {
      "id": "kospi",
      "label": "KOSPI",
      "symbol": "^KS11",
      "group": "국내 지수",
      "kind": "equity",
      "decimals": 2,
      "price": 5547.45,
      "previousClose": 5405.75,
      "change": 141.7,
      "changePercent": 2.6213,
      "tone": "up",
      "direction": "상승",
      "series": [
        [
          1774310400000,
          5592.129883
        ],
        [
          1774310700000,
          5585.47998
        ],
        [
          1774311000000,
          5597.779785
        ],
        [
          1774311300000,
          5583.790039
        ],
        [
          1774311600000,
          5602.810059
        ],
        [
          1774311900000,
          5596.040039
        ],
        [
          1774312200000,
          5579.160156
        ],
        [
          1774312500000,
          5526.410156
        ],
        [
          1774312800000,
          5535.859863
        ],
        [
          1774313100000,
          5530.100098
        ],
        [
          1774313400000,
          5529.529785
        ],
        [
          1774313700000,
          5514.350098
        ],
        [
          1774314000000,
          5494.799805
        ],
        [
          1774314300000,
          5490.740234
        ],
        [
          1774314600000,
          5481.910156
        ],
        [
          1774314900000,
          5458.620117
        ],
        [
          1774315200000,
          5497.859863
        ],
        [
          1774315500000,
          5509.22998
        ],
        [
          1774315800000,
          5488.649902
        ],
        [
          1774316100000,
          5460.189941
        ],
        [
          1774316400000,
          5437.609863
        ],
        [
          1774316700000,
          5420.370117
        ],
        [
          1774317000000,
          5405.339844
        ],
        [
          1774317300000,
          5412.959961
        ],
        [
          1774317600000,
          5441.660156
        ],
        [
          1774317900000,
          5436.879883
        ],
        [
          1774318200000,
          5420.879883
        ],
        [
          1774318500000,
          5449.330078
        ],
        [
          1774318800000,
          5470.339844
        ],
        [
          1774319100000,
          5470.259766
        ],
        [
          1774319400000,
          5473.640137
        ],
        [
          1774319700000,
          5479.839844
        ],
        [
          1774320000000,
          5494.899902
        ],
        [
          1774320300000,
          5498.640137
        ],
        [
          1774320600000,
          5480.390137
        ],
        [
          1774320900000,
          5474.47998
        ],
        [
          1774321200000,
          5483.22998
        ],
        [
          1774321500000,
          5486.720215
        ],
        [
          1774321800000,
          5496.220215
        ],
        [
          1774322100000,
          5504.060059
        ],
        [
          1774322400000,
          5523.609863
        ],
        [
          1774322700000,
          5531.589844
        ],
        [
          1774323000000,
          5508.47998
        ],
        [
          1774323300000,
          5522.509766
        ],
        [
          1774323600000,
          5532.810059
        ],
        [
          1774323900000,
          5527.189941
        ],
        [
          1774324200000,
          5519.720215
        ],
        [
          1774324500000,
          5529.279785
        ],
        [
          1774324800000,
          5540.709961
        ],
        [
          1774325100000,
          5536.549805
        ],
        [
          1774325400000,
          5536.790039
        ],
        [
          1774325700000,
          5527.540039
        ],
        [
          1774326000000,
          5519.069824
        ],
        [
          1774326300000,
          5516.410156
        ],
        [
          1774326600000,
          5521.629883
        ],
        [
          1774326900000,
          5527.740234
        ],
        [
          1774327200000,
          5521.540039
        ],
        [
          1774327500000,
          5529.859863
        ],
        [
          1774327800000,
          5548.450195
        ],
        [
          1774328100000,
          5550.459961
        ],
        [
          1774328180000,
          5547.450195
        ]
      ],
      "marketState": "UNKNOWN",
      "marketTime": "2026-03-24 13:56 KST",
      "marketTimestamp": 1774328180
    },
    {
      "id": "kosdaq",
      "label": "KOSDAQ",
      "symbol": "^KQ11",
      "group": "국내 지수",
      "kind": "equity",
      "decimals": 2,
      "price": 1119.56,
      "previousClose": 1161.52,
      "change": -41.96,
      "changePercent": -3.6125,
      "tone": "down",
      "direction": "하락",
      "series": [
        [
          1774310400000,
          1131.569946
        ],
        [
          1774310700000,
          1132.780029
        ],
        [
          1774311000000,
          1133.569946
        ],
        [
          1774311300000,
          1130.040039
        ],
        [
          1774311600000,
          1133.290039
        ],
        [
          1774311900000,
          1132.410034
        ],
        [
          1774312200000,
          1131.560059
        ],
        [
          1774312500000,
          1124.5
        ],
        [
          1774312800000,
          1125.920044
        ],
        [
          1774313100000,
          1125.25
        ],
        [
          1774313400000,
          1124.130005
        ],
        [
          1774313700000,
          1120.589966
        ],
        [
          1774314000000,
          1115.969971
        ],
        [
          1774314300000,
          1114.469971
        ],
        [
          1774314600000,
          1113.97998
        ],
        [
          1774314900000,
          1108.560059
        ],
        [
          1774315200000,
          1117.400024
        ],
        [
          1774315500000,
          1120.329956
        ],
        [
          1774315800000,
          1116.51001
        ],
        [
          1774316100000,
          1110.219971
        ],
        [
          1774316400000,
          1105.459961
        ],
        [
          1774316700000,
          1101.300049
        ],
        [
          1774317000000,
          1098.699951
        ],
        [
          1774317300000,
          1097.160034
        ],
        [
          1774317600000,
          1105.040039
        ],
        [
          1774317900000,
          1103.98999
        ],
        [
          1774318200000,
          1099.140015
        ],
        [
          1774318500000,
          1104.119995
        ],
        [
          1774318800000,
          1108.530029
        ],
        [
          1774319100000,
          1108.709961
        ],
        [
          1774319400000,
          1109.560059
        ],
        [
          1774319700000,
          1110.5
        ],
        [
          1774320000000,
          1110.969971
        ],
        [
          1774320300000,
          1111.880005
        ],
        [
          1774320600000,
          1108.459961
        ],
        [
          1774320900000,
          1107.469971
        ],
        [
          1774321200000,
          1106.829956
        ],
        [
          1774321500000,
          1107.530029
        ],
        [
          1774321800000,
          1108.569946
        ],
        [
          1774322100000,
          1110.199951
        ],
        [
          1774322400000,
          1112.27002
        ],
        [
          1774322700000,
          1113.089966
        ],
        [
          1774323000000,
          1110.410034
        ],
        [
          1774323300000,
          1111.079956
        ],
        [
          1774323600000,
          1112.27002
        ],
        [
          1774323900000,
          1112.109985
        ],
        [
          1774324200000,
          1111.540039
        ],
        [
          1774324500000,
          1113.5
        ],
        [
          1774324800000,
          1116.25
        ],
        [
          1774325100000,
          1116.680054
        ],
        [
          1774325400000,
          1117.219971
        ],
        [
          1774325700000,
          1115.420044
        ],
        [
          1774326000000,
          1114.25
        ],
        [
          1774326300000,
          1113.449951
        ],
        [
          1774326600000,
          1113.680054
        ],
        [
          1774326900000,
          1116.069946
        ],
        [
          1774327200000,
          1115.699951
        ],
        [
          1774327500000,
          1116.920044
        ],
        [
          1774327800000,
          1119.359985
        ],
        [
          1774328100000,
          1119.670044
        ],
        [
          1774328180000,
          1119.560059
        ]
      ],
      "marketState": "UNKNOWN",
      "marketTime": "2026-03-24 13:56 KST",
      "marketTimestamp": 1774328180
    },
    {
      "id": "sp500",
      "label": "S&P 500",
      "symbol": "^GSPC",
      "group": "해외 지수",
      "kind": "equity",
      "decimals": 2,
      "price": 6581.0,
      "previousClose": 6506.48,
      "change": 74.52,
      "changePercent": 1.1453,
      "tone": "up",
      "direction": "상승",
      "series": [
        [
          1774272600000,
          6592.169922
        ],
        [
          1774272900000,
          6606.470215
        ],
        [
          1774273200000,
          6606.549805
        ],
        [
          1774273500000,
          6614.47998
        ],
        [
          1774273800000,
          6622.700195
        ],
        [
          1774274100000,
          6627.580078
        ],
        [
          1774274400000,
          6618.609863
        ],
        [
          1774274700000,
          6622.259766
        ],
        [
          1774275000000,
          6627.149902
        ],
        [
          1774275300000,
          6637.200195
        ],
        [
          1774275600000,
          6645.0
        ],
        [
          1774275900000,
          6636.069824
        ],
        [
          1774276200000,
          6634.189941
        ],
        [
          1774276500000,
          6630.740234
        ],
        [
          1774276800000,
          6629.77002
        ],
        [
          1774277100000,
          6638.720215
        ],
        [
          1774277400000,
          6634.060059
        ],
        [
          1774277700000,
          6636.419922
        ],
        [
          1774278000000,
          6650.0
        ],
        [
          1774278300000,
          6648.720215
        ],
        [
          1774278600000,
          6646.089844
        ],
        [
          1774278900000,
          6640.470215
        ],
        [
          1774279200000,
          6646.189941
        ],
        [
          1774279500000,
          6635.160156
        ],
        [
          1774279800000,
          6632.350098
        ],
        [
          1774280100000,
          6619.310059
        ],
        [
          1774280400000,
          6618.890137
        ],
        [
          1774280700000,
          6612.72998
        ],
        [
          1774281000000,
          6599.410156
        ],
        [
          1774281300000,
          6585.689941
        ],
        [
          1774281600000,
          6590.52002
        ],
        [
          1774281900000,
          6596.049805
        ],
        [
          1774282200000,
          6596.740234
        ],
        [
          1774282500000,
          6586.330078
        ],
        [
          1774282800000,
          6582.740234
        ],
        [
          1774283100000,
          6566.52002
        ],
        [
          1774283400000,
          6580.52002
        ],
        [
          1774283700000,
          6580.609863
        ],
        [
          1774284000000,
          6586.310059
        ],
        [
          1774284300000,
          6588.959961
        ],
        [
          1774284600000,
          6583.810059
        ],
        [
          1774284900000,
          6581.509766
        ],
        [
          1774285200000,
          6576.689941
        ],
        [
          1774285500000,
          6586.810059
        ],
        [
          1774285800000,
          6579.799805
        ],
        [
          1774286100000,
          6578.129883
        ],
        [
          1774286400000,
          6573.669922
        ],
        [
          1774286700000,
          6579.399902
        ],
        [
          1774287000000,
          6596.879883
        ],
        [
          1774287300000,
          6603.819824
        ],
        [
          1774287600000,
          6594.330078
        ],
        [
          1774287900000,
          6593.410156
        ],
        [
          1774288200000,
          6600.240234
        ],
        [
          1774288500000,
          6606.970215
        ],
        [
          1774288800000,
          6607.129883
        ],
        [
          1774289100000,
          6599.970215
        ],
        [
          1774289400000,
          6603.310059
        ],
        [
          1774289700000,
          6600.509766
        ],
        [
          1774290000000,
          6601.350098
        ],
        [
          1774290300000,
          6600.029785
        ],
        [
          1774290600000,
          6614.370117
        ],
        [
          1774290900000,
          6615.5
        ],
        [
          1774291200000,
          6613.600098
        ],
        [
          1774291500000,
          6617.47998
        ],
        [
          1774291800000,
          6614.419922
        ],
        [
          1774292100000,
          6615.600098
        ],
        [
          1774292400000,
          6611.850098
        ],
        [
          1774292700000,
          6613.390137
        ],
        [
          1774293000000,
          6607.430176
        ],
        [
          1774293300000,
          6604.419922
        ],
        [
          1774293600000,
          6601.509766
        ],
        [
          1774293900000,
          6599.439941
        ],
        [
          1774294200000,
          6599.129883
        ],
        [
          1774294500000,
          6601.799805
        ],
        [
          1774294800000,
          6604.580078
        ],
        [
          1774295100000,
          6603.660156
        ],
        [
          1774295400000,
          6592.779785
        ],
        [
          1774295700000,
          6581.759766
        ],
        [
          1774296000000,
          6581.0
        ]
      ],
      "marketState": "UNKNOWN",
      "marketTime": "2026-03-24 06:11 KST",
      "marketTimestamp": 1774300298
    },
    {
      "id": "nasdaq",
      "label": "NASDAQ",
      "symbol": "^IXIC",
      "group": "해외 지수",
      "kind": "equity",
      "decimals": 2,
      "price": 21946.76,
      "previousClose": 21647.611,
      "change": 299.149,
      "changePercent": 1.3819,
      "tone": "up",
      "direction": "상승",
      "series": [
        [
          1774272600000,
          21984.035156
        ],
        [
          1774272900000,
          22039.744141
        ],
        [
          1774273200000,
          22023.835938
        ],
        [
          1774273500000,
          22070.417969
        ],
        [
          1774273800000,
          22096.423828
        ],
        [
          1774274100000,
          22100.785156
        ],
        [
          1774274400000,
          22067.890625
        ],
        [
          1774274700000,
          22067.585938
        ],
        [
          1774275000000,
          22103.400391
        ],
        [
          1774275300000,
          22142.1875
        ],
        [
          1774275600000,
          22169.068359
        ],
        [
          1774275900000,
          22138.234375
        ],
        [
          1774276200000,
          22129.634766
        ],
        [
          1774276500000,
          22116.138672
        ],
        [
          1774276800000,
          22102.447266
        ],
        [
          1774277100000,
          22129.402344
        ],
        [
          1774277400000,
          22109.908203
        ],
        [
          1774277700000,
          22122.544922
        ],
        [
          1774278000000,
          22178.126953
        ],
        [
          1774278300000,
          22178.703125
        ],
        [
          1774278600000,
          22172.121094
        ],
        [
          1774278900000,
          22144.279297
        ],
        [
          1774279200000,
          22168.017578
        ],
        [
          1774279500000,
          22129.396484
        ],
        [
          1774279800000,
          22119.234375
        ],
        [
          1774280100000,
          22067.296875
        ],
        [
          1774280400000,
          22062.984375
        ],
        [
          1774280700000,
          22037.458984
        ],
        [
          1774281000000,
          21977.945312
        ],
        [
          1774281300000,
          21926.5
        ],
        [
          1774281600000,
          21938.835938
        ],
        [
          1774281900000,
          21980.447266
        ],
        [
          1774282200000,
          21983.474609
        ],
        [
          1774282500000,
          21950.958984
        ],
        [
          1774282800000,
          21929.484375
        ],
        [
          1774283100000,
          21868.066406
        ],
        [
          1774283400000,
          21914.345703
        ],
        [
          1774283700000,
          21915.005859
        ],
        [
          1774284000000,
          21936.580078
        ],
        [
          1774284300000,
          21950.492188
        ],
        [
          1774284600000,
          21927.96875
        ],
        [
          1774284900000,
          21917.886719
        ],
        [
          1774285200000,
          21901.345703
        ],
        [
          1774285500000,
          21930.269531
        ],
        [
          1774285800000,
          21905.546875
        ],
        [
          1774286100000,
          21897.976562
        ],
        [
          1774286400000,
          21880.367188
        ],
        [
          1774286700000,
          21904.855469
        ],
        [
          1774287000000,
          21959.587891
        ],
        [
          1774287300000,
          21985.101562
        ],
        [
          1774287600000,
          21954.513672
        ],
        [
          1774287900000,
          21947.919922
        ],
        [
          1774288200000,
          21972.75
        ],
        [
          1774288500000,
          22000.019531
        ],
        [
          1774288800000,
          22009.986328
        ],
        [
          1774289100000,
          21981.591797
        ],
        [
          1774289400000,
          21989.259766
        ],
        [
          1774289700000,
          21978.222656
        ],
        [
          1774290000000,
          21982.414062
        ],
        [
          1774290300000,
          21977.605469
        ],
        [
          1774290600000,
          22032.466797
        ],
        [
          1774290900000,
          22033.359375
        ],
        [
          1774291200000,
          22032.175781
        ],
        [
          1774291500000,
          22049.150391
        ],
        [
          1774291800000,
          22040.320312
        ],
        [
          1774292100000,
          22046.792969
        ],
        [
          1774292400000,
          22032.462891
        ],
        [
          1774292700000,
          22042.207031
        ],
        [
          1774293000000,
          22023.652344
        ],
        [
          1774293300000,
          22016.353516
        ],
        [
          1774293600000,
          22012.511719
        ],
        [
          1774293900000,
          22007.005859
        ],
        [
          1774294200000,
          22008.197266
        ],
        [
          1774294500000,
          22018.089844
        ],
        [
          1774294800000,
          22028.5
        ],
        [
          1774295100000,
          22026.205078
        ],
        [
          1774295400000,
          21982.537109
        ],
        [
          1774295700000,
          21956.785156
        ],
        [
          1774296000000,
          21946.759766
        ]
      ],
      "marketState": "UNKNOWN",
      "marketTime": "2026-03-24 06:15 KST",
      "marketTimestamp": 1774300559
    },
    {
      "id": "dow",
      "label": "DOW",
      "symbol": "^DJI",
      "group": "해외 지수",
      "kind": "equity",
      "decimals": 2,
      "price": 46208.47,
      "previousClose": 45577.47,
      "change": 631.0,
      "changePercent": 1.3845,
      "tone": "up",
      "direction": "상승",
      "series": [
        [
          1774272600000,
          46235.851562
        ],
        [
          1774272900000,
          46349.699219
        ],
        [
          1774273200000,
          46394.328125
        ],
        [
          1774273500000,
          46396.050781
        ],
        [
          1774273800000,
          46460.941406
        ],
        [
          1774274100000,
          46498.019531
        ],
        [
          1774274400000,
          46429.488281
        ],
        [
          1774274700000,
          46479.941406
        ],
        [
          1774275000000,
          46477.421875
        ],
        [
          1774275300000,
          46552.75
        ],
        [
          1774275600000,
          46586.988281
        ],
        [
          1774275900000,
          46514.339844
        ],
        [
          1774276200000,
          46496.078125
        ],
        [
          1774276500000,
          46476.21875
        ],
        [
          1774276800000,
          46485.949219
        ],
        [
          1774277100000,
          46573.46875
        ],
        [
          1774277400000,
          46571.230469
        ],
        [
          1774277700000,
          46581.671875
        ],
        [
          1774278000000,
          46692.878906
        ],
        [
          1774278300000,
          46683.730469
        ],
        [
          1774278600000,
          46676.039062
        ],
        [
          1774278900000,
          46615.660156
        ],
        [
          1774279200000,
          46682.980469
        ],
        [
          1774279500000,
          46595.949219
        ],
        [
          1774279800000,
          46576.300781
        ],
        [
          1774280100000,
          46509.710938
        ],
        [
          1774280400000,
          46492.359375
        ],
        [
          1774280700000,
          46464.601562
        ],
        [
          1774281000000,
          46355.949219
        ],
        [
          1774281300000,
          46271.601562
        ],
        [
          1774281600000,
          46297.988281
        ],
        [
          1774281900000,
          46294.320312
        ],
        [
          1774282200000,
          46294.660156
        ],
        [
          1774282500000,
          46234.449219
        ],
        [
          1774282800000,
          46208.921875
        ],
        [
          1774283100000,
          46114.691406
        ],
        [
          1774283400000,
          46206.578125
        ],
        [
          1774283700000,
          46208.820312
        ],
        [
          1774284000000,
          46237.609375
        ],
        [
          1774284300000,
          46242.710938
        ],
        [
          1774284600000,
          46227.628906
        ],
        [
          1774284900000,
          46217.601562
        ],
        [
          1774285200000,
          46173.730469
        ],
        [
          1774285500000,
          46257.429688
        ],
        [
          1774285800000,
          46193.121094
        ],
        [
          1774286100000,
          46184.761719
        ],
        [
          1774286400000,
          46177.761719
        ],
        [
          1774286700000,
          46219.191406
        ],
        [
          1774287000000,
          46346.191406
        ],
        [
          1774287300000,
          46397.78125
        ],
        [
          1774287600000,
          46320.058594
        ],
        [
          1774287900000,
          46311.648438
        ],
        [
          1774288200000,
          46371.371094
        ],
        [
          1774288500000,
          46419.671875
        ],
        [
          1774288800000,
          46410.640625
        ],
        [
          1774289100000,
          46361.601562
        ],
        [
          1774289400000,
          46382.660156
        ],
        [
          1774289700000,
          46356.589844
        ],
        [
          1774290000000,
          46357.171875
        ],
        [
          1774290300000,
          46352.800781
        ],
        [
          1774290600000,
          46453.308594
        ],
        [
          1774290900000,
          46469.390625
        ],
        [
          1774291200000,
          46449.691406
        ],
        [
          1774291500000,
          46475.730469
        ],
        [
          1774291800000,
          46448.921875
        ],
        [
          1774292100000,
          46447.050781
        ],
        [
          1774292400000,
          46424.441406
        ],
        [
          1774292700000,
          46434.109375
        ],
        [
          1774293000000,
          46397.890625
        ],
        [
          1774293300000,
          46365.871094
        ],
        [
          1774293600000,
          46346.289062
        ],
        [
          1774293900000,
          46321.378906
        ],
        [
          1774294200000,
          46324.039062
        ],
        [
          1774294500000,
          46336.339844
        ],
        [
          1774294800000,
          46359.679688
        ],
        [
          1774295100000,
          46343.449219
        ],
        [
          1774295400000,
          46282.039062
        ],
        [
          1774295700000,
          46214.320312
        ],
        [
          1774296000000,
          46208.46875
        ]
      ],
      "marketState": "UNKNOWN",
      "marketTime": "2026-03-24 06:11 KST",
      "marketTimestamp": 1774300313
    },
    {
      "id": "usdkrw",
      "label": "USD/KRW",
      "symbol": "KRW=X",
      "group": "거시 자산",
      "kind": "fx",
      "decimals": 2,
      "price": 1499.68,
      "previousClose": 1486.3,
      "change": 13.38,
      "changePercent": 0.9002,
      "tone": "up",
      "direction": "상승",
      "series": [
        [
          1774310400000,
          1494.780029
        ],
        [
          1774310700000,
          1493.369995
        ],
        [
          1774311000000,
          1495.680054
        ],
        [
          1774311300000,
          1495.880005
        ],
        [
          1774311600000,
          1495.280029
        ],
        [
          1774311900000,
          1495.150024
        ],
        [
          1774312200000,
          1496.180054
        ],
        [
          1774312500000,
          1498.680054
        ],
        [
          1774312800000,
          1498.680054
        ],
        [
          1774313100000,
          1499.079956
        ],
        [
          1774313400000,
          1497.119995
        ],
        [
          1774313700000,
          1498.280029
        ],
        [
          1774314000000,
          1498.030029
        ],
        [
          1774314300000,
          1498.880005
        ],
        [
          1774314600000,
          1498.380005
        ],
        [
          1774314900000,
          1498.380005
        ],
        [
          1774315200000,
          1497.880005
        ],
        [
          1774315500000,
          1498.880005
        ],
        [
          1774315800000,
          1499.579956
        ],
        [
          1774316100000,
          1499.680054
        ],
        [
          1774316400000,
          1499.880005
        ],
        [
          1774316700000,
          1500.579956
        ],
        [
          1774317000000,
          1500.030029
        ],
        [
          1774317300000,
          1500.380005
        ],
        [
          1774317600000,
          1498.97998
        ],
        [
          1774317900000,
          1499.180054
        ],
        [
          1774318200000,
          1500.280029
        ],
        [
          1774318500000,
          1498.780029
        ],
        [
          1774318800000,
          1498.180054
        ],
        [
          1774319100000,
          1498.079956
        ],
        [
          1774319400000,
          1497.73999
        ],
        [
          1774319700000,
          1499.079956
        ],
        [
          1774320000000,
          1498.380005
        ],
        [
          1774320300000,
          1499.47998
        ],
        [
          1774320600000,
          1501.280029
        ],
        [
          1774320900000,
          1502.579956
        ],
        [
          1774321200000,
          1502.579956
        ],
        [
          1774321500000,
          1501.280029
        ],
        [
          1774321800000,
          1500.959961
        ],
        [
          1774322100000,
          1499.76001
        ],
        [
          1774322400000,
          1500.280029
        ],
        [
          1774322700000,
          1500.23999
        ],
        [
          1774323000000,
          1500.680054
        ],
        [
          1774323300000,
          1499.97998
        ],
        [
          1774323600000,
          1500.050049
        ],
        [
          1774323900000,
          1500.079956
        ],
        [
          1774324200000,
          1499.780029
        ],
        [
          1774324500000,
          1500.420044
        ],
        [
          1774324800000,
          1500.380005
        ],
        [
          1774325100000,
          1500.25
        ],
        [
          1774325400000,
          1500.670044
        ],
        [
          1774325700000,
          1500.689941
        ],
        [
          1774326000000,
          1500.579956
        ],
        [
          1774326300000,
          1500.680054
        ],
        [
          1774326600000,
          1500.97998
        ],
        [
          1774326900000,
          1500.47998
        ],
        [
          1774327200000,
          1501.079956
        ],
        [
          1774327500000,
          1500.130005
        ],
        [
          1774327800000,
          1500.579956
        ],
        [
          1774328100000,
          1500.680054
        ],
        [
          1774328400000,
          1500.400024
        ],
        [
          1774328700000,
          1500.680054
        ],
        [
          1774329000000,
          1500.26001
        ],
        [
          1774329300000,
          1499.97998
        ],
        [
          1774329379000,
          1499.680054
        ]
      ],
      "marketState": "UNKNOWN",
      "marketTime": "2026-03-24 14:16 KST",
      "marketTimestamp": 1774329379
    },
    {
      "id": "us10y",
      "label": "미국 10Y",
      "symbol": "^TNX",
      "group": "거시 자산",
      "kind": "yield",
      "decimals": 3,
      "price": 4.334,
      "previousClose": 4.391,
      "change": -0.057,
      "changePercent": -1.2981,
      "tone": "down",
      "direction": "하락",
      "series": [
        [
          1774268400000,
          4.384
        ],
        [
          1774268700000,
          4.382
        ],
        [
          1774269000000,
          4.382
        ],
        [
          1774269300000,
          4.39
        ],
        [
          1774269600000,
          4.36
        ],
        [
          1774269900000,
          4.358
        ],
        [
          1774270200000,
          4.36
        ],
        [
          1774270500000,
          4.358
        ],
        [
          1774270800000,
          4.36
        ],
        [
          1774271100000,
          4.362
        ],
        [
          1774271400000,
          4.366
        ],
        [
          1774271700000,
          4.368
        ],
        [
          1774272000000,
          4.37
        ],
        [
          1774272300000,
          4.372
        ],
        [
          1774272600000,
          4.386
        ],
        [
          1774272900000,
          4.368
        ],
        [
          1774273200000,
          4.358
        ],
        [
          1774273500000,
          4.346
        ],
        [
          1774273800000,
          4.348
        ],
        [
          1774274100000,
          4.348
        ],
        [
          1774274400000,
          4.354
        ],
        [
          1774274700000,
          4.352
        ],
        [
          1774275000000,
          4.35
        ],
        [
          1774275300000,
          4.334
        ],
        [
          1774275600000,
          4.33
        ],
        [
          1774275900000,
          4.336
        ],
        [
          1774276200000,
          4.338
        ],
        [
          1774276500000,
          4.338
        ],
        [
          1774276800000,
          4.346
        ],
        [
          1774277100000,
          4.34
        ],
        [
          1774277400000,
          4.34
        ],
        [
          1774277700000,
          4.336
        ],
        [
          1774278000000,
          4.318
        ],
        [
          1774278300000,
          4.314
        ],
        [
          1774278600000,
          4.316
        ],
        [
          1774278900000,
          4.324
        ],
        [
          1774279200000,
          4.32
        ],
        [
          1774279500000,
          4.332
        ],
        [
          1774279800000,
          4.332
        ],
        [
          1774280100000,
          4.348
        ],
        [
          1774280400000,
          4.346
        ],
        [
          1774280700000,
          4.348
        ],
        [
          1774281000000,
          4.364
        ],
        [
          1774281300000,
          4.368
        ],
        [
          1774281600000,
          4.37
        ],
        [
          1774281900000,
          4.364
        ],
        [
          1774282200000,
          4.368
        ],
        [
          1774282500000,
          4.372
        ],
        [
          1774282800000,
          4.374
        ],
        [
          1774283100000,
          4.384
        ],
        [
          1774283400000,
          4.37
        ],
        [
          1774283700000,
          4.374
        ],
        [
          1774284000000,
          4.368
        ],
        [
          1774284300000,
          4.364
        ],
        [
          1774284600000,
          4.368
        ],
        [
          1774284900000,
          4.366
        ],
        [
          1774285200000,
          4.368
        ],
        [
          1774285500000,
          4.358
        ],
        [
          1774285800000,
          4.36
        ],
        [
          1774286100000,
          4.36
        ],
        [
          1774286400000,
          4.354
        ],
        [
          1774286700000,
          4.348
        ],
        [
          1774287000000,
          4.348
        ],
        [
          1774287300000,
          4.342
        ],
        [
          1774287600000,
          4.346
        ],
        [
          1774287900000,
          4.35
        ],
        [
          1774288200000,
          4.34
        ],
        [
          1774288500000,
          4.338
        ],
        [
          1774288800000,
          4.338
        ],
        [
          1774289100000,
          4.34
        ],
        [
          1774289400000,
          4.336
        ],
        [
          1774289700000,
          4.338
        ],
        [
          1774290000000,
          4.336
        ],
        [
          1774290300000,
          4.336
        ],
        [
          1774290600000,
          4.324
        ],
        [
          1774290900000,
          4.324
        ],
        [
          1774291200000,
          4.332
        ],
        [
          1774291500000,
          4.33
        ],
        [
          1774291800000,
          4.33
        ],
        [
          1774292100000,
          4.334
        ]
      ],
      "marketState": "UNKNOWN",
      "marketTime": "2026-03-24 03:59 KST",
      "marketTimestamp": 1774292391
    },
    {
      "id": "wti",
      "label": "WTI",
      "symbol": "CL=F",
      "group": "거시 자산",
      "kind": "commodity",
      "decimals": 2,
      "price": 91.83,
      "previousClose": 88.13,
      "change": 3.7,
      "changePercent": 4.1983,
      "tone": "up",
      "direction": "상승",
      "series": [
        [
          1774324800000,
          91.830002
        ],
        [
          1774325100000,
          91.849998
        ],
        [
          1774325400000,
          91.900002
        ],
        [
          1774325700000,
          91.940002
        ],
        [
          1774326000000,
          91.879997
        ],
        [
          1774326300000,
          91.800003
        ],
        [
          1774326600000,
          91.809998
        ],
        [
          1774326900000,
          91.68
        ],
        [
          1774327200000,
          91.699997
        ],
        [
          1774327500000,
          91.610001
        ],
        [
          1774327800000,
          91.529999
        ],
        [
          1774328100000,
          91.519997
        ],
        [
          1774328400000,
          91.660004
        ],
        [
          1774328700000,
          91.779999
        ],
        [
          1774328776000,
          91.830002
        ]
      ],
      "marketState": "UNKNOWN",
      "marketTime": "2026-03-24 14:06 KST",
      "marketTimestamp": 1774328776
    },
    {
      "id": "gold",
      "label": "Gold",
      "symbol": "GC=F",
      "group": "거시 자산",
      "kind": "commodity",
      "decimals": 2,
      "price": 4321.9,
      "previousClose": 4407.3,
      "change": -85.4,
      "changePercent": -1.9377,
      "tone": "down",
      "direction": "하락",
      "series": [
        [
          1774324800000,
          4352.700195
        ],
        [
          1774325100000,
          4352.600098
        ],
        [
          1774325400000,
          4351.0
        ],
        [
          1774325700000,
          4330.600098
        ],
        [
          1774326000000,
          4332.700195
        ],
        [
          1774326300000,
          4339.600098
        ],
        [
          1774326600000,
          4343.0
        ],
        [
          1774326900000,
          4343.799805
        ],
        [
          1774327200000,
          4341.799805
        ],
        [
          1774327500000,
          4346.399902
        ],
        [
          1774327800000,
          4348.700195
        ],
        [
          1774328100000,
          4334.0
        ],
        [
          1774328400000,
          4328.700195
        ],
        [
          1774328700000,
          4326.200195
        ],
        [
          1774328782000,
          4321.899902
        ]
      ],
      "marketState": "UNKNOWN",
      "marketTime": "2026-03-24 14:06 KST",
      "marketTimestamp": 1774328782
    },
    {
      "id": "bitcoin",
      "label": "Bitcoin",
      "symbol": "BTC-USD",
      "group": "거시 자산",
      "kind": "crypto",
      "decimals": 0,
      "price": 70201.8,
      "previousClose": 70898.664,
      "change": -696.864,
      "changePercent": -0.9829,
      "tone": "down",
      "direction": "하락",
      "series": [
        [
          1774310400000,
          70920.460938
        ],
        [
          1774310700000,
          70917.3125
        ],
        [
          1774311000000,
          70794.84375
        ],
        [
          1774311300000,
          70668.046875
        ],
        [
          1774311600000,
          70740.695312
        ],
        [
          1774311900000,
          70700.398438
        ],
        [
          1774312200000,
          70576.351562
        ],
        [
          1774312500000,
          70591.125
        ],
        [
          1774312800000,
          70641.0
        ],
        [
          1774313100000,
          70691.742188
        ],
        [
          1774313400000,
          70789.835938
        ],
        [
          1774313700000,
          70694.296875
        ],
        [
          1774314000000,
          70600.3125
        ],
        [
          1774314300000,
          70629.765625
        ],
        [
          1774314600000,
          70537.523438
        ],
        [
          1774314900000,
          70576.898438
        ],
        [
          1774315200000,
          70758.585938
        ],
        [
          1774315500000,
          70832.515625
        ],
        [
          1774315800000,
          70725.492188
        ],
        [
          1774316100000,
          70636.226562
        ],
        [
          1774316400000,
          70415.257812
        ],
        [
          1774316700000,
          70470.828125
        ],
        [
          1774317000000,
          70552.335938
        ],
        [
          1774317300000,
          70505.296875
        ],
        [
          1774317600000,
          70656.46875
        ],
        [
          1774317900000,
          70524.804688
        ],
        [
          1774318200000,
          70495.257812
        ],
        [
          1774318500000,
          70427.140625
        ],
        [
          1774318800000,
          70599.0
        ],
        [
          1774319100000,
          70498.226562
        ],
        [
          1774319400000,
          70529.304688
        ],
        [
          1774319700000,
          70536.171875
        ],
        [
          1774320000000,
          70514.835938
        ],
        [
          1774320300000,
          70560.554688
        ],
        [
          1774320600000,
          70478.015625
        ],
        [
          1774320900000,
          70444.484375
        ],
        [
          1774321200000,
          70402.664062
        ],
        [
          1774321500000,
          70437.859375
        ],
        [
          1774321800000,
          70467.070312
        ],
        [
          1774322100000,
          70518.609375
        ],
        [
          1774322400000,
          70541.015625
        ],
        [
          1774322700000,
          70554.234375
        ],
        [
          1774323000000,
          70460.984375
        ],
        [
          1774323300000,
          70435.734375
        ],
        [
          1774323600000,
          70470.523438
        ],
        [
          1774323900000,
          70479.125
        ],
        [
          1774324200000,
          70473.921875
        ],
        [
          1774324500000,
          70523.75
        ],
        [
          1774324800000,
          70522.234375
        ],
        [
          1774325100000,
          70659.320312
        ],
        [
          1774325400000,
          70634.648438
        ],
        [
          1774325700000,
          70602.023438
        ],
        [
          1774326000000,
          70591.890625
        ],
        [
          1774326300000,
          70546.109375
        ],
        [
          1774326600000,
          70343.0
        ],
        [
          1774326900000,
          70327.484375
        ],
        [
          1774327200000,
          70327.46875
        ],
        [
          1774327500000,
          70316.148438
        ],
        [
          1774327800000,
          70370.007812
        ],
        [
          1774328100000,
          70376.320312
        ],
        [
          1774328400000,
          70240.4375
        ],
        [
          1774328700000,
          70197.289062
        ],
        [
          1774329000000,
          70184.179688
        ],
        [
          1774329180000,
          70201.796875
        ]
      ],
      "marketState": "UNKNOWN",
      "marketTime": "2026-03-24 14:13 KST",
      "marketTimestamp": 1774329180
    }
  ],
  "mainCharts": [
    {
      "id": "kospi",
      "label": "KOSPI",
      "symbol": "^KS11",
      "group": "국내 지수",
      "kind": "equity",
      "decimals": 2,
      "price": 5547.45,
      "previousClose": 5405.75,
      "change": 141.7,
      "changePercent": 2.6213,
      "tone": "up",
      "direction": "상승",
      "series": [
        [
          1774310400000,
          5592.129883
        ],
        [
          1774310700000,
          5585.47998
        ],
        [
          1774311000000,
          5597.779785
        ],
        [
          1774311300000,
          5583.790039
        ],
        [
          1774311600000,
          5602.810059
        ],
        [
          1774311900000,
          5596.040039
        ],
        [
          1774312200000,
          5579.160156
        ],
        [
          1774312500000,
          5526.410156
        ],
        [
          1774312800000,
          5535.859863
        ],
        [
          1774313100000,
          5530.100098
        ],
        [
          1774313400000,
          5529.529785
        ],
        [
          1774313700000,
          5514.350098
        ],
        [
          1774314000000,
          5494.799805
        ],
        [
          1774314300000,
          5490.740234
        ],
        [
          1774314600000,
          5481.910156
        ],
        [
          1774314900000,
          5458.620117
        ],
        [
          1774315200000,
          5497.859863
        ],
        [
          1774315500000,
          5509.22998
        ],
        [
          1774315800000,
          5488.649902
        ],
        [
          1774316100000,
          5460.189941
        ],
        [
          1774316400000,
          5437.609863
        ],
        [
          1774316700000,
          5420.370117
        ],
        [
          1774317000000,
          5405.339844
        ],
        [
          1774317300000,
          5412.959961
        ],
        [
          1774317600000,
          5441.660156
        ],
        [
          1774317900000,
          5436.879883
        ],
        [
          1774318200000,
          5420.879883
        ],
        [
          1774318500000,
          5449.330078
        ],
        [
          1774318800000,
          5470.339844
        ],
        [
          1774319100000,
          5470.259766
        ],
        [
          1774319400000,
          5473.640137
        ],
        [
          1774319700000,
          5479.839844
        ],
        [
          1774320000000,
          5494.899902
        ],
        [
          1774320300000,
          5498.640137
        ],
        [
          1774320600000,
          5480.390137
        ],
        [
          1774320900000,
          5474.47998
        ],
        [
          1774321200000,
          5483.22998
        ],
        [
          1774321500000,
          5486.720215
        ],
        [
          1774321800000,
          5496.220215
        ],
        [
          1774322100000,
          5504.060059
        ],
        [
          1774322400000,
          5523.609863
        ],
        [
          1774322700000,
          5531.589844
        ],
        [
          1774323000000,
          5508.47998
        ],
        [
          1774323300000,
          5522.509766
        ],
        [
          1774323600000,
          5532.810059
        ],
        [
          1774323900000,
          5527.189941
        ],
        [
          1774324200000,
          5519.720215
        ],
        [
          1774324500000,
          5529.279785
        ],
        [
          1774324800000,
          5540.709961
        ],
        [
          1774325100000,
          5536.549805
        ],
        [
          1774325400000,
          5536.790039
        ],
        [
          1774325700000,
          5527.540039
        ],
        [
          1774326000000,
          5519.069824
        ],
        [
          1774326300000,
          5516.410156
        ],
        [
          1774326600000,
          5521.629883
        ],
        [
          1774326900000,
          5527.740234
        ],
        [
          1774327200000,
          5521.540039
        ],
        [
          1774327500000,
          5529.859863
        ],
        [
          1774327800000,
          5548.450195
        ],
        [
          1774328100000,
          5550.459961
        ],
        [
          1774328180000,
          5547.450195
        ]
      ],
      "marketState": "UNKNOWN",
      "marketTime": "2026-03-24 13:56 KST",
      "marketTimestamp": 1774328180
    },
    {
      "id": "kosdaq",
      "label": "KOSDAQ",
      "symbol": "^KQ11",
      "group": "국내 지수",
      "kind": "equity",
      "decimals": 2,
      "price": 1119.56,
      "previousClose": 1161.52,
      "change": -41.96,
      "changePercent": -3.6125,
      "tone": "down",
      "direction": "하락",
      "series": [
        [
          1774310400000,
          1131.569946
        ],
        [
          1774310700000,
          1132.780029
        ],
        [
          1774311000000,
          1133.569946
        ],
        [
          1774311300000,
          1130.040039
        ],
        [
          1774311600000,
          1133.290039
        ],
        [
          1774311900000,
          1132.410034
        ],
        [
          1774312200000,
          1131.560059
        ],
        [
          1774312500000,
          1124.5
        ],
        [
          1774312800000,
          1125.920044
        ],
        [
          1774313100000,
          1125.25
        ],
        [
          1774313400000,
          1124.130005
        ],
        [
          1774313700000,
          1120.589966
        ],
        [
          1774314000000,
          1115.969971
        ],
        [
          1774314300000,
          1114.469971
        ],
        [
          1774314600000,
          1113.97998
        ],
        [
          1774314900000,
          1108.560059
        ],
        [
          1774315200000,
          1117.400024
        ],
        [
          1774315500000,
          1120.329956
        ],
        [
          1774315800000,
          1116.51001
        ],
        [
          1774316100000,
          1110.219971
        ],
        [
          1774316400000,
          1105.459961
        ],
        [
          1774316700000,
          1101.300049
        ],
        [
          1774317000000,
          1098.699951
        ],
        [
          1774317300000,
          1097.160034
        ],
        [
          1774317600000,
          1105.040039
        ],
        [
          1774317900000,
          1103.98999
        ],
        [
          1774318200000,
          1099.140015
        ],
        [
          1774318500000,
          1104.119995
        ],
        [
          1774318800000,
          1108.530029
        ],
        [
          1774319100000,
          1108.709961
        ],
        [
          1774319400000,
          1109.560059
        ],
        [
          1774319700000,
          1110.5
        ],
        [
          1774320000000,
          1110.969971
        ],
        [
          1774320300000,
          1111.880005
        ],
        [
          1774320600000,
          1108.459961
        ],
        [
          1774320900000,
          1107.469971
        ],
        [
          1774321200000,
          1106.829956
        ],
        [
          1774321500000,
          1107.530029
        ],
        [
          1774321800000,
          1108.569946
        ],
        [
          1774322100000,
          1110.199951
        ],
        [
          1774322400000,
          1112.27002
        ],
        [
          1774322700000,
          1113.089966
        ],
        [
          1774323000000,
          1110.410034
        ],
        [
          1774323300000,
          1111.079956
        ],
        [
          1774323600000,
          1112.27002
        ],
        [
          1774323900000,
          1112.109985
        ],
        [
          1774324200000,
          1111.540039
        ],
        [
          1774324500000,
          1113.5
        ],
        [
          1774324800000,
          1116.25
        ],
        [
          1774325100000,
          1116.680054
        ],
        [
          1774325400000,
          1117.219971
        ],
        [
          1774325700000,
          1115.420044
        ],
        [
          1774326000000,
          1114.25
        ],
        [
          1774326300000,
          1113.449951
        ],
        [
          1774326600000,
          1113.680054
        ],
        [
          1774326900000,
          1116.069946
        ],
        [
          1774327200000,
          1115.699951
        ],
        [
          1774327500000,
          1116.920044
        ],
        [
          1774327800000,
          1119.359985
        ],
        [
          1774328100000,
          1119.670044
        ],
        [
          1774328180000,
          1119.560059
        ]
      ],
      "marketState": "UNKNOWN",
      "marketTime": "2026-03-24 13:56 KST",
      "marketTimestamp": 1774328180
    },
    {
      "id": "sp500",
      "label": "S&P 500",
      "symbol": "^GSPC",
      "group": "해외 지수",
      "kind": "equity",
      "decimals": 2,
      "price": 6581.0,
      "previousClose": 6506.48,
      "change": 74.52,
      "changePercent": 1.1453,
      "tone": "up",
      "direction": "상승",
      "series": [
        [
          1774272600000,
          6592.169922
        ],
        [
          1774272900000,
          6606.470215
        ],
        [
          1774273200000,
          6606.549805
        ],
        [
          1774273500000,
          6614.47998
        ],
        [
          1774273800000,
          6622.700195
        ],
        [
          1774274100000,
          6627.580078
        ],
        [
          1774274400000,
          6618.609863
        ],
        [
          1774274700000,
          6622.259766
        ],
        [
          1774275000000,
          6627.149902
        ],
        [
          1774275300000,
          6637.200195
        ],
        [
          1774275600000,
          6645.0
        ],
        [
          1774275900000,
          6636.069824
        ],
        [
          1774276200000,
          6634.189941
        ],
        [
          1774276500000,
          6630.740234
        ],
        [
          1774276800000,
          6629.77002
        ],
        [
          1774277100000,
          6638.720215
        ],
        [
          1774277400000,
          6634.060059
        ],
        [
          1774277700000,
          6636.419922
        ],
        [
          1774278000000,
          6650.0
        ],
        [
          1774278300000,
          6648.720215
        ],
        [
          1774278600000,
          6646.089844
        ],
        [
          1774278900000,
          6640.470215
        ],
        [
          1774279200000,
          6646.189941
        ],
        [
          1774279500000,
          6635.160156
        ],
        [
          1774279800000,
          6632.350098
        ],
        [
          1774280100000,
          6619.310059
        ],
        [
          1774280400000,
          6618.890137
        ],
        [
          1774280700000,
          6612.72998
        ],
        [
          1774281000000,
          6599.410156
        ],
        [
          1774281300000,
          6585.689941
        ],
        [
          1774281600000,
          6590.52002
        ],
        [
          1774281900000,
          6596.049805
        ],
        [
          1774282200000,
          6596.740234
        ],
        [
          1774282500000,
          6586.330078
        ],
        [
          1774282800000,
          6582.740234
        ],
        [
          1774283100000,
          6566.52002
        ],
        [
          1774283400000,
          6580.52002
        ],
        [
          1774283700000,
          6580.609863
        ],
        [
          1774284000000,
          6586.310059
        ],
        [
          1774284300000,
          6588.959961
        ],
        [
          1774284600000,
          6583.810059
        ],
        [
          1774284900000,
          6581.509766
        ],
        [
          1774285200000,
          6576.689941
        ],
        [
          1774285500000,
          6586.810059
        ],
        [
          1774285800000,
          6579.799805
        ],
        [
          1774286100000,
          6578.129883
        ],
        [
          1774286400000,
          6573.669922
        ],
        [
          1774286700000,
          6579.399902
        ],
        [
          1774287000000,
          6596.879883
        ],
        [
          1774287300000,
          6603.819824
        ],
        [
          1774287600000,
          6594.330078
        ],
        [
          1774287900000,
          6593.410156
        ],
        [
          1774288200000,
          6600.240234
        ],
        [
          1774288500000,
          6606.970215
        ],
        [
          1774288800000,
          6607.129883
        ],
        [
          1774289100000,
          6599.970215
        ],
        [
          1774289400000,
          6603.310059
        ],
        [
          1774289700000,
          6600.509766
        ],
        [
          1774290000000,
          6601.350098
        ],
        [
          1774290300000,
          6600.029785
        ],
        [
          1774290600000,
          6614.370117
        ],
        [
          1774290900000,
          6615.5
        ],
        [
          1774291200000,
          6613.600098
        ],
        [
          1774291500000,
          6617.47998
        ],
        [
          1774291800000,
          6614.419922
        ],
        [
          1774292100000,
          6615.600098
        ],
        [
          1774292400000,
          6611.850098
        ],
        [
          1774292700000,
          6613.390137
        ],
        [
          1774293000000,
          6607.430176
        ],
        [
          1774293300000,
          6604.419922
        ],
        [
          1774293600000,
          6601.509766
        ],
        [
          1774293900000,
          6599.439941
        ],
        [
          1774294200000,
          6599.129883
        ],
        [
          1774294500000,
          6601.799805
        ],
        [
          1774294800000,
          6604.580078
        ],
        [
          1774295100000,
          6603.660156
        ],
        [
          1774295400000,
          6592.779785
        ],
        [
          1774295700000,
          6581.759766
        ],
        [
          1774296000000,
          6581.0
        ]
      ],
      "marketState": "UNKNOWN",
      "marketTime": "2026-03-24 06:11 KST",
      "marketTimestamp": 1774300298
    },
    {
      "id": "nasdaq",
      "label": "NASDAQ",
      "symbol": "^IXIC",
      "group": "해외 지수",
      "kind": "equity",
      "decimals": 2,
      "price": 21946.76,
      "previousClose": 21647.611,
      "change": 299.149,
      "changePercent": 1.3819,
      "tone": "up",
      "direction": "상승",
      "series": [
        [
          1774272600000,
          21984.035156
        ],
        [
          1774272900000,
          22039.744141
        ],
        [
          1774273200000,
          22023.835938
        ],
        [
          1774273500000,
          22070.417969
        ],
        [
          1774273800000,
          22096.423828
        ],
        [
          1774274100000,
          22100.785156
        ],
        [
          1774274400000,
          22067.890625
        ],
        [
          1774274700000,
          22067.585938
        ],
        [
          1774275000000,
          22103.400391
        ],
        [
          1774275300000,
          22142.1875
        ],
        [
          1774275600000,
          22169.068359
        ],
        [
          1774275900000,
          22138.234375
        ],
        [
          1774276200000,
          22129.634766
        ],
        [
          1774276500000,
          22116.138672
        ],
        [
          1774276800000,
          22102.447266
        ],
        [
          1774277100000,
          22129.402344
        ],
        [
          1774277400000,
          22109.908203
        ],
        [
          1774277700000,
          22122.544922
        ],
        [
          1774278000000,
          22178.126953
        ],
        [
          1774278300000,
          22178.703125
        ],
        [
          1774278600000,
          22172.121094
        ],
        [
          1774278900000,
          22144.279297
        ],
        [
          1774279200000,
          22168.017578
        ],
        [
          1774279500000,
          22129.396484
        ],
        [
          1774279800000,
          22119.234375
        ],
        [
          1774280100000,
          22067.296875
        ],
        [
          1774280400000,
          22062.984375
        ],
        [
          1774280700000,
          22037.458984
        ],
        [
          1774281000000,
          21977.945312
        ],
        [
          1774281300000,
          21926.5
        ],
        [
          1774281600000,
          21938.835938
        ],
        [
          1774281900000,
          21980.447266
        ],
        [
          1774282200000,
          21983.474609
        ],
        [
          1774282500000,
          21950.958984
        ],
        [
          1774282800000,
          21929.484375
        ],
        [
          1774283100000,
          21868.066406
        ],
        [
          1774283400000,
          21914.345703
        ],
        [
          1774283700000,
          21915.005859
        ],
        [
          1774284000000,
          21936.580078
        ],
        [
          1774284300000,
          21950.492188
        ],
        [
          1774284600000,
          21927.96875
        ],
        [
          1774284900000,
          21917.886719
        ],
        [
          1774285200000,
          21901.345703
        ],
        [
          1774285500000,
          21930.269531
        ],
        [
          1774285800000,
          21905.546875
        ],
        [
          1774286100000,
          21897.976562
        ],
        [
          1774286400000,
          21880.367188
        ],
        [
          1774286700000,
          21904.855469
        ],
        [
          1774287000000,
          21959.587891
        ],
        [
          1774287300000,
          21985.101562
        ],
        [
          1774287600000,
          21954.513672
        ],
        [
          1774287900000,
          21947.919922
        ],
        [
          1774288200000,
          21972.75
        ],
        [
          1774288500000,
          22000.019531
        ],
        [
          1774288800000,
          22009.986328
        ],
        [
          1774289100000,
          21981.591797
        ],
        [
          1774289400000,
          21989.259766
        ],
        [
          1774289700000,
          21978.222656
        ],
        [
          1774290000000,
          21982.414062
        ],
        [
          1774290300000,
          21977.605469
        ],
        [
          1774290600000,
          22032.466797
        ],
        [
          1774290900000,
          22033.359375
        ],
        [
          1774291200000,
          22032.175781
        ],
        [
          1774291500000,
          22049.150391
        ],
        [
          1774291800000,
          22040.320312
        ],
        [
          1774292100000,
          22046.792969
        ],
        [
          1774292400000,
          22032.462891
        ],
        [
          1774292700000,
          22042.207031
        ],
        [
          1774293000000,
          22023.652344
        ],
        [
          1774293300000,
          22016.353516
        ],
        [
          1774293600000,
          22012.511719
        ],
        [
          1774293900000,
          22007.005859
        ],
        [
          1774294200000,
          22008.197266
        ],
        [
          1774294500000,
          22018.089844
        ],
        [
          1774294800000,
          22028.5
        ],
        [
          1774295100000,
          22026.205078
        ],
        [
          1774295400000,
          21982.537109
        ],
        [
          1774295700000,
          21956.785156
        ],
        [
          1774296000000,
          21946.759766
        ]
      ],
      "marketState": "UNKNOWN",
      "marketTime": "2026-03-24 06:15 KST",
      "marketTimestamp": 1774300559
    }
  ],
  "headlines": [
    {
      "title": "[마켓뷰] 트럼프 이란 폭격 보류에 美증시 훈풍…코스피도 반등할까",
      "source": "연합뉴스",
      "link": "https://news.google.com/rss/articles/CBMiYEFVX3lxTE5fczluU200Rm1vYjFJT1BWTkN6WEJZNHk4RS1JS2MtS3V4WU1TLVR0ekpqNTFTRk1lXzdqVFdJNVQ4a2dDWWY3UVM3UDBjeElsbWVSN0dHUGc2T29KeWZBNNIBYEFVX3lxTE5fczluU200Rm1vYjFJT1BWTkN6WEJZNHk4RS1JS2MtS3V4WU1TLVR0ekpqNTFTRk1lXzdqVFdJNVQ4a2dDWWY3UVM3UDBjeElsbWVSN0dHUGc2T29KeWZBNA?oc=5",
      "publishedAt": "Mon, 23 Mar 2026 23:08:07 GMT"
    },
    {
      "title": "[증시타임] 이란 전쟁에 대한 미국의 현지 반응은?",
      "source": "v.daum.net",
      "link": "https://news.google.com/rss/articles/CBMiT0FVX3lxTFBGZFZ3TXljdVVKcDBIMmVtSlpqUFBISzB0Um1yRnB3QXVOc0pCaHFDWFp2RnVEY2lwMzJQNEpZZjBnX2Q1aG5SLVR1dTROYTA?oc=5",
      "publishedAt": "Tue, 24 Mar 2026 01:28:18 GMT"
    },
    {
      "title": "해외자산의 국내 유턴…RIA, 환율·증시 ‘두 토끼’ 잡을까",
      "source": "브릿지경제",
      "link": "https://news.google.com/rss/articles/CBMiWkFVX3lxTE0tMXhlSVBNdEc2dHY1bW96VW9hbzdhdU1zc1YxejJFM1VxcDZGdG9wVk8wb21vYVRGeWg5SVlaN1pmWEUxZ201aG5SNGt2amhtU0VJSy1jMWxWdw?oc=5",
      "publishedAt": "Tue, 24 Mar 2026 03:55:00 GMT"
    },
    {
      "title": "중동 긴장 완화·뉴욕증시 랠리에…코스피, 3%대 급등 출발",
      "source": "조선일보",
      "link": "https://news.google.com/rss/articles/CBMijgFBVV95cUxPM3VDOUEwOGxiRVpUd1pnMVZGa0ZTQmE3VnhMOGVpcjVsWkpqSDFkcTY3TlBDSXpkQkJha2ZvTG1VcWVMSTE3T292Q1JNS0ZjZnRRUDBOZkxUZUN1OC1rNXRGdGlvSmQ1aER6bTBlaFJGQkpQT0Z4MVlzRS1QQU9NQnlYa180aEVVYlUzc2F30gGiAUFVX3lxTE9YeWVrOVJiLWZIbHpTMHg2TkYzZEUtYTdHR0M4XzJLWWV6c2NXYWJiRTg3Zjh4eDFaeUNKb29aUnVmZldoeFBHRUMwQmJ5QlpoZDhvS1g4clRtaHB1OWVPT3BSNmJxMTBRandhTURUTmpkYk1NM1ZsTFNwTVVoZWxyQVREc3VfQWdwdnZWN192ZzlpVEtmdHBoT1I4Q3djWHlmUQ?oc=5",
      "publishedAt": "Tue, 24 Mar 2026 00:11:00 GMT"
    },
    {
      "title": "\"서학개미 유턴 기대\"…RIA 계좌 24시간 만에 1.5만개 개설",
      "source": "뉴스1",
      "link": "https://news.google.com/rss/articles/CBMiZEFVX3lxTE41RkVCTFZfeUppVEdvQ1hENGRUaXJMQV9Fcmk4US1yZ2E4WkZscVpORF9KUzFrQVEyRWkzTVlkOXNLMTgtMVR3MnV1RjlYR3N2WDVoS1RJbURoM2ppazdDMzFYV1c?oc=5",
      "publishedAt": "Tue, 24 Mar 2026 01:58:19 GMT"
    },
    {
      "title": "JP모건 “널뛰는 한국 증시, 밸류업이 게임 체인저”",
      "source": "중앙일보",
      "link": "https://news.google.com/rss/articles/CBMiVkFVX3lxTE95cDJIcU5TdHhzYzFNeTI1aUE1TUgyYWFVWTVXRnltYTZKYVZOdWo3WUNWdk5rSUlaWGRzWk5PUm1lT21yU2l1cU5yRmE1NXdZYWMzM3pR?oc=5",
      "publishedAt": "Mon, 23 Mar 2026 15:02:07 GMT"
    },
    {
      "title": "[굿모닝 증시]중동전쟁 협상 기대감에 美 반등…韓도 상승세 전망",
      "source": "아시아경제",
      "link": "https://news.google.com/rss/articles/CBMiYkFVX3lxTE1lS2xkM0c4SWNsMjlEZTA1RE1Qb1JXUXIyVUVWRTdJSjFNMkM4Ry1FbUVyYi1KdnM3dmxqNXlidTM4RFBDVk5ZeFFuYTZtTklRc0xwZnpDa1RoR0V6eWZuVm9n?oc=5",
      "publishedAt": "Mon, 23 Mar 2026 23:31:00 GMT"
    },
    {
      "title": "위기때 외국인 '1순위 ATM', 증시 하락률 세계 1위 … 채권 금리 변동성은 튀르키예보다 커",
      "source": "뉴데일리 경제",
      "link": "https://news.google.com/rss/articles/CBMie0FVX3lxTE9PY2hUM3VySVBQaUIzLWMzSU84YXpfSmhMcWxSYWc4NHBDc0ZMUXdleWVyNkhvNDViN2xvT2ttR1VaQVRMUTRHX1IwM0czTkFEeG83LUluUlZvbEJYZWI0SXE2SzVnRUM1MThDb0N4TjZtRkZoS2M3TUd2TQ?oc=5",
      "publishedAt": "Tue, 24 Mar 2026 01:50:20 GMT"
    }
  ],
  "summary": {
    "signal": {
      "label": "Risk-On",
      "tone": "up",
      "message": "주식과 위험자산 강세가 우세합니다."
    },
    "overview": [
      "국내장은 KOSPI 상승, KOSDAQ 하락 흐름입니다.",
      "해외는 S&P 500 +1.15%, NASDAQ +1.38%로 확인됩니다.",
      "매크로 변수는 USD/KRW +0.90%, 미 10년물 -1.30%입니다."
    ],
    "checkpoints": [
      "KOSPI +2.62% 상승",
      "KOSDAQ -3.61% 하락",
      "미국 증시 상승 / 나스닥 +1.38%",
      "원달러 +0.90% (+13.38)",
      "미 10년물 -0.057p (-1.30%)"
    ],
    "leaders": [
      {
        "label": "WTI",
        "changePercent": 4.1983,
        "direction": "상승"
      },
      {
        "label": "KOSPI",
        "changePercent": 2.6213,
        "direction": "상승"
      },
      {
        "label": "DOW",
        "changePercent": 1.3845,
        "direction": "상승"
      }
    ],
    "laggards": [
      {
        "label": "KOSDAQ",
        "changePercent": -3.6125,
        "direction": "하락"
      },
      {
        "label": "Gold",
        "changePercent": -1.9377,
        "direction": "하락"
      },
      {
        "label": "Bitcoin",
        "changePercent": -0.9829,
        "direction": "하락"
      }
    ]
  },
  "errors": []
}