{
  "updatedAt": "2026-07-13T03:27:51.895371+09:00",
  "updatedLabel": "2026-07-13 03:27:51 KST",
  "groups": [
    "국내 지수",
    "해외 지수",
    "거시 자산"
  ],
  "cards": [
    {
      "id": "kospi",
      "label": "KOSPI",
      "symbol": "^KS11",
      "group": "국내 지수",
      "kind": "equity",
      "decimals": 2,
      "price": 7475.94,
      "previousClose": 7291.91,
      "change": 184.03,
      "changePercent": 2.5238,
      "tone": "up",
      "direction": "상승",
      "series": [
        [
          1783641600000,
          7534.759766
        ],
        [
          1783641900000,
          7497.100098
        ],
        [
          1783642200000,
          7517.189941
        ],
        [
          1783642500000,
          7493.029785
        ],
        [
          1783642800000,
          7434.22998
        ],
        [
          1783643100000,
          7470.069824
        ],
        [
          1783643400000,
          7451.819824
        ],
        [
          1783643700000,
          7477.169922
        ],
        [
          1783644000000,
          7496.850098
        ],
        [
          1783644300000,
          7493.220215
        ],
        [
          1783644600000,
          7521.649902
        ],
        [
          1783644900000,
          7545.890137
        ],
        [
          1783645200000,
          7520.080078
        ],
        [
          1783645500000,
          7537.109863
        ],
        [
          1783645800000,
          7531.950195
        ],
        [
          1783646100000,
          7548.959961
        ],
        [
          1783646400000,
          7581.390137
        ],
        [
          1783646700000,
          7573.220215
        ],
        [
          1783647000000,
          7620.069824
        ],
        [
          1783647300000,
          7632.899902
        ],
        [
          1783647600000,
          7615.02002
        ],
        [
          1783647900000,
          7636.459961
        ],
        [
          1783648200000,
          7588.299805
        ],
        [
          1783648500000,
          7585.549805
        ],
        [
          1783648800000,
          7572.25
        ],
        [
          1783649100000,
          7554.759766
        ],
        [
          1783649400000,
          7549.160156
        ],
        [
          1783649700000,
          7556.350098
        ],
        [
          1783650000000,
          7534.419922
        ],
        [
          1783650300000,
          7555.959961
        ],
        [
          1783650600000,
          7592.620117
        ],
        [
          1783650900000,
          7583.27002
        ],
        [
          1783651200000,
          7585.120117
        ],
        [
          1783651500000,
          7595.649902
        ],
        [
          1783651800000,
          7583.390137
        ],
        [
          1783652100000,
          7608.720215
        ],
        [
          1783652400000,
          7599.279785
        ],
        [
          1783652700000,
          7614.310059
        ],
        [
          1783653000000,
          7607.669922
        ],
        [
          1783653300000,
          7625.859863
        ],
        [
          1783653600000,
          7624.399902
        ],
        [
          1783653900000,
          7606.580078
        ],
        [
          1783654200000,
          7610.069824
        ],
        [
          1783654500000,
          7630.02002
        ],
        [
          1783654800000,
          7636.689941
        ],
        [
          1783655100000,
          7628.049805
        ],
        [
          1783655400000,
          7654.629883
        ],
        [
          1783655700000,
          7660.100098
        ],
        [
          1783656000000,
          7676.680176
        ],
        [
          1783656300000,
          7687.060059
        ],
        [
          1783656600000,
          7692.560059
        ],
        [
          1783656900000,
          7696.549805
        ],
        [
          1783657200000,
          7667.669922
        ],
        [
          1783657500000,
          7675.490234
        ],
        [
          1783657800000,
          7649.169922
        ],
        [
          1783658100000,
          7677.209961
        ],
        [
          1783658400000,
          7686.169922
        ],
        [
          1783658700000,
          7681.450195
        ],
        [
          1783659000000,
          7641.290039
        ],
        [
          1783659300000,
          7626.120117
        ],
        [
          1783659600000,
          7610.899902
        ],
        [
          1783659900000,
          7586.279785
        ],
        [
          1783660200000,
          7628.970215
        ],
        [
          1783660500000,
          7622.819824
        ],
        [
          1783660800000,
          7631.189941
        ],
        [
          1783661100000,
          7613.810059
        ],
        [
          1783661400000,
          7621.959961
        ],
        [
          1783661700000,
          7600.589844
        ],
        [
          1783662000000,
          7578.370117
        ],
        [
          1783662300000,
          7593.580078
        ],
        [
          1783662600000,
          7585.490234
        ],
        [
          1783662900000,
          7581.350098
        ],
        [
          1783663200000,
          7475.939941
        ]
      ],
      "marketState": "UNKNOWN",
      "marketTime": "2026-07-10 18:05 KST",
      "marketTimestamp": 1783674340
    },
    {
      "id": "kosdaq",
      "label": "KOSDAQ",
      "symbol": "^KQ11",
      "group": "국내 지수",
      "kind": "equity",
      "decimals": 2,
      "price": 837.43,
      "previousClose": 794.0,
      "change": 43.43,
      "changePercent": 5.4698,
      "tone": "up",
      "direction": "상승",
      "series": [
        [
          1783641600000,
          804.309998
        ],
        [
          1783641900000,
          810.22998
        ],
        [
          1783642200000,
          812.380005
        ],
        [
          1783642500000,
          813.409973
        ],
        [
          1783642800000,
          809.200012
        ],
        [
          1783643100000,
          817.909973
        ],
        [
          1783643400000,
          814.039978
        ],
        [
          1783643700000,
          820.080017
        ],
        [
          1783644000000,
          826.349976
        ],
        [
          1783644300000,
          827.900024
        ],
        [
          1783644600000,
          826.72998
        ],
        [
          1783644900000,
          826.190002
        ],
        [
          1783645200000,
          828.940002
        ],
        [
          1783645500000,
          827.830017
        ],
        [
          1783645800000,
          833.289978
        ],
        [
          1783646100000,
          836.77002
        ],
        [
          1783646400000,
          832.380005
        ],
        [
          1783646700000,
          836.320007
        ],
        [
          1783647000000,
          834.119995
        ],
        [
          1783647300000,
          835.590027
        ],
        [
          1783647600000,
          838.400024
        ],
        [
          1783647900000,
          841.27002
        ],
        [
          1783648200000,
          837.419983
        ],
        [
          1783648500000,
          836.599976
        ],
        [
          1783648800000,
          835.01001
        ],
        [
          1783649100000,
          836.299988
        ],
        [
          1783649400000,
          832.840027
        ],
        [
          1783649700000,
          836.390015
        ],
        [
          1783650000000,
          836.580017
        ],
        [
          1783650300000,
          838.119995
        ],
        [
          1783650600000,
          842.390015
        ],
        [
          1783650900000,
          842.929993
        ],
        [
          1783651200000,
          843.169983
        ],
        [
          1783651500000,
          843.590027
        ],
        [
          1783651800000,
          842.409973
        ],
        [
          1783652100000,
          843.280029
        ],
        [
          1783652400000,
          843.330017
        ],
        [
          1783652700000,
          844.190002
        ],
        [
          1783653000000,
          844.940002
        ],
        [
          1783653300000,
          845.200012
        ],
        [
          1783653600000,
          842.679993
        ],
        [
          1783653900000,
          841.380005
        ],
        [
          1783654200000,
          841.619995
        ],
        [
          1783654500000,
          841.950012
        ],
        [
          1783654800000,
          843.97998
        ],
        [
          1783655100000,
          843.349976
        ],
        [
          1783655400000,
          842.169983
        ],
        [
          1783655700000,
          841.929993
        ],
        [
          1783656000000,
          844.570007
        ],
        [
          1783656300000,
          843.969971
        ],
        [
          1783656600000,
          844.679993
        ],
        [
          1783656900000,
          843.849976
        ],
        [
          1783657200000,
          843.700012
        ],
        [
          1783657500000,
          844.450012
        ],
        [
          1783657800000,
          843.580017
        ],
        [
          1783658100000,
          843.669983
        ],
        [
          1783658400000,
          843.52002
        ],
        [
          1783658700000,
          842.090027
        ],
        [
          1783659000000,
          840.0
        ],
        [
          1783659300000,
          839.5
        ],
        [
          1783659600000,
          838.150024
        ],
        [
          1783659900000,
          835.909973
        ],
        [
          1783660200000,
          840.030029
        ],
        [
          1783660500000,
          840.409973
        ],
        [
          1783660800000,
          841.900024
        ],
        [
          1783661100000,
          840.98999
        ],
        [
          1783661400000,
          841.210022
        ],
        [
          1783661700000,
          839.539978
        ],
        [
          1783662000000,
          838.950012
        ],
        [
          1783662300000,
          843.849976
        ],
        [
          1783662600000,
          843.280029
        ],
        [
          1783662900000,
          843.47998
        ],
        [
          1783663200000,
          837.429993
        ]
      ],
      "marketState": "UNKNOWN",
      "marketTime": "2026-07-10 18:05 KST",
      "marketTimestamp": 1783674340
    },
    {
      "id": "sp500",
      "label": "S&P 500",
      "symbol": "^GSPC",
      "group": "해외 지수",
      "kind": "equity",
      "decimals": 2,
      "price": 7575.39,
      "previousClose": 7543.64,
      "change": 31.75,
      "changePercent": 0.4209,
      "tone": "up",
      "direction": "상승",
      "series": [
        [
          1783690200000,
          7553.299805
        ],
        [
          1783690500000,
          7551.839844
        ],
        [
          1783690800000,
          7548.080078
        ],
        [
          1783691100000,
          7556.870117
        ],
        [
          1783691400000,
          7556.160156
        ],
        [
          1783691700000,
          7555.359863
        ],
        [
          1783692000000,
          7557.600098
        ],
        [
          1783692300000,
          7557.5
        ],
        [
          1783692600000,
          7553.47998
        ],
        [
          1783692900000,
          7552.109863
        ],
        [
          1783693200000,
          7551.379883
        ],
        [
          1783693500000,
          7552.120117
        ],
        [
          1783693800000,
          7534.660156
        ],
        [
          1783694100000,
          7543.0
        ],
        [
          1783694400000,
          7547.450195
        ],
        [
          1783694700000,
          7549.77002
        ],
        [
          1783695000000,
          7545.189941
        ],
        [
          1783695300000,
          7538.129883
        ],
        [
          1783695600000,
          7535.5
        ],
        [
          1783695900000,
          7542.919922
        ],
        [
          1783696200000,
          7544.819824
        ],
        [
          1783696500000,
          7553.259766
        ],
        [
          1783696800000,
          7556.700195
        ],
        [
          1783697100000,
          7558.72998
        ],
        [
          1783697400000,
          7556.410156
        ],
        [
          1783697700000,
          7550.200195
        ],
        [
          1783698000000,
          7546.549805
        ],
        [
          1783698300000,
          7551.120117
        ],
        [
          1783698600000,
          7554.459961
        ],
        [
          1783698900000,
          7554.279785
        ],
        [
          1783699200000,
          7558.100098
        ],
        [
          1783699500000,
          7555.779785
        ],
        [
          1783699800000,
          7558.319824
        ],
        [
          1783700100000,
          7562.029785
        ],
        [
          1783700400000,
          7560.25
        ],
        [
          1783700700000,
          7558.240234
        ],
        [
          1783701000000,
          7561.549805
        ],
        [
          1783701300000,
          7559.169922
        ],
        [
          1783701600000,
          7562.430176
        ],
        [
          1783701900000,
          7564.700195
        ],
        [
          1783702200000,
          7566.339844
        ],
        [
          1783702500000,
          7566.379883
        ],
        [
          1783702800000,
          7563.27002
        ],
        [
          1783703100000,
          7562.560059
        ],
        [
          1783703400000,
          7564.160156
        ],
        [
          1783703700000,
          7564.890137
        ],
        [
          1783704000000,
          7565.669922
        ],
        [
          1783704300000,
          7566.290039
        ],
        [
          1783704600000,
          7566.609863
        ],
        [
          1783704900000,
          7568.899902
        ],
        [
          1783705200000,
          7567.939941
        ],
        [
          1783705500000,
          7569.27002
        ],
        [
          1783705800000,
          7568.830078
        ],
        [
          1783706100000,
          7566.439941
        ],
        [
          1783706400000,
          7566.740234
        ],
        [
          1783706700000,
          7568.930176
        ],
        [
          1783707000000,
          7569.299805
        ],
        [
          1783707300000,
          7568.379883
        ],
        [
          1783707600000,
          7569.669922
        ],
        [
          1783707900000,
          7570.379883
        ],
        [
          1783708200000,
          7571.740234
        ],
        [
          1783708500000,
          7570.25
        ],
        [
          1783708800000,
          7571.100098
        ],
        [
          1783709100000,
          7570.970215
        ],
        [
          1783709400000,
          7571.779785
        ],
        [
          1783709700000,
          7571.259766
        ],
        [
          1783710000000,
          7575.839844
        ],
        [
          1783710300000,
          7575.330078
        ],
        [
          1783710600000,
          7577.439941
        ],
        [
          1783710900000,
          7576.470215
        ],
        [
          1783711200000,
          7575.609863
        ],
        [
          1783711500000,
          7575.640137
        ],
        [
          1783711800000,
          7575.799805
        ],
        [
          1783712100000,
          7576.859863
        ],
        [
          1783712400000,
          7576.540039
        ],
        [
          1783712700000,
          7577.390137
        ],
        [
          1783713000000,
          7577.319824
        ],
        [
          1783713300000,
          7575.379883
        ],
        [
          1783713600000,
          7575.390137
        ]
      ],
      "marketState": "UNKNOWN",
      "marketTime": "2026-07-11 06:28 KST",
      "marketTimestamp": 1783718910
    },
    {
      "id": "nasdaq",
      "label": "NASDAQ",
      "symbol": "^IXIC",
      "group": "해외 지수",
      "kind": "equity",
      "decimals": 2,
      "price": 26281.607,
      "previousClose": 26206.9,
      "change": 74.707,
      "changePercent": 0.2851,
      "tone": "up",
      "direction": "상승",
      "series": [
        [
          1783690200000,
          26237.296875
        ],
        [
          1783690500000,
          26194.166016
        ],
        [
          1783690800000,
          26169.138672
        ],
        [
          1783691100000,
          26224.751953
        ],
        [
          1783691400000,
          26227.886719
        ],
        [
          1783691700000,
          26211.619141
        ],
        [
          1783692000000,
          26210.113281
        ],
        [
          1783692300000,
          26219.107422
        ],
        [
          1783692600000,
          26207.419922
        ],
        [
          1783692900000,
          26180.65625
        ],
        [
          1783693200000,
          26167.191406
        ],
        [
          1783693500000,
          26184.652344
        ],
        [
          1783693800000,
          26125.863281
        ],
        [
          1783694100000,
          26149.267578
        ],
        [
          1783694400000,
          26155.357422
        ],
        [
          1783694700000,
          26167.560547
        ],
        [
          1783695000000,
          26132.304688
        ],
        [
          1783695300000,
          26106.925781
        ],
        [
          1783695600000,
          26087.427734
        ],
        [
          1783695900000,
          26132.957031
        ],
        [
          1783696200000,
          26140.996094
        ],
        [
          1783696500000,
          26182.988281
        ],
        [
          1783696800000,
          26202.013672
        ],
        [
          1783697100000,
          26221.099609
        ],
        [
          1783697400000,
          26226.037109
        ],
        [
          1783697700000,
          26187.320312
        ],
        [
          1783698000000,
          26156.408203
        ],
        [
          1783698300000,
          26188.621094
        ],
        [
          1783698600000,
          26202.625
        ],
        [
          1783698900000,
          26208.773438
        ],
        [
          1783699200000,
          26228.994141
        ],
        [
          1783699500000,
          26221.070312
        ],
        [
          1783699800000,
          26229.009766
        ],
        [
          1783700100000,
          26258.222656
        ],
        [
          1783700400000,
          26261.074219
        ],
        [
          1783700700000,
          26251.314453
        ],
        [
          1783701000000,
          26268.648438
        ],
        [
          1783701300000,
          26257.054688
        ],
        [
          1783701600000,
          26264.5
        ],
        [
          1783701900000,
          26271.085938
        ],
        [
          1783702200000,
          26275.210938
        ],
        [
          1783702500000,
          26271.880859
        ],
        [
          1783702800000,
          26258.451172
        ],
        [
          1783703100000,
          26250.376953
        ],
        [
          1783703400000,
          26251.277344
        ],
        [
          1783703700000,
          26254.173828
        ],
        [
          1783704000000,
          26264.320312
        ],
        [
          1783704300000,
          26269.529297
        ],
        [
          1783704600000,
          26265.498047
        ],
        [
          1783704900000,
          26277.652344
        ],
        [
          1783705200000,
          26272.921875
        ],
        [
          1783705500000,
          26277.589844
        ],
        [
          1783705800000,
          26274.234375
        ],
        [
          1783706100000,
          26265.457031
        ],
        [
          1783706400000,
          26272.638672
        ],
        [
          1783706700000,
          26278.482422
        ],
        [
          1783707000000,
          26280.011719
        ],
        [
          1783707300000,
          26272.582031
        ],
        [
          1783707600000,
          26282.263672
        ],
        [
          1783707900000,
          26284.617188
        ],
        [
          1783708200000,
          26289.923828
        ],
        [
          1783708500000,
          26278.541016
        ],
        [
          1783708800000,
          26280.914062
        ],
        [
          1783709100000,
          26272.097656
        ],
        [
          1783709400000,
          26275.578125
        ],
        [
          1783709700000,
          26272.650391
        ],
        [
          1783710000000,
          26296.84375
        ],
        [
          1783710300000,
          26287.398438
        ],
        [
          1783710600000,
          26293.640625
        ],
        [
          1783710900000,
          26290.042969
        ],
        [
          1783711200000,
          26283.642578
        ],
        [
          1783711500000,
          26285.320312
        ],
        [
          1783711800000,
          26288.074219
        ],
        [
          1783712100000,
          26291.091797
        ],
        [
          1783712400000,
          26287.628906
        ],
        [
          1783712700000,
          26287.798828
        ],
        [
          1783713000000,
          26283.367188
        ],
        [
          1783713300000,
          26278.699219
        ],
        [
          1783713600000,
          26281.607422
        ]
      ],
      "marketState": "UNKNOWN",
      "marketTime": "2026-07-11 06:15 KST",
      "marketTimestamp": 1783718159
    },
    {
      "id": "dow",
      "label": "DOW",
      "symbol": "^DJI",
      "group": "해외 지수",
      "kind": "equity",
      "decimals": 2,
      "price": 52637.01,
      "previousClose": 52487.4,
      "change": 149.61,
      "changePercent": 0.285,
      "tone": "up",
      "direction": "상승",
      "series": [
        [
          1783690200000,
          52549.050781
        ],
        [
          1783690500000,
          52582.0
        ],
        [
          1783690800000,
          52570.359375
        ],
        [
          1783691100000,
          52531.460938
        ],
        [
          1783691400000,
          52547.808594
        ],
        [
          1783691700000,
          52543.53125
        ],
        [
          1783692000000,
          52549.128906
        ],
        [
          1783692300000,
          52518.898438
        ],
        [
          1783692600000,
          52453.230469
        ],
        [
          1783692900000,
          52557.511719
        ],
        [
          1783693200000,
          52559.21875
        ],
        [
          1783693500000,
          52563.398438
        ],
        [
          1783693800000,
          52427.210938
        ],
        [
          1783694100000,
          52488.921875
        ],
        [
          1783694400000,
          52568.539062
        ],
        [
          1783694700000,
          52561.070312
        ],
        [
          1783695000000,
          52559.351562
        ],
        [
          1783695300000,
          52522.851562
        ],
        [
          1783695600000,
          52537.441406
        ],
        [
          1783695900000,
          52565.28125
        ],
        [
          1783696200000,
          52573.078125
        ],
        [
          1783696500000,
          52612.308594
        ],
        [
          1783696800000,
          52630.539062
        ],
        [
          1783697100000,
          52628.390625
        ],
        [
          1783697400000,
          52605.078125
        ],
        [
          1783697700000,
          52582.71875
        ],
        [
          1783698000000,
          52600.730469
        ],
        [
          1783698300000,
          52580.03125
        ],
        [
          1783698600000,
          52618.28125
        ],
        [
          1783698900000,
          52593.78125
        ],
        [
          1783699200000,
          52593.789062
        ],
        [
          1783699500000,
          52573.53125
        ],
        [
          1783699800000,
          52597.449219
        ],
        [
          1783700100000,
          52590.171875
        ],
        [
          1783700400000,
          52564.699219
        ],
        [
          1783700700000,
          52566.339844
        ],
        [
          1783701000000,
          52577.839844
        ],
        [
          1783701300000,
          52572.351562
        ],
        [
          1783701600000,
          52599.710938
        ],
        [
          1783701900000,
          52610.5
        ],
        [
          1783702200000,
          52624.039062
        ],
        [
          1783702500000,
          52627.878906
        ],
        [
          1783702800000,
          52615.738281
        ],
        [
          1783703100000,
          52617.78125
        ],
        [
          1783703400000,
          52630.441406
        ],
        [
          1783703700000,
          52637.519531
        ],
        [
          1783704000000,
          52626.441406
        ],
        [
          1783704300000,
          52622.839844
        ],
        [
          1783704600000,
          52637.910156
        ],
        [
          1783704900000,
          52639.601562
        ],
        [
          1783705200000,
          52632.449219
        ],
        [
          1783705500000,
          52649.371094
        ],
        [
          1783705800000,
          52657.03125
        ],
        [
          1783706100000,
          52630.300781
        ],
        [
          1783706400000,
          52628.800781
        ],
        [
          1783706700000,
          52646.53125
        ],
        [
          1783707000000,
          52645.539062
        ],
        [
          1783707300000,
          52643.511719
        ],
        [
          1783707600000,
          52653.109375
        ],
        [
          1783707900000,
          52660.0
        ],
        [
          1783708200000,
          52659.878906
        ],
        [
          1783708500000,
          52658.261719
        ],
        [
          1783708800000,
          52668.488281
        ],
        [
          1783709100000,
          52671.0
        ],
        [
          1783709400000,
          52667.898438
        ],
        [
          1783709700000,
          52670.0
        ],
        [
          1783710000000,
          52680.308594
        ],
        [
          1783710300000,
          52695.429688
        ],
        [
          1783710600000,
          52700.660156
        ],
        [
          1783710900000,
          52690.328125
        ],
        [
          1783711200000,
          52701.359375
        ],
        [
          1783711500000,
          52692.550781
        ],
        [
          1783711800000,
          52678.609375
        ],
        [
          1783712100000,
          52678.269531
        ],
        [
          1783712400000,
          52690.289062
        ],
        [
          1783712700000,
          52690.320312
        ],
        [
          1783713000000,
          52691.699219
        ],
        [
          1783713300000,
          52640.308594
        ],
        [
          1783713600000,
          52637.011719
        ]
      ],
      "marketState": "UNKNOWN",
      "marketTime": "2026-07-11 06:28 KST",
      "marketTimestamp": 1783718915
    },
    {
      "id": "usdkrw",
      "label": "USD/KRW",
      "symbol": "KRW=X",
      "group": "거시 자산",
      "kind": "fx",
      "decimals": 2,
      "price": 1498.87,
      "previousClose": 1506.48,
      "change": -7.61,
      "changePercent": -0.5052,
      "tone": "down",
      "direction": "하락",
      "series": [
        [
          1783638000000,
          1506.849976
        ],
        [
          1783638300000,
          1505.52002
        ],
        [
          1783638600000,
          1506.099976
        ],
        [
          1783638900000,
          1505.780029
        ],
        [
          1783639200000,
          1506.030029
        ],
        [
          1783639500000,
          1505.880005
        ],
        [
          1783639800000,
          1505.98999
        ],
        [
          1783640100000,
          1506.869995
        ],
        [
          1783640400000,
          1506.390015
        ],
        [
          1783640700000,
          1505.599976
        ],
        [
          1783641000000,
          1505.800049
        ],
        [
          1783641300000,
          1505.589966
        ],
        [
          1783641600000,
          1505.880005
        ],
        [
          1783641900000,
          1507.76001
        ],
        [
          1783642200000,
          1507.829956
        ],
        [
          1783642500000,
          1510.079956
        ],
        [
          1783642800000,
          1510.880005
        ],
        [
          1783643100000,
          1510.880005
        ],
        [
          1783643400000,
          1512.280029
        ],
        [
          1783643700000,
          1510.680054
        ],
        [
          1783644000000,
          1509.079956
        ],
        [
          1783644300000,
          1509.380005
        ],
        [
          1783644600000,
          1508.469971
        ],
        [
          1783644900000,
          1507.780029
        ],
        [
          1783645200000,
          1507.680054
        ],
        [
          1783645500000,
          1507.780029
        ],
        [
          1783645800000,
          1507.079956
        ],
        [
          1783646100000,
          1506.469971
        ],
        [
          1783646400000,
          1509.589966
        ],
        [
          1783646700000,
          1510.97998
        ],
        [
          1783647000000,
          1510.880005
        ],
        [
          1783647300000,
          1511.880005
        ],
        [
          1783647600000,
          1512.280029
        ],
        [
          1783647900000,
          1511.439941
        ],
        [
          1783648200000,
          1509.780029
        ],
        [
          1783648500000,
          1509.780029
        ],
        [
          1783648800000,
          1509.97998
        ],
        [
          1783649100000,
          1506.079956
        ],
        [
          1783649400000,
          1505.380005
        ],
        [
          1783649700000,
          1503.97998
        ],
        [
          1783650000000,
          1504.97998
        ],
        [
          1783650300000,
          1506.180054
        ],
        [
          1783650600000,
          1507.040039
        ],
        [
          1783650900000,
          1507.079956
        ],
        [
          1783651200000,
          1506.180054
        ],
        [
          1783651500000,
          1507.079956
        ],
        [
          1783651800000,
          1506.050049
        ],
        [
          1783652100000,
          1505.079956
        ],
        [
          1783652400000,
          1505.380005
        ],
        [
          1783652700000,
          1505.97998
        ],
        [
          1783653000000,
          1507.680054
        ],
        [
          1783653300000,
          1507.780029
        ],
        [
          1783653600000,
          1508.380005
        ],
        [
          1783653900000,
          1507.180054
        ],
        [
          1783654200000,
          1507.280029
        ],
        [
          1783654500000,
          1508.630005
        ],
        [
          1783654800000,
          1508.780029
        ],
        [
          1783655100000,
          1508.880005
        ],
        [
          1783655400000,
          1508.880005
        ],
        [
          1783655700000,
          1508.97998
        ],
        [
          1783656000000,
          1508.880005
        ],
        [
          1783656300000,
          1507.780029
        ],
        [
          1783656600000,
          1509.099976
        ],
        [
          1783656900000,
          1508.97998
        ],
        [
          1783657200000,
          1510.609985
        ],
        [
          1783657500000,
          1509.819946
        ],
        [
          1783657800000,
          1509.880005
        ],
        [
          1783658100000,
          1510.939941
        ],
        [
          1783658400000,
          1510.880005
        ],
        [
          1783658700000,
          1511.150024
        ],
        [
          1783659000000,
          1511.280029
        ],
        [
          1783659300000,
          1510.880005
        ],
        [
          1783659600000,
          1510.97998
        ],
        [
          1783659900000,
          1511.040039
        ],
        [
          1783660200000,
          1510.380005
        ],
        [
          1783660500000,
          1511.47998
        ],
        [
          1783660800000,
          1511.079956
        ],
        [
          1783661100000,
          1510.079956
        ],
        [
          1783661400000,
          1509.880005
        ],
        [
          1783661700000,
          1510.579956
        ],
        [
          1783662000000,
          1510.589966
        ],
        [
          1783662300000,
          1510.97998
        ],
        [
          1783662600000,
          1509.180054
        ],
        [
          1783662900000,
          1507.680054
        ],
        [
          1783663200000,
          1502.880005
        ],
        [
          1783663500000,
          1503.050049
        ],
        [
          1783663800000,
          1501.079956
        ],
        [
          1783664100000,
          1498.97998
        ],
        [
          1783664400000,
          1500.97998
        ],
        [
          1783664700000,
          1501.280029
        ],
        [
          1783665000000,
          1502.73999
        ],
        [
          1783665300000,
          1503.52002
        ],
        [
          1783665600000,
          1503.680054
        ],
        [
          1783665900000,
          1502.73999
        ],
        [
          1783666200000,
          1502.880005
        ],
        [
          1783666500000,
          1504.180054
        ],
        [
          1783666800000,
          1504.47998
        ],
        [
          1783667100000,
          1503.75
        ],
        [
          1783667400000,
          1502.880005
        ],
        [
          1783667700000,
          1502.97998
        ],
        [
          1783668000000,
          1502.599976
        ],
        [
          1783668300000,
          1502.48999
        ],
        [
          1783668600000,
          1502.780029
        ],
        [
          1783668900000,
          1503.290039
        ],
        [
          1783669200000,
          1503.140015
        ],
        [
          1783669500000,
          1503.48999
        ],
        [
          1783669800000,
          1503.26001
        ],
        [
          1783670100000,
          1503.079956
        ],
        [
          1783670400000,
          1503.400024
        ],
        [
          1783670700000,
          1504.280029
        ],
        [
          1783671000000,
          1504.709961
        ],
        [
          1783671300000,
          1505.030029
        ],
        [
          1783671600000,
          1505.810059
        ],
        [
          1783671900000,
          1506.109985
        ],
        [
          1783672200000,
          1506.089966
        ],
        [
          1783672500000,
          1506.140015
        ],
        [
          1783672800000,
          1505.780029
        ],
        [
          1783673100000,
          1505.459961
        ],
        [
          1783673400000,
          1505.319946
        ],
        [
          1783673700000,
          1504.910034
        ],
        [
          1783674000000,
          1505.430054
        ],
        [
          1783674300000,
          1505.380005
        ],
        [
          1783674600000,
          1505.369995
        ],
        [
          1783674900000,
          1505.099976
        ],
        [
          1783675200000,
          1505.209961
        ],
        [
          1783675500000,
          1505.329956
        ],
        [
          1783675800000,
          1505.160034
        ],
        [
          1783676100000,
          1504.540039
        ],
        [
          1783676400000,
          1504.849976
        ],
        [
          1783676700000,
          1504.569946
        ],
        [
          1783677000000,
          1504.780029
        ],
        [
          1783677300000,
          1504.5
        ],
        [
          1783677600000,
          1504.349976
        ],
        [
          1783677900000,
          1504.640015
        ],
        [
          1783678200000,
          1505.119995
        ],
        [
          1783678500000,
          1504.550049
        ],
        [
          1783678800000,
          1504.430054
        ],
        [
          1783679100000,
          1504.569946
        ],
        [
          1783679400000,
          1504.329956
        ],
        [
          1783679700000,
          1504.47998
        ],
        [
          1783680000000,
          1503.880005
        ],
        [
          1783680300000,
          1503.180054
        ],
        [
          1783680600000,
          1503.780029
        ],
        [
          1783680900000,
          1503.800049
        ],
        [
          1783681200000,
          1503.410034
        ],
        [
          1783681500000,
          1503.619995
        ],
        [
          1783681800000,
          1503.77002
        ],
        [
          1783682100000,
          1504.02002
        ],
        [
          1783682400000,
          1504.030029
        ],
        [
          1783682700000,
          1504.780029
        ],
        [
          1783683000000,
          1505.089966
        ],
        [
          1783683300000,
          1505.209961
        ],
        [
          1783683600000,
          1504.829956
        ],
        [
          1783683900000,
          1504.719971
        ],
        [
          1783684200000,
          1504.72998
        ],
        [
          1783684500000,
          1504.880005
        ],
        [
          1783684800000,
          1505.22998
        ],
        [
          1783685100000,
          1504.670044
        ],
        [
          1783685400000,
          1503.97998
        ],
        [
          1783685700000,
          1504.160034
        ],
        [
          1783686000000,
          1504.160034
        ],
        [
          1783686300000,
          1504.579956
        ],
        [
          1783686600000,
          1505.380005
        ],
        [
          1783686900000,
          1503.880005
        ],
        [
          1783687200000,
          1504.650024
        ],
        [
          1783687500000,
          1504.51001
        ],
        [
          1783687800000,
          1504.5
        ],
        [
          1783688100000,
          1504.390015
        ],
        [
          1783688400000,
          1504.430054
        ],
        [
          1783688700000,
          1504.410034
        ],
        [
          1783689000000,
          1504.27002
        ],
        [
          1783689300000,
          1504.280029
        ],
        [
          1783689600000,
          1503.900024
        ],
        [
          1783689900000,
          1504.170044
        ],
        [
          1783690200000,
          1504.079956
        ],
        [
          1783690500000,
          1502.829956
        ],
        [
          1783690800000,
          1501.939941
        ],
        [
          1783691100000,
          1501.780029
        ],
        [
          1783691400000,
          1501.780029
        ],
        [
          1783691700000,
          1501.219971
        ],
        [
          1783692000000,
          1501.390015
        ],
        [
          1783692300000,
          1501.369995
        ],
        [
          1783692600000,
          1501.51001
        ],
        [
          1783692900000,
          1501.699951
        ],
        [
          1783693200000,
          1501.569946
        ],
        [
          1783693500000,
          1501.079956
        ],
        [
          1783693800000,
          1501.97998
        ],
        [
          1783694100000,
          1501.849976
        ],
        [
          1783694400000,
          1501.869995
        ],
        [
          1783694700000,
          1502.069946
        ],
        [
          1783695000000,
          1502.079956
        ],
        [
          1783695300000,
          1502.880005
        ],
        [
          1783695600000,
          1502.910034
        ],
        [
          1783695900000,
          1501.880005
        ],
        [
          1783696200000,
          1501.880005
        ],
        [
          1783696500000,
          1500.579956
        ],
        [
          1783696800000,
          1500.800049
        ],
        [
          1783697100000,
          1501.209961
        ],
        [
          1783697400000,
          1500.869995
        ],
        [
          1783697700000,
          1501.02002
        ],
        [
          1783698000000,
          1501.160034
        ],
        [
          1783698300000,
          1500.869995
        ],
        [
          1783698600000,
          1501.0
        ],
        [
          1783698900000,
          1500.51001
        ],
        [
          1783699200000,
          1500.560059
        ],
        [
          1783699500000,
          1500.329956
        ],
        [
          1783699800000,
          1500.569946
        ],
        [
          1783700100000,
          1500.52002
        ],
        [
          1783700400000,
          1500.72998
        ],
        [
          1783700700000,
          1500.689941
        ],
        [
          1783701000000,
          1501.380005
        ],
        [
          1783701300000,
          1500.579956
        ],
        [
          1783701600000,
          1501.319946
        ],
        [
          1783701900000,
          1500.719971
        ],
        [
          1783702200000,
          1501.079956
        ],
        [
          1783702500000,
          1501.079956
        ],
        [
          1783702800000,
          1502.369995
        ],
        [
          1783703100000,
          1501.949951
        ],
        [
          1783703400000,
          1500.380005
        ],
        [
          1783703700000,
          1502.459961
        ],
        [
          1783704000000,
          1502.040039
        ],
        [
          1783704300000,
          1501.780029
        ],
        [
          1783704600000,
          1501.689941
        ],
        [
          1783704900000,
          1501.719971
        ],
        [
          1783705200000,
          1501.839966
        ],
        [
          1783705500000,
          1501.650024
        ],
        [
          1783705800000,
          1501.660034
        ],
        [
          1783706100000,
          1501.51001
        ],
        [
          1783706400000,
          1501.199951
        ],
        [
          1783706700000,
          1501.150024
        ],
        [
          1783707000000,
          1501.060059
        ],
        [
          1783707300000,
          1500.810059
        ],
        [
          1783707600000,
          1501.050049
        ],
        [
          1783707900000,
          1500.800049
        ],
        [
          1783708200000,
          1500.589966
        ],
        [
          1783708500000,
          1501.219971
        ],
        [
          1783708800000,
          1500.719971
        ],
        [
          1783709100000,
          1500.810059
        ],
        [
          1783709400000,
          1500.810059
        ],
        [
          1783709700000,
          1500.75
        ],
        [
          1783710000000,
          1500.810059
        ],
        [
          1783710300000,
          1500.900024
        ],
        [
          1783710600000,
          1500.930054
        ],
        [
          1783710900000,
          1500.48999
        ],
        [
          1783711200000,
          1500.930054
        ],
        [
          1783711500000,
          1500.97998
        ],
        [
          1783711800000,
          1500.949951
        ],
        [
          1783712100000,
          1500.810059
        ],
        [
          1783712400000,
          1500.719971
        ],
        [
          1783712700000,
          1500.939941
        ],
        [
          1783713000000,
          1500.51001
        ],
        [
          1783713300000,
          1499.73999
        ],
        [
          1783713600000,
          1500.069946
        ],
        [
          1783713900000,
          1499.5
        ],
        [
          1783714200000,
          1499.880005
        ],
        [
          1783714500000,
          1499.930054
        ],
        [
          1783714800000,
          1499.650024
        ],
        [
          1783715100000,
          1499.680054
        ],
        [
          1783715400000,
          1499.359985
        ],
        [
          1783715700000,
          1499.930054
        ],
        [
          1783716000000,
          1499.670044
        ],
        [
          1783716300000,
          1499.819946
        ],
        [
          1783716600000,
          1499.800049
        ],
        [
          1783716900000,
          1498.869995
        ],
        [
          1783717500000,
          1498.869995
        ]
      ],
      "marketState": "UNKNOWN",
      "marketTime": "2026-07-12 22:42 KST",
      "marketTimestamp": 1783863731
    },
    {
      "id": "us10y",
      "label": "미국 10Y",
      "symbol": "^TNX",
      "group": "거시 자산",
      "kind": "yield",
      "decimals": 3,
      "price": 4.569,
      "previousClose": 4.539,
      "change": 0.03,
      "changePercent": 0.6609,
      "tone": "up",
      "direction": "상승",
      "series": [
        [
          1783686000000,
          4.543
        ],
        [
          1783686300000,
          4.539
        ],
        [
          1783686600000,
          4.543
        ],
        [
          1783686900000,
          4.543
        ],
        [
          1783687200000,
          4.545
        ],
        [
          1783687500000,
          4.543
        ],
        [
          1783687800000,
          4.545
        ],
        [
          1783688100000,
          4.543
        ],
        [
          1783688400000,
          4.545
        ],
        [
          1783688700000,
          4.549
        ],
        [
          1783689000000,
          4.549
        ],
        [
          1783689300000,
          4.549
        ],
        [
          1783689600000,
          4.549
        ],
        [
          1783689900000,
          4.549
        ],
        [
          1783690200000,
          4.551
        ],
        [
          1783690500000,
          4.547
        ],
        [
          1783690800000,
          4.545
        ],
        [
          1783691100000,
          4.545
        ],
        [
          1783691400000,
          4.549
        ],
        [
          1783691700000,
          4.553
        ],
        [
          1783692000000,
          4.555
        ],
        [
          1783692300000,
          4.553
        ],
        [
          1783692600000,
          4.549
        ],
        [
          1783692900000,
          4.549
        ],
        [
          1783693200000,
          4.553
        ],
        [
          1783693500000,
          4.551
        ],
        [
          1783693800000,
          4.561
        ],
        [
          1783694100000,
          4.557
        ],
        [
          1783694400000,
          4.557
        ],
        [
          1783694700000,
          4.557
        ],
        [
          1783695000000,
          4.557
        ],
        [
          1783695300000,
          4.563
        ],
        [
          1783695600000,
          4.553
        ],
        [
          1783695900000,
          4.553
        ],
        [
          1783696200000,
          4.555
        ],
        [
          1783696500000,
          4.551
        ],
        [
          1783696800000,
          4.545
        ],
        [
          1783697100000,
          4.545
        ],
        [
          1783697400000,
          4.547
        ],
        [
          1783697700000,
          4.545
        ],
        [
          1783698000000,
          4.545
        ],
        [
          1783698300000,
          4.547
        ],
        [
          1783698600000,
          4.545
        ],
        [
          1783698900000,
          4.547
        ],
        [
          1783699200000,
          4.553
        ],
        [
          1783699500000,
          4.553
        ],
        [
          1783699800000,
          4.553
        ],
        [
          1783700100000,
          4.553
        ],
        [
          1783700400000,
          4.553
        ],
        [
          1783700700000,
          4.553
        ],
        [
          1783701000000,
          4.553
        ],
        [
          1783701300000,
          4.557
        ],
        [
          1783701600000,
          4.561
        ],
        [
          1783701900000,
          4.561
        ],
        [
          1783702200000,
          4.561
        ],
        [
          1783702500000,
          4.561
        ],
        [
          1783702800000,
          4.563
        ],
        [
          1783703100000,
          4.563
        ],
        [
          1783703400000,
          4.565
        ],
        [
          1783703700000,
          4.565
        ],
        [
          1783704000000,
          4.565
        ],
        [
          1783704300000,
          4.565
        ],
        [
          1783704600000,
          4.565
        ],
        [
          1783704900000,
          4.569
        ],
        [
          1783705200000,
          4.565
        ],
        [
          1783705500000,
          4.567
        ],
        [
          1783705800000,
          4.567
        ],
        [
          1783706100000,
          4.567
        ],
        [
          1783706400000,
          4.569
        ],
        [
          1783706700000,
          4.569
        ],
        [
          1783707000000,
          4.565
        ],
        [
          1783707300000,
          4.569
        ],
        [
          1783707600000,
          4.567
        ],
        [
          1783707900000,
          4.569
        ],
        [
          1783708200000,
          4.569
        ],
        [
          1783708500000,
          4.569
        ],
        [
          1783708800000,
          4.569
        ],
        [
          1783709100000,
          4.569
        ],
        [
          1783709400000,
          4.567
        ],
        [
          1783709700000,
          4.569
        ]
      ],
      "marketState": "UNKNOWN",
      "marketTime": "2026-07-11 03:59 KST",
      "marketTimestamp": 1783709994
    },
    {
      "id": "wti",
      "label": "WTI",
      "symbol": "CL=F",
      "group": "거시 자산",
      "kind": "commodity",
      "decimals": 2,
      "price": 71.41,
      "previousClose": 72.08,
      "change": -0.67,
      "changePercent": -0.9295,
      "tone": "down",
      "direction": "하락",
      "series": [],
      "marketState": "UNKNOWN",
      "marketTime": "2026-07-11 05:59 KST",
      "marketTimestamp": 1783717195
    },
    {
      "id": "gold",
      "label": "Gold",
      "symbol": "GC=F",
      "group": "거시 자산",
      "kind": "commodity",
      "decimals": 2,
      "price": 4113.7,
      "previousClose": 4140.8,
      "change": -27.1,
      "changePercent": -0.6545,
      "tone": "down",
      "direction": "하락",
      "series": [],
      "marketState": "UNKNOWN",
      "marketTime": "2026-07-11 05:59 KST",
      "marketTimestamp": 1783717197
    },
    {
      "id": "bitcoin",
      "label": "Bitcoin",
      "symbol": "BTC-USD",
      "group": "거시 자산",
      "kind": "crypto",
      "decimals": 0,
      "price": 63994.9,
      "previousClose": 63777.508,
      "change": 217.392,
      "changePercent": 0.3409,
      "tone": "up",
      "direction": "상승",
      "series": [
        [
          1783814400000,
          63849.230469
        ],
        [
          1783814700000,
          63751.988281
        ],
        [
          1783815000000,
          63747.320312
        ],
        [
          1783815300000,
          63804.589844
        ],
        [
          1783815600000,
          63787.359375
        ],
        [
          1783815900000,
          63784.171875
        ],
        [
          1783816200000,
          63760.050781
        ],
        [
          1783816500000,
          63707.28125
        ],
        [
          1783816800000,
          63751.578125
        ],
        [
          1783817100000,
          63740.769531
        ],
        [
          1783817400000,
          63791.03125
        ],
        [
          1783817700000,
          63783.71875
        ],
        [
          1783818000000,
          63857.96875
        ],
        [
          1783818300000,
          63903.828125
        ],
        [
          1783818600000,
          63878.359375
        ],
        [
          1783818900000,
          63950.921875
        ],
        [
          1783819200000,
          63918.398438
        ],
        [
          1783819500000,
          63907.328125
        ],
        [
          1783819800000,
          63965.730469
        ],
        [
          1783820100000,
          64034.871094
        ],
        [
          1783820400000,
          64118.0
        ],
        [
          1783820700000,
          64080.578125
        ],
        [
          1783821000000,
          64089.601562
        ],
        [
          1783821300000,
          64085.261719
        ],
        [
          1783821600000,
          64029.859375
        ],
        [
          1783821900000,
          64013.039062
        ],
        [
          1783822200000,
          64013.03125
        ],
        [
          1783822500000,
          64003.910156
        ],
        [
          1783822800000,
          64084.378906
        ],
        [
          1783823100000,
          64074.730469
        ],
        [
          1783823400000,
          64056.71875
        ],
        [
          1783823700000,
          64040.558594
        ],
        [
          1783824000000,
          64044.839844
        ],
        [
          1783824300000,
          64031.96875
        ],
        [
          1783824600000,
          64035.980469
        ],
        [
          1783824900000,
          64031.238281
        ],
        [
          1783825200000,
          64039.941406
        ],
        [
          1783825500000,
          64006.738281
        ],
        [
          1783825800000,
          64056.71875
        ],
        [
          1783826100000,
          64076.628906
        ],
        [
          1783826400000,
          64082.199219
        ],
        [
          1783826700000,
          64088.640625
        ],
        [
          1783827000000,
          64141.320312
        ],
        [
          1783827300000,
          64097.191406
        ],
        [
          1783827600000,
          64130.75
        ],
        [
          1783827900000,
          64146.300781
        ],
        [
          1783828200000,
          64111.25
        ],
        [
          1783828500000,
          64179.359375
        ],
        [
          1783828800000,
          64155.019531
        ],
        [
          1783829100000,
          64141.589844
        ],
        [
          1783829400000,
          64135.089844
        ],
        [
          1783829700000,
          64078.550781
        ],
        [
          1783830000000,
          64081.820312
        ],
        [
          1783830300000,
          64043.109375
        ],
        [
          1783830600000,
          63968.820312
        ],
        [
          1783830900000,
          63951.148438
        ],
        [
          1783831200000,
          63992.011719
        ],
        [
          1783831500000,
          63952.429688
        ],
        [
          1783831800000,
          63947.0
        ],
        [
          1783832100000,
          63962.070312
        ],
        [
          1783832400000,
          63974.449219
        ],
        [
          1783832700000,
          63971.75
        ],
        [
          1783833000000,
          63951.589844
        ],
        [
          1783833300000,
          63909.871094
        ],
        [
          1783833600000,
          63879.53125
        ],
        [
          1783833900000,
          63873.039062
        ],
        [
          1783834200000,
          63889.269531
        ],
        [
          1783834500000,
          63944.070312
        ],
        [
          1783834800000,
          63932.960938
        ],
        [
          1783835100000,
          63932.96875
        ],
        [
          1783835400000,
          63933.699219
        ],
        [
          1783835700000,
          63925.679688
        ],
        [
          1783836000000,
          63834.679688
        ],
        [
          1783836300000,
          63740.0
        ],
        [
          1783836600000,
          63701.691406
        ],
        [
          1783836900000,
          63686.628906
        ],
        [
          1783837200000,
          63725.480469
        ],
        [
          1783837500000,
          63629.980469
        ],
        [
          1783837800000,
          63682.699219
        ],
        [
          1783838100000,
          63692.71875
        ],
        [
          1783838400000,
          63730.800781
        ],
        [
          1783838700000,
          63765.210938
        ],
        [
          1783839000000,
          63725.46875
        ],
        [
          1783839300000,
          63714.75
        ],
        [
          1783839600000,
          63744.371094
        ],
        [
          1783839900000,
          63760.71875
        ],
        [
          1783840200000,
          63774.738281
        ],
        [
          1783840500000,
          63795.0
        ],
        [
          1783840800000,
          63834.808594
        ],
        [
          1783841100000,
          63819.550781
        ],
        [
          1783841400000,
          63841.0
        ],
        [
          1783841700000,
          63816.5
        ],
        [
          1783842000000,
          63820.910156
        ],
        [
          1783842300000,
          63834.128906
        ],
        [
          1783842600000,
          63841.351562
        ],
        [
          1783842900000,
          63843.699219
        ],
        [
          1783843200000,
          63874.71875
        ],
        [
          1783843500000,
          63976.640625
        ],
        [
          1783843800000,
          64005.941406
        ],
        [
          1783844100000,
          63966.050781
        ],
        [
          1783844400000,
          63966.988281
        ],
        [
          1783844700000,
          63952.019531
        ],
        [
          1783845000000,
          63962.070312
        ],
        [
          1783845300000,
          63951.148438
        ],
        [
          1783845600000,
          63965.710938
        ],
        [
          1783845900000,
          63915.078125
        ],
        [
          1783846200000,
          63937.089844
        ],
        [
          1783846500000,
          63940.078125
        ],
        [
          1783846800000,
          63923.421875
        ],
        [
          1783847100000,
          63929.769531
        ],
        [
          1783847400000,
          63840.210938
        ],
        [
          1783847700000,
          63798.929688
        ],
        [
          1783848000000,
          63738.859375
        ],
        [
          1783848300000,
          63789.511719
        ],
        [
          1783848600000,
          63852.441406
        ],
        [
          1783848900000,
          63896.019531
        ],
        [
          1783849200000,
          63961.25
        ],
        [
          1783849500000,
          63942.601562
        ],
        [
          1783849800000,
          63953.710938
        ],
        [
          1783850100000,
          63915.199219
        ],
        [
          1783850400000,
          63897.660156
        ],
        [
          1783850700000,
          63863.339844
        ],
        [
          1783851000000,
          63885.628906
        ],
        [
          1783851300000,
          63868.511719
        ],
        [
          1783851600000,
          63849.238281
        ],
        [
          1783851900000,
          63836.890625
        ],
        [
          1783852200000,
          63860.140625
        ],
        [
          1783852500000,
          63827.398438
        ],
        [
          1783852800000,
          63826.390625
        ],
        [
          1783853100000,
          63809.199219
        ],
        [
          1783853400000,
          63807.628906
        ],
        [
          1783853700000,
          63812.0
        ],
        [
          1783854000000,
          63856.25
        ],
        [
          1783854300000,
          63860.148438
        ],
        [
          1783854600000,
          63798.0
        ],
        [
          1783854900000,
          63847.019531
        ],
        [
          1783855200000,
          63830.128906
        ],
        [
          1783855500000,
          63863.789062
        ],
        [
          1783855800000,
          63938.390625
        ],
        [
          1783856100000,
          63951.171875
        ],
        [
          1783856400000,
          63953.761719
        ],
        [
          1783856700000,
          63973.988281
        ],
        [
          1783857000000,
          63957.988281
        ],
        [
          1783857300000,
          63966.539062
        ],
        [
          1783857600000,
          63932.898438
        ],
        [
          1783857900000,
          63964.820312
        ],
        [
          1783858200000,
          64056.710938
        ],
        [
          1783858500000,
          64009.398438
        ],
        [
          1783858800000,
          63991.210938
        ],
        [
          1783859100000,
          64011.601562
        ],
        [
          1783859400000,
          63996.898438
        ],
        [
          1783859700000,
          63973.878906
        ],
        [
          1783860000000,
          63988.789062
        ],
        [
          1783860300000,
          63994.011719
        ],
        [
          1783860600000,
          64002.410156
        ],
        [
          1783860900000,
          63982.160156
        ],
        [
          1783861200000,
          64011.691406
        ],
        [
          1783861500000,
          64010.480469
        ],
        [
          1783861800000,
          64002.109375
        ],
        [
          1783862100000,
          64042.199219
        ],
        [
          1783862400000,
          63988.0
        ],
        [
          1783862700000,
          64001.121094
        ],
        [
          1783863000000,
          64023.941406
        ],
        [
          1783863300000,
          64002.0
        ],
        [
          1783863600000,
          63999.148438
        ],
        [
          1783863900000,
          63965.71875
        ],
        [
          1783864200000,
          63985.949219
        ],
        [
          1783864500000,
          63980.53125
        ],
        [
          1783864800000,
          63986.839844
        ],
        [
          1783865100000,
          63958.140625
        ],
        [
          1783865400000,
          63934.878906
        ],
        [
          1783865700000,
          63944.300781
        ],
        [
          1783866000000,
          63958.0
        ],
        [
          1783866300000,
          63956.390625
        ],
        [
          1783866600000,
          64014.710938
        ],
        [
          1783866900000,
          64020.320312
        ],
        [
          1783867200000,
          64027.160156
        ],
        [
          1783867500000,
          64146.0
        ],
        [
          1783867800000,
          64173.210938
        ],
        [
          1783868100000,
          64158.640625
        ],
        [
          1783868400000,
          64128.359375
        ],
        [
          1783868700000,
          64139.078125
        ],
        [
          1783869000000,
          64147.71875
        ],
        [
          1783869300000,
          64118.210938
        ],
        [
          1783869600000,
          64153.988281
        ],
        [
          1783869900000,
          64178.0
        ],
        [
          1783870200000,
          64105.71875
        ],
        [
          1783870500000,
          64110.730469
        ],
        [
          1783870800000,
          64104.679688
        ],
        [
          1783871100000,
          64133.160156
        ],
        [
          1783871400000,
          64136.800781
        ],
        [
          1783871700000,
          64136.519531
        ],
        [
          1783872000000,
          64097.050781
        ],
        [
          1783872300000,
          64139.589844
        ],
        [
          1783872600000,
          64030.039062
        ],
        [
          1783872900000,
          64059.890625
        ],
        [
          1783873200000,
          64093.121094
        ],
        [
          1783873500000,
          64137.730469
        ],
        [
          1783873800000,
          64080.558594
        ],
        [
          1783874100000,
          64076.230469
        ],
        [
          1783874400000,
          64079.5
        ],
        [
          1783874700000,
          64102.890625
        ],
        [
          1783875000000,
          64076.25
        ],
        [
          1783875300000,
          64131.789062
        ],
        [
          1783875600000,
          64115.199219
        ],
        [
          1783875900000,
          64120.550781
        ],
        [
          1783876200000,
          64104.148438
        ],
        [
          1783876500000,
          64126.46875
        ],
        [
          1783876800000,
          64088.0
        ],
        [
          1783877100000,
          64087.550781
        ],
        [
          1783877400000,
          64108.441406
        ],
        [
          1783877700000,
          64124.140625
        ],
        [
          1783878000000,
          64115.828125
        ],
        [
          1783878300000,
          64105.078125
        ],
        [
          1783878600000,
          64017.339844
        ],
        [
          1783878900000,
          64034.910156
        ],
        [
          1783879200000,
          64040.550781
        ],
        [
          1783879500000,
          63985.988281
        ],
        [
          1783879800000,
          63996.800781
        ],
        [
          1783880100000,
          63985.980469
        ],
        [
          1783880400000,
          63991.890625
        ],
        [
          1783880700000,
          63996.988281
        ],
        [
          1783880869000,
          63994.898438
        ]
      ],
      "marketState": "UNKNOWN",
      "marketTime": "2026-07-13 03:27 KST",
      "marketTimestamp": 1783880869
    }
  ],
  "mainCharts": [
    {
      "id": "kospi",
      "label": "KOSPI",
      "symbol": "^KS11",
      "group": "국내 지수",
      "kind": "equity",
      "decimals": 2,
      "price": 7475.94,
      "previousClose": 7291.91,
      "change": 184.03,
      "changePercent": 2.5238,
      "tone": "up",
      "direction": "상승",
      "series": [
        [
          1783641600000,
          7534.759766
        ],
        [
          1783641900000,
          7497.100098
        ],
        [
          1783642200000,
          7517.189941
        ],
        [
          1783642500000,
          7493.029785
        ],
        [
          1783642800000,
          7434.22998
        ],
        [
          1783643100000,
          7470.069824
        ],
        [
          1783643400000,
          7451.819824
        ],
        [
          1783643700000,
          7477.169922
        ],
        [
          1783644000000,
          7496.850098
        ],
        [
          1783644300000,
          7493.220215
        ],
        [
          1783644600000,
          7521.649902
        ],
        [
          1783644900000,
          7545.890137
        ],
        [
          1783645200000,
          7520.080078
        ],
        [
          1783645500000,
          7537.109863
        ],
        [
          1783645800000,
          7531.950195
        ],
        [
          1783646100000,
          7548.959961
        ],
        [
          1783646400000,
          7581.390137
        ],
        [
          1783646700000,
          7573.220215
        ],
        [
          1783647000000,
          7620.069824
        ],
        [
          1783647300000,
          7632.899902
        ],
        [
          1783647600000,
          7615.02002
        ],
        [
          1783647900000,
          7636.459961
        ],
        [
          1783648200000,
          7588.299805
        ],
        [
          1783648500000,
          7585.549805
        ],
        [
          1783648800000,
          7572.25
        ],
        [
          1783649100000,
          7554.759766
        ],
        [
          1783649400000,
          7549.160156
        ],
        [
          1783649700000,
          7556.350098
        ],
        [
          1783650000000,
          7534.419922
        ],
        [
          1783650300000,
          7555.959961
        ],
        [
          1783650600000,
          7592.620117
        ],
        [
          1783650900000,
          7583.27002
        ],
        [
          1783651200000,
          7585.120117
        ],
        [
          1783651500000,
          7595.649902
        ],
        [
          1783651800000,
          7583.390137
        ],
        [
          1783652100000,
          7608.720215
        ],
        [
          1783652400000,
          7599.279785
        ],
        [
          1783652700000,
          7614.310059
        ],
        [
          1783653000000,
          7607.669922
        ],
        [
          1783653300000,
          7625.859863
        ],
        [
          1783653600000,
          7624.399902
        ],
        [
          1783653900000,
          7606.580078
        ],
        [
          1783654200000,
          7610.069824
        ],
        [
          1783654500000,
          7630.02002
        ],
        [
          1783654800000,
          7636.689941
        ],
        [
          1783655100000,
          7628.049805
        ],
        [
          1783655400000,
          7654.629883
        ],
        [
          1783655700000,
          7660.100098
        ],
        [
          1783656000000,
          7676.680176
        ],
        [
          1783656300000,
          7687.060059
        ],
        [
          1783656600000,
          7692.560059
        ],
        [
          1783656900000,
          7696.549805
        ],
        [
          1783657200000,
          7667.669922
        ],
        [
          1783657500000,
          7675.490234
        ],
        [
          1783657800000,
          7649.169922
        ],
        [
          1783658100000,
          7677.209961
        ],
        [
          1783658400000,
          7686.169922
        ],
        [
          1783658700000,
          7681.450195
        ],
        [
          1783659000000,
          7641.290039
        ],
        [
          1783659300000,
          7626.120117
        ],
        [
          1783659600000,
          7610.899902
        ],
        [
          1783659900000,
          7586.279785
        ],
        [
          1783660200000,
          7628.970215
        ],
        [
          1783660500000,
          7622.819824
        ],
        [
          1783660800000,
          7631.189941
        ],
        [
          1783661100000,
          7613.810059
        ],
        [
          1783661400000,
          7621.959961
        ],
        [
          1783661700000,
          7600.589844
        ],
        [
          1783662000000,
          7578.370117
        ],
        [
          1783662300000,
          7593.580078
        ],
        [
          1783662600000,
          7585.490234
        ],
        [
          1783662900000,
          7581.350098
        ],
        [
          1783663200000,
          7475.939941
        ]
      ],
      "marketState": "UNKNOWN",
      "marketTime": "2026-07-10 18:05 KST",
      "marketTimestamp": 1783674340
    },
    {
      "id": "kosdaq",
      "label": "KOSDAQ",
      "symbol": "^KQ11",
      "group": "국내 지수",
      "kind": "equity",
      "decimals": 2,
      "price": 837.43,
      "previousClose": 794.0,
      "change": 43.43,
      "changePercent": 5.4698,
      "tone": "up",
      "direction": "상승",
      "series": [
        [
          1783641600000,
          804.309998
        ],
        [
          1783641900000,
          810.22998
        ],
        [
          1783642200000,
          812.380005
        ],
        [
          1783642500000,
          813.409973
        ],
        [
          1783642800000,
          809.200012
        ],
        [
          1783643100000,
          817.909973
        ],
        [
          1783643400000,
          814.039978
        ],
        [
          1783643700000,
          820.080017
        ],
        [
          1783644000000,
          826.349976
        ],
        [
          1783644300000,
          827.900024
        ],
        [
          1783644600000,
          826.72998
        ],
        [
          1783644900000,
          826.190002
        ],
        [
          1783645200000,
          828.940002
        ],
        [
          1783645500000,
          827.830017
        ],
        [
          1783645800000,
          833.289978
        ],
        [
          1783646100000,
          836.77002
        ],
        [
          1783646400000,
          832.380005
        ],
        [
          1783646700000,
          836.320007
        ],
        [
          1783647000000,
          834.119995
        ],
        [
          1783647300000,
          835.590027
        ],
        [
          1783647600000,
          838.400024
        ],
        [
          1783647900000,
          841.27002
        ],
        [
          1783648200000,
          837.419983
        ],
        [
          1783648500000,
          836.599976
        ],
        [
          1783648800000,
          835.01001
        ],
        [
          1783649100000,
          836.299988
        ],
        [
          1783649400000,
          832.840027
        ],
        [
          1783649700000,
          836.390015
        ],
        [
          1783650000000,
          836.580017
        ],
        [
          1783650300000,
          838.119995
        ],
        [
          1783650600000,
          842.390015
        ],
        [
          1783650900000,
          842.929993
        ],
        [
          1783651200000,
          843.169983
        ],
        [
          1783651500000,
          843.590027
        ],
        [
          1783651800000,
          842.409973
        ],
        [
          1783652100000,
          843.280029
        ],
        [
          1783652400000,
          843.330017
        ],
        [
          1783652700000,
          844.190002
        ],
        [
          1783653000000,
          844.940002
        ],
        [
          1783653300000,
          845.200012
        ],
        [
          1783653600000,
          842.679993
        ],
        [
          1783653900000,
          841.380005
        ],
        [
          1783654200000,
          841.619995
        ],
        [
          1783654500000,
          841.950012
        ],
        [
          1783654800000,
          843.97998
        ],
        [
          1783655100000,
          843.349976
        ],
        [
          1783655400000,
          842.169983
        ],
        [
          1783655700000,
          841.929993
        ],
        [
          1783656000000,
          844.570007
        ],
        [
          1783656300000,
          843.969971
        ],
        [
          1783656600000,
          844.679993
        ],
        [
          1783656900000,
          843.849976
        ],
        [
          1783657200000,
          843.700012
        ],
        [
          1783657500000,
          844.450012
        ],
        [
          1783657800000,
          843.580017
        ],
        [
          1783658100000,
          843.669983
        ],
        [
          1783658400000,
          843.52002
        ],
        [
          1783658700000,
          842.090027
        ],
        [
          1783659000000,
          840.0
        ],
        [
          1783659300000,
          839.5
        ],
        [
          1783659600000,
          838.150024
        ],
        [
          1783659900000,
          835.909973
        ],
        [
          1783660200000,
          840.030029
        ],
        [
          1783660500000,
          840.409973
        ],
        [
          1783660800000,
          841.900024
        ],
        [
          1783661100000,
          840.98999
        ],
        [
          1783661400000,
          841.210022
        ],
        [
          1783661700000,
          839.539978
        ],
        [
          1783662000000,
          838.950012
        ],
        [
          1783662300000,
          843.849976
        ],
        [
          1783662600000,
          843.280029
        ],
        [
          1783662900000,
          843.47998
        ],
        [
          1783663200000,
          837.429993
        ]
      ],
      "marketState": "UNKNOWN",
      "marketTime": "2026-07-10 18:05 KST",
      "marketTimestamp": 1783674340
    },
    {
      "id": "sp500",
      "label": "S&P 500",
      "symbol": "^GSPC",
      "group": "해외 지수",
      "kind": "equity",
      "decimals": 2,
      "price": 7575.39,
      "previousClose": 7543.64,
      "change": 31.75,
      "changePercent": 0.4209,
      "tone": "up",
      "direction": "상승",
      "series": [
        [
          1783690200000,
          7553.299805
        ],
        [
          1783690500000,
          7551.839844
        ],
        [
          1783690800000,
          7548.080078
        ],
        [
          1783691100000,
          7556.870117
        ],
        [
          1783691400000,
          7556.160156
        ],
        [
          1783691700000,
          7555.359863
        ],
        [
          1783692000000,
          7557.600098
        ],
        [
          1783692300000,
          7557.5
        ],
        [
          1783692600000,
          7553.47998
        ],
        [
          1783692900000,
          7552.109863
        ],
        [
          1783693200000,
          7551.379883
        ],
        [
          1783693500000,
          7552.120117
        ],
        [
          1783693800000,
          7534.660156
        ],
        [
          1783694100000,
          7543.0
        ],
        [
          1783694400000,
          7547.450195
        ],
        [
          1783694700000,
          7549.77002
        ],
        [
          1783695000000,
          7545.189941
        ],
        [
          1783695300000,
          7538.129883
        ],
        [
          1783695600000,
          7535.5
        ],
        [
          1783695900000,
          7542.919922
        ],
        [
          1783696200000,
          7544.819824
        ],
        [
          1783696500000,
          7553.259766
        ],
        [
          1783696800000,
          7556.700195
        ],
        [
          1783697100000,
          7558.72998
        ],
        [
          1783697400000,
          7556.410156
        ],
        [
          1783697700000,
          7550.200195
        ],
        [
          1783698000000,
          7546.549805
        ],
        [
          1783698300000,
          7551.120117
        ],
        [
          1783698600000,
          7554.459961
        ],
        [
          1783698900000,
          7554.279785
        ],
        [
          1783699200000,
          7558.100098
        ],
        [
          1783699500000,
          7555.779785
        ],
        [
          1783699800000,
          7558.319824
        ],
        [
          1783700100000,
          7562.029785
        ],
        [
          1783700400000,
          7560.25
        ],
        [
          1783700700000,
          7558.240234
        ],
        [
          1783701000000,
          7561.549805
        ],
        [
          1783701300000,
          7559.169922
        ],
        [
          1783701600000,
          7562.430176
        ],
        [
          1783701900000,
          7564.700195
        ],
        [
          1783702200000,
          7566.339844
        ],
        [
          1783702500000,
          7566.379883
        ],
        [
          1783702800000,
          7563.27002
        ],
        [
          1783703100000,
          7562.560059
        ],
        [
          1783703400000,
          7564.160156
        ],
        [
          1783703700000,
          7564.890137
        ],
        [
          1783704000000,
          7565.669922
        ],
        [
          1783704300000,
          7566.290039
        ],
        [
          1783704600000,
          7566.609863
        ],
        [
          1783704900000,
          7568.899902
        ],
        [
          1783705200000,
          7567.939941
        ],
        [
          1783705500000,
          7569.27002
        ],
        [
          1783705800000,
          7568.830078
        ],
        [
          1783706100000,
          7566.439941
        ],
        [
          1783706400000,
          7566.740234
        ],
        [
          1783706700000,
          7568.930176
        ],
        [
          1783707000000,
          7569.299805
        ],
        [
          1783707300000,
          7568.379883
        ],
        [
          1783707600000,
          7569.669922
        ],
        [
          1783707900000,
          7570.379883
        ],
        [
          1783708200000,
          7571.740234
        ],
        [
          1783708500000,
          7570.25
        ],
        [
          1783708800000,
          7571.100098
        ],
        [
          1783709100000,
          7570.970215
        ],
        [
          1783709400000,
          7571.779785
        ],
        [
          1783709700000,
          7571.259766
        ],
        [
          1783710000000,
          7575.839844
        ],
        [
          1783710300000,
          7575.330078
        ],
        [
          1783710600000,
          7577.439941
        ],
        [
          1783710900000,
          7576.470215
        ],
        [
          1783711200000,
          7575.609863
        ],
        [
          1783711500000,
          7575.640137
        ],
        [
          1783711800000,
          7575.799805
        ],
        [
          1783712100000,
          7576.859863
        ],
        [
          1783712400000,
          7576.540039
        ],
        [
          1783712700000,
          7577.390137
        ],
        [
          1783713000000,
          7577.319824
        ],
        [
          1783713300000,
          7575.379883
        ],
        [
          1783713600000,
          7575.390137
        ]
      ],
      "marketState": "UNKNOWN",
      "marketTime": "2026-07-11 06:28 KST",
      "marketTimestamp": 1783718910
    },
    {
      "id": "nasdaq",
      "label": "NASDAQ",
      "symbol": "^IXIC",
      "group": "해외 지수",
      "kind": "equity",
      "decimals": 2,
      "price": 26281.607,
      "previousClose": 26206.9,
      "change": 74.707,
      "changePercent": 0.2851,
      "tone": "up",
      "direction": "상승",
      "series": [
        [
          1783690200000,
          26237.296875
        ],
        [
          1783690500000,
          26194.166016
        ],
        [
          1783690800000,
          26169.138672
        ],
        [
          1783691100000,
          26224.751953
        ],
        [
          1783691400000,
          26227.886719
        ],
        [
          1783691700000,
          26211.619141
        ],
        [
          1783692000000,
          26210.113281
        ],
        [
          1783692300000,
          26219.107422
        ],
        [
          1783692600000,
          26207.419922
        ],
        [
          1783692900000,
          26180.65625
        ],
        [
          1783693200000,
          26167.191406
        ],
        [
          1783693500000,
          26184.652344
        ],
        [
          1783693800000,
          26125.863281
        ],
        [
          1783694100000,
          26149.267578
        ],
        [
          1783694400000,
          26155.357422
        ],
        [
          1783694700000,
          26167.560547
        ],
        [
          1783695000000,
          26132.304688
        ],
        [
          1783695300000,
          26106.925781
        ],
        [
          1783695600000,
          26087.427734
        ],
        [
          1783695900000,
          26132.957031
        ],
        [
          1783696200000,
          26140.996094
        ],
        [
          1783696500000,
          26182.988281
        ],
        [
          1783696800000,
          26202.013672
        ],
        [
          1783697100000,
          26221.099609
        ],
        [
          1783697400000,
          26226.037109
        ],
        [
          1783697700000,
          26187.320312
        ],
        [
          1783698000000,
          26156.408203
        ],
        [
          1783698300000,
          26188.621094
        ],
        [
          1783698600000,
          26202.625
        ],
        [
          1783698900000,
          26208.773438
        ],
        [
          1783699200000,
          26228.994141
        ],
        [
          1783699500000,
          26221.070312
        ],
        [
          1783699800000,
          26229.009766
        ],
        [
          1783700100000,
          26258.222656
        ],
        [
          1783700400000,
          26261.074219
        ],
        [
          1783700700000,
          26251.314453
        ],
        [
          1783701000000,
          26268.648438
        ],
        [
          1783701300000,
          26257.054688
        ],
        [
          1783701600000,
          26264.5
        ],
        [
          1783701900000,
          26271.085938
        ],
        [
          1783702200000,
          26275.210938
        ],
        [
          1783702500000,
          26271.880859
        ],
        [
          1783702800000,
          26258.451172
        ],
        [
          1783703100000,
          26250.376953
        ],
        [
          1783703400000,
          26251.277344
        ],
        [
          1783703700000,
          26254.173828
        ],
        [
          1783704000000,
          26264.320312
        ],
        [
          1783704300000,
          26269.529297
        ],
        [
          1783704600000,
          26265.498047
        ],
        [
          1783704900000,
          26277.652344
        ],
        [
          1783705200000,
          26272.921875
        ],
        [
          1783705500000,
          26277.589844
        ],
        [
          1783705800000,
          26274.234375
        ],
        [
          1783706100000,
          26265.457031
        ],
        [
          1783706400000,
          26272.638672
        ],
        [
          1783706700000,
          26278.482422
        ],
        [
          1783707000000,
          26280.011719
        ],
        [
          1783707300000,
          26272.582031
        ],
        [
          1783707600000,
          26282.263672
        ],
        [
          1783707900000,
          26284.617188
        ],
        [
          1783708200000,
          26289.923828
        ],
        [
          1783708500000,
          26278.541016
        ],
        [
          1783708800000,
          26280.914062
        ],
        [
          1783709100000,
          26272.097656
        ],
        [
          1783709400000,
          26275.578125
        ],
        [
          1783709700000,
          26272.650391
        ],
        [
          1783710000000,
          26296.84375
        ],
        [
          1783710300000,
          26287.398438
        ],
        [
          1783710600000,
          26293.640625
        ],
        [
          1783710900000,
          26290.042969
        ],
        [
          1783711200000,
          26283.642578
        ],
        [
          1783711500000,
          26285.320312
        ],
        [
          1783711800000,
          26288.074219
        ],
        [
          1783712100000,
          26291.091797
        ],
        [
          1783712400000,
          26287.628906
        ],
        [
          1783712700000,
          26287.798828
        ],
        [
          1783713000000,
          26283.367188
        ],
        [
          1783713300000,
          26278.699219
        ],
        [
          1783713600000,
          26281.607422
        ]
      ],
      "marketState": "UNKNOWN",
      "marketTime": "2026-07-11 06:15 KST",
      "marketTimestamp": 1783718159
    }
  ],
  "headlines": [
    {
      "title": "[사설] 하이닉스 美 상장 성공이 ‘도박판 증시’ 한국에 던진 경고",
      "source": "조선일보",
      "link": "https://news.google.com/rss/articles/CBMihgFBVV95cUxOT2Jha1RXdUMwVEJNZ2swRmR3ZmR2Nk4yTWJpbUJxeVpwZzZFNnY0Qlo0aWlsUFF5a1JYLURvZUktanhrNlVZRmFINWl5amF2czlZU1R5MDd6aEozTHMwSXc5bldDdW1XTG4wRHZnbGtBMjFJaFE5Sm1sU1dRVGxzeUJKRm9DQQ?oc=5",
      "publishedAt": "Sun, 12 Jul 2026 15:20:00 GMT"
    },
    {
      "title": "한국 증시, 사상 최저 밸류에이션…AI 실적 호조 속 투자 기회로 부각",
      "source": "Investing.com 한국어",
      "link": "https://news.google.com/rss/articles/CBMicEFVX3lxTFBKU2MzWWtOWW9ZclVyU0VGZGswRWllSVBTb0pUSFA4Tzk2SGdZc3FySG1ocDdCWFlqaENQSWNFUHF1NmpETHZsTEJMVUhqNXFvX1VDLVNXVy14S3Q5OVpMTEFmTUctZXBKenZVVVRoNVY?oc=5",
      "publishedAt": "Sun, 12 Jul 2026 03:25:00 GMT"
    },
    {
      "title": "SK하이닉스, 나스닥서 12.8% 상승… 40조원 조달 효과, 한국 증시·환율로 번질까",
      "source": "S저널",
      "link": "https://news.google.com/rss/articles/CBMibkFVX3lxTE81SXE0THg2WjgzeWw1QzZwVXN3T2RJZUYzUG9EdXZVaFF2eUlNc1E0VHp0MnNvNTJQRWtSdnRyNDBKUjZCb3ptU2N6ak5TUHJGV2FWQ0ZYTFF4YzREM1ZBbHhmcGQ0Z21qb0dmTTB3?oc=5",
      "publishedAt": "Sun, 12 Jul 2026 04:56:07 GMT"
    },
    {
      "title": "환율·채권, 하이닉스 미국 상장發 달러유입 기대",
      "source": "한국경제",
      "link": "https://news.google.com/rss/articles/CBMiWkFVX3lxTFBzWWd5bUZNU09CbVNtLXdMdTAwMEhqaWR4MGlXNzZhd1JQNGpjVTlPeGMyNEc4Ym05TjhTTXB5MnVIX1J3YnExV2JNalY3cVZvZjdrY0xVeGpvUdIBVEFVX3lxTFBWU2ZYSDJiS2xYOWx0X1lMcURhSm1NdHVpcXVWb3ZEaEU5Njg3THViUDFDZk1rZEpPdDB3ZXUtOFVWZW5GY1dULTcybkpfQmNfanpnSA?oc=5",
      "publishedAt": "Sun, 12 Jul 2026 08:22:20 GMT"
    },
    {
      "title": "미국 하이닉스 주가, 한국보다 16% 높아…한국 주식 오를까",
      "source": "부산일보",
      "link": "https://news.google.com/rss/articles/CBMidEFVX3lxTFA1blBmcFBCS19XWXp0aUhJeHVNSzdJRm1oU3BucDB4MDJ3YmlRSUo4NHk1OXliZU1xcE5DY2lCTEN3dUxEWDA5TlY0cElKeWZqVURlb2ktd1VHUnRtT0lSNjdvNjF6WkpqMHRvR2xZcjBhalZ5?oc=5",
      "publishedAt": "Sun, 12 Jul 2026 06:01:30 GMT"
    },
    {
      "title": "SK하이닉스 나스닥 상장 흥행대박…국내 증시 온기로 이어질까",
      "source": "연합뉴스",
      "link": "https://news.google.com/rss/articles/CBMiW0FVX3lxTE5DQTRmZmNJX3BTT1hyVkFJR0hUV3JDbVlGWFduQWFoZWVud2pRQUhVQXhjNzlrR2pFejFaaklNRDFtSXJZZkNNTnJSazRkQjg1OGxlTGk3MFVEWTDSAWBBVV95cUxPbHhUYjl2UEs0QS1lZEd1UURESEZzOWZad0JKRlNHX211SEtQVFhJT0RHNVZ5dXM0MmprRXZYR3l5MDVaa2IxdTAwU2h6LUVYSzNVTldJcjliY0ctOWlGeWU?oc=5",
      "publishedAt": "Sat, 11 Jul 2026 21:05:02 GMT"
    },
    {
      "title": "반도체 피크아웃 우려 씻어… 코스피 투심 회복 관심",
      "source": "국민일보",
      "link": "https://news.google.com/rss/articles/CBMibEFVX3lxTFBmTm5XejNyYkEzalZtMVpRdXFsNWF3WmJBLTVLY2FoRFdUMmFZMjZuLXJfc3FfYjhLc3Rscm9aRFRGandwQmhIVHgybkxBODRBTXdSWjBYeEdqbVJkR2U0RV9wa2NLNGNoRXI2bdIBbEFVX3lxTFBmTm5XejNyYkEzalZtMVpRdXFsNWF3WmJBLTVLY2FoRFdUMmFZMjZuLXJfc3FfYjhLc3Rscm9aRFRGandwQmhIVHgybkxBODRBTXdSWjBYeEdqbVJkR2U0RV9wa2NLNGNoRXI2bQ?oc=5",
      "publishedAt": "Sun, 12 Jul 2026 10:25:00 GMT"
    },
    {
      "title": "美서 16% 비싸진 SK하이닉스…ADR 격차에 국내 증시 변동성 확대되나",
      "source": "브릿지경제",
      "link": "https://news.google.com/rss/articles/CBMiWkFVX3lxTE1qckJ3NlQzTlZuNDhOZkJ0eXpBLUh1YmU3V2ZkazZkeHlwSjhFcm9kNXU5NFdVOXpxLWpxRDl2eGFVbVZWd3FmOGxIZmh2dmZvcjlBeU1nMFRidw?oc=5",
      "publishedAt": "Sun, 12 Jul 2026 10:51:00 GMT"
    }
  ],
  "summary": {
    "signal": {
      "label": "Risk-On",
      "tone": "up",
      "message": "주식과 위험자산 강세가 우세합니다."
    },
    "overview": [
      "국내장은 KOSPI 상승, KOSDAQ 상승 흐름입니다.",
      "해외는 S&P 500 +0.42%, NASDAQ +0.29%로 확인됩니다.",
      "매크로 변수는 USD/KRW -0.51%, 미 10년물 +0.66%입니다."
    ],
    "checkpoints": [
      "KOSPI +2.52% 상승",
      "KOSDAQ +5.47% 상승",
      "미국 증시 상승 / 나스닥 +0.29%",
      "원달러 -0.51% (-7.61)",
      "미 10년물 +0.030p (+0.66%)"
    ],
    "leaders": [
      {
        "label": "KOSDAQ",
        "changePercent": 5.4698,
        "direction": "상승"
      },
      {
        "label": "KOSPI",
        "changePercent": 2.5238,
        "direction": "상승"
      },
      {
        "label": "S&P 500",
        "changePercent": 0.4209,
        "direction": "상승"
      }
    ],
    "laggards": [
      {
        "label": "WTI",
        "changePercent": -0.9295,
        "direction": "하락"
      },
      {
        "label": "Gold",
        "changePercent": -0.6545,
        "direction": "하락"
      },
      {
        "label": "USD/KRW",
        "changePercent": -0.5052,
        "direction": "하락"
      }
    ]
  },
  "errors": []
}