{
  "updatedAt": "2026-06-01T16:04:07.176944+09:00",
  "updatedLabel": "2026-06-01 16:04:07 KST",
  "groups": [
    "국내 지수",
    "해외 지수",
    "거시 자산"
  ],
  "cards": [
    {
      "id": "kospi",
      "label": "KOSPI",
      "symbol": "^KS11",
      "group": "국내 지수",
      "kind": "equity",
      "decimals": 2,
      "price": 8788.38,
      "previousClose": 8476.15,
      "change": 312.23,
      "changePercent": 3.6836,
      "tone": "up",
      "direction": "상승",
      "series": [
        [
          1780272000000,
          8585.730469
        ],
        [
          1780272300000,
          8583.5
        ],
        [
          1780272600000,
          8587.080078
        ],
        [
          1780272900000,
          8552.799805
        ],
        [
          1780273200000,
          8613.459961
        ],
        [
          1780273500000,
          8628.80957
        ],
        [
          1780273800000,
          8640.209961
        ],
        [
          1780274100000,
          8691.830078
        ],
        [
          1780274400000,
          8689.419922
        ],
        [
          1780274700000,
          8672.570312
        ],
        [
          1780275000000,
          8647.740234
        ],
        [
          1780275300000,
          8672.169922
        ],
        [
          1780275600000,
          8708.070312
        ],
        [
          1780275900000,
          8712.080078
        ],
        [
          1780276200000,
          8715.629883
        ],
        [
          1780276500000,
          8726.860352
        ],
        [
          1780276800000,
          8741.419922
        ],
        [
          1780277100000,
          8747.110352
        ],
        [
          1780277400000,
          8765.969727
        ],
        [
          1780277700000,
          8785.580078
        ],
        [
          1780278000000,
          8795.200195
        ],
        [
          1780278300000,
          8821.870117
        ],
        [
          1780278600000,
          8826.610352
        ],
        [
          1780278900000,
          8837.290039
        ],
        [
          1780279200000,
          8835.25
        ],
        [
          1780279500000,
          8846.650391
        ],
        [
          1780279800000,
          8850.389648
        ],
        [
          1780280100000,
          8845.290039
        ],
        [
          1780280400000,
          8844.209961
        ],
        [
          1780280700000,
          8866.639648
        ],
        [
          1780281000000,
          8842.089844
        ],
        [
          1780281300000,
          8869.230469
        ],
        [
          1780281600000,
          8847.790039
        ],
        [
          1780281900000,
          8828.919922
        ],
        [
          1780282200000,
          8825.05957
        ],
        [
          1780282500000,
          8849.19043
        ],
        [
          1780282800000,
          8863.759766
        ],
        [
          1780283100000,
          8865.469727
        ],
        [
          1780283400000,
          8864.360352
        ],
        [
          1780283700000,
          8864.269531
        ],
        [
          1780284000000,
          8860.650391
        ],
        [
          1780284300000,
          8860.530273
        ],
        [
          1780284600000,
          8860.400391
        ],
        [
          1780284900000,
          8859.740234
        ],
        [
          1780285200000,
          8835.839844
        ],
        [
          1780285500000,
          8841.459961
        ],
        [
          1780285800000,
          8822.889648
        ],
        [
          1780286100000,
          8820.219727
        ],
        [
          1780286400000,
          8840.30957
        ],
        [
          1780286700000,
          8838.320312
        ],
        [
          1780287000000,
          8850.080078
        ],
        [
          1780287300000,
          8848.860352
        ],
        [
          1780287600000,
          8844.049805
        ],
        [
          1780287900000,
          8848.94043
        ],
        [
          1780288200000,
          8852.049805
        ],
        [
          1780288500000,
          8851.849609
        ],
        [
          1780288800000,
          8855.080078
        ],
        [
          1780289100000,
          8852.669922
        ],
        [
          1780289400000,
          8856.700195
        ],
        [
          1780289700000,
          8863.730469
        ],
        [
          1780290000000,
          8853.990234
        ],
        [
          1780290300000,
          8842.480469
        ],
        [
          1780290600000,
          8834.370117
        ],
        [
          1780290900000,
          8823.009766
        ],
        [
          1780291200000,
          8801.269531
        ],
        [
          1780291500000,
          8739.769531
        ],
        [
          1780291800000,
          8748.860352
        ],
        [
          1780292100000,
          8776.929688
        ],
        [
          1780292400000,
          8810.049805
        ],
        [
          1780292700000,
          8826.450195
        ],
        [
          1780293000000,
          8811.759766
        ],
        [
          1780293300000,
          8820.05957
        ],
        [
          1780293600000,
          8788.379883
        ]
      ],
      "marketState": "UNKNOWN",
      "marketTime": "2026-06-01 15:33 KST",
      "marketTimestamp": 1780295580
    },
    {
      "id": "kosdaq",
      "label": "KOSDAQ",
      "symbol": "^KQ11",
      "group": "국내 지수",
      "kind": "equity",
      "decimals": 2,
      "price": 1050.03,
      "previousClose": 1074.8,
      "change": -24.77,
      "changePercent": -2.3046,
      "tone": "down",
      "direction": "하락",
      "series": [
        [
          1780272000000,
          1055.890015
        ],
        [
          1780272300000,
          1052.849976
        ],
        [
          1780272600000,
          1050.439941
        ],
        [
          1780272900000,
          1068.75
        ],
        [
          1780273200000,
          1073.530029
        ],
        [
          1780273500000,
          1081.400024
        ],
        [
          1780273800000,
          1077.699951
        ],
        [
          1780274100000,
          1070.829956
        ],
        [
          1780274400000,
          1068.130005
        ],
        [
          1780274700000,
          1064.959961
        ],
        [
          1780275000000,
          1063.199951
        ],
        [
          1780275300000,
          1067.180054
        ],
        [
          1780275600000,
          1061.52002
        ],
        [
          1780275900000,
          1059.560059
        ],
        [
          1780276200000,
          1057.890015
        ],
        [
          1780276500000,
          1056.920044
        ],
        [
          1780276800000,
          1059.560059
        ],
        [
          1780277100000,
          1058.310059
        ],
        [
          1780277400000,
          1054.76001
        ],
        [
          1780277700000,
          1056.079956
        ],
        [
          1780278000000,
          1056.0
        ],
        [
          1780278300000,
          1052.47998
        ],
        [
          1780278600000,
          1052.069946
        ],
        [
          1780278900000,
          1050.140015
        ],
        [
          1780279200000,
          1050.180054
        ],
        [
          1780279500000,
          1051.709961
        ],
        [
          1780279800000,
          1050.880005
        ],
        [
          1780280100000,
          1052.27002
        ],
        [
          1780280400000,
          1054.060059
        ],
        [
          1780280700000,
          1052.349976
        ],
        [
          1780281000000,
          1052.089966
        ],
        [
          1780281300000,
          1051.02002
        ],
        [
          1780281600000,
          1050.97998
        ],
        [
          1780281900000,
          1052.630005
        ],
        [
          1780282200000,
          1053.73999
        ],
        [
          1780282500000,
          1052.189941
        ],
        [
          1780282800000,
          1050.699951
        ],
        [
          1780283100000,
          1050.810059
        ],
        [
          1780283400000,
          1050.98999
        ],
        [
          1780283700000,
          1050.619995
        ],
        [
          1780284000000,
          1050.079956
        ],
        [
          1780284300000,
          1049.099976
        ],
        [
          1780284600000,
          1050.699951
        ],
        [
          1780284900000,
          1049.099976
        ],
        [
          1780285200000,
          1049.5
        ],
        [
          1780285500000,
          1050.599976
        ],
        [
          1780285800000,
          1050.079956
        ],
        [
          1780286100000,
          1049.23999
        ],
        [
          1780286400000,
          1048.439941
        ],
        [
          1780286700000,
          1047.790039
        ],
        [
          1780287000000,
          1048.0
        ],
        [
          1780287300000,
          1046.97998
        ],
        [
          1780287600000,
          1046.630005
        ],
        [
          1780287900000,
          1046.589966
        ],
        [
          1780288200000,
          1046.829956
        ],
        [
          1780288500000,
          1046.01001
        ],
        [
          1780288800000,
          1048.290039
        ],
        [
          1780289100000,
          1046.680054
        ],
        [
          1780289400000,
          1045.630005
        ],
        [
          1780289700000,
          1044.839966
        ],
        [
          1780290000000,
          1044.319946
        ],
        [
          1780290300000,
          1047.959961
        ],
        [
          1780290600000,
          1050.069946
        ],
        [
          1780290900000,
          1047.890015
        ],
        [
          1780291200000,
          1051.76001
        ],
        [
          1780291500000,
          1050.76001
        ],
        [
          1780291800000,
          1051.280029
        ],
        [
          1780292100000,
          1051.530029
        ],
        [
          1780292400000,
          1049.949951
        ],
        [
          1780292700000,
          1050.339966
        ],
        [
          1780293000000,
          1049.280029
        ],
        [
          1780293300000,
          1048.47998
        ],
        [
          1780293600000,
          1050.030029
        ]
      ],
      "marketState": "UNKNOWN",
      "marketTime": "2026-06-01 15:33 KST",
      "marketTimestamp": 1780295580
    },
    {
      "id": "sp500",
      "label": "S&P 500",
      "symbol": "^GSPC",
      "group": "해외 지수",
      "kind": "equity",
      "decimals": 2,
      "price": 7580.06,
      "previousClose": 7563.63,
      "change": 16.43,
      "changePercent": 0.2172,
      "tone": "up",
      "direction": "상승",
      "series": [
        [
          1780061400000,
          7578.290039
        ],
        [
          1780061700000,
          7585.27002
        ],
        [
          1780062000000,
          7593.390137
        ],
        [
          1780062300000,
          7594.939941
        ],
        [
          1780062600000,
          7597.069824
        ],
        [
          1780062900000,
          7596.390137
        ],
        [
          1780063200000,
          7595.25
        ],
        [
          1780063500000,
          7590.660156
        ],
        [
          1780063800000,
          7590.350098
        ],
        [
          1780064100000,
          7585.330078
        ],
        [
          1780064400000,
          7579.919922
        ],
        [
          1780064700000,
          7583.740234
        ],
        [
          1780065000000,
          7587.140137
        ],
        [
          1780065300000,
          7573.450195
        ],
        [
          1780065600000,
          7568.529785
        ],
        [
          1780065900000,
          7567.080078
        ],
        [
          1780066200000,
          7575.52002
        ],
        [
          1780066500000,
          7577.660156
        ],
        [
          1780066800000,
          7580.77002
        ],
        [
          1780067100000,
          7584.529785
        ],
        [
          1780067400000,
          7591.029785
        ],
        [
          1780067700000,
          7586.379883
        ],
        [
          1780068000000,
          7586.629883
        ],
        [
          1780068300000,
          7587.160156
        ],
        [
          1780068600000,
          7587.859863
        ],
        [
          1780068900000,
          7588.490234
        ],
        [
          1780069200000,
          7584.379883
        ],
        [
          1780069500000,
          7584.049805
        ],
        [
          1780069800000,
          7584.140137
        ],
        [
          1780070100000,
          7581.200195
        ],
        [
          1780070400000,
          7586.390137
        ],
        [
          1780070700000,
          7590.040039
        ],
        [
          1780071000000,
          7590.700195
        ],
        [
          1780071300000,
          7585.470215
        ],
        [
          1780071600000,
          7587.220215
        ],
        [
          1780071900000,
          7584.359863
        ],
        [
          1780072200000,
          7589.75
        ],
        [
          1780072500000,
          7593.919922
        ],
        [
          1780072800000,
          7591.950195
        ],
        [
          1780073100000,
          7589.350098
        ],
        [
          1780073400000,
          7586.839844
        ],
        [
          1780073700000,
          7585.620117
        ],
        [
          1780074000000,
          7583.419922
        ],
        [
          1780074300000,
          7585.22998
        ],
        [
          1780074600000,
          7584.430176
        ],
        [
          1780074900000,
          7585.399902
        ],
        [
          1780075200000,
          7584.029785
        ],
        [
          1780075500000,
          7583.319824
        ],
        [
          1780075800000,
          7582.660156
        ],
        [
          1780076100000,
          7580.759766
        ],
        [
          1780076400000,
          7577.669922
        ],
        [
          1780076700000,
          7577.839844
        ],
        [
          1780077000000,
          7575.970215
        ],
        [
          1780077300000,
          7569.919922
        ],
        [
          1780077600000,
          7574.629883
        ],
        [
          1780077900000,
          7576.759766
        ],
        [
          1780078200000,
          7574.390137
        ],
        [
          1780078500000,
          7576.950195
        ],
        [
          1780078800000,
          7579.359863
        ],
        [
          1780079100000,
          7580.609863
        ],
        [
          1780079400000,
          7584.52002
        ],
        [
          1780079700000,
          7583.02002
        ],
        [
          1780080000000,
          7581.640137
        ],
        [
          1780080300000,
          7575.299805
        ],
        [
          1780080600000,
          7574.540039
        ],
        [
          1780080900000,
          7572.0
        ],
        [
          1780081200000,
          7575.720215
        ],
        [
          1780081500000,
          7580.22998
        ],
        [
          1780081800000,
          7581.27002
        ],
        [
          1780082100000,
          7579.52002
        ],
        [
          1780082400000,
          7582.72998
        ],
        [
          1780082700000,
          7586.049805
        ],
        [
          1780083000000,
          7589.049805
        ],
        [
          1780083300000,
          7592.080078
        ],
        [
          1780083600000,
          7589.950195
        ],
        [
          1780083900000,
          7588.72998
        ],
        [
          1780084200000,
          7582.799805
        ],
        [
          1780084500000,
          7581.25
        ],
        [
          1780084800000,
          7580.060059
        ]
      ],
      "marketState": "UNKNOWN",
      "marketTime": "2026-05-30 06:03 KST",
      "marketTimestamp": 1780088617
    },
    {
      "id": "nasdaq",
      "label": "NASDAQ",
      "symbol": "^IXIC",
      "group": "해외 지수",
      "kind": "equity",
      "decimals": 2,
      "price": 26972.62,
      "previousClose": 26917.5,
      "change": 55.12,
      "changePercent": 0.2048,
      "tone": "up",
      "direction": "상승",
      "series": [
        [
          1780061400000,
          26948.324219
        ],
        [
          1780061700000,
          27004.226562
        ],
        [
          1780062000000,
          27058.679688
        ],
        [
          1780062300000,
          27065.632812
        ],
        [
          1780062600000,
          27066.587891
        ],
        [
          1780062900000,
          27073.699219
        ],
        [
          1780063200000,
          27073.953125
        ],
        [
          1780063500000,
          27043.253906
        ],
        [
          1780063800000,
          27016.048828
        ],
        [
          1780064100000,
          26978.080078
        ],
        [
          1780064400000,
          26952.291016
        ],
        [
          1780064700000,
          26967.972656
        ],
        [
          1780065000000,
          26988.941406
        ],
        [
          1780065300000,
          26919.898438
        ],
        [
          1780065600000,
          26875.951172
        ],
        [
          1780065900000,
          26889.816406
        ],
        [
          1780066200000,
          26926.265625
        ],
        [
          1780066500000,
          26937.181641
        ],
        [
          1780066800000,
          26953.978516
        ],
        [
          1780067100000,
          26979.351562
        ],
        [
          1780067400000,
          27012.904297
        ],
        [
          1780067700000,
          26986.683594
        ],
        [
          1780068000000,
          26984.330078
        ],
        [
          1780068300000,
          26989.722656
        ],
        [
          1780068600000,
          26998.705078
        ],
        [
          1780068900000,
          26998.359375
        ],
        [
          1780069200000,
          26969.347656
        ],
        [
          1780069500000,
          26972.451172
        ],
        [
          1780069800000,
          26973.013672
        ],
        [
          1780070100000,
          26962.53125
        ],
        [
          1780070400000,
          26996.544922
        ],
        [
          1780070700000,
          27019.542969
        ],
        [
          1780071000000,
          27025.615234
        ],
        [
          1780071300000,
          27007.884766
        ],
        [
          1780071600000,
          27016.177734
        ],
        [
          1780071900000,
          26992.951172
        ],
        [
          1780072200000,
          27011.779297
        ],
        [
          1780072500000,
          27031.796875
        ],
        [
          1780072800000,
          27022.316406
        ],
        [
          1780073100000,
          27010.072266
        ],
        [
          1780073400000,
          26999.613281
        ],
        [
          1780073700000,
          26993.0625
        ],
        [
          1780074000000,
          26985.464844
        ],
        [
          1780074300000,
          26995.869141
        ],
        [
          1780074600000,
          26992.236328
        ],
        [
          1780074900000,
          26989.9375
        ],
        [
          1780075200000,
          26982.310547
        ],
        [
          1780075500000,
          26975.044922
        ],
        [
          1780075800000,
          26971.46875
        ],
        [
          1780076100000,
          26966.988281
        ],
        [
          1780076400000,
          26955.529297
        ],
        [
          1780076700000,
          26955.396484
        ],
        [
          1780077000000,
          26947.322266
        ],
        [
          1780077300000,
          26915.394531
        ],
        [
          1780077600000,
          26934.931641
        ],
        [
          1780077900000,
          26951.394531
        ],
        [
          1780078200000,
          26939.0625
        ],
        [
          1780078500000,
          26952.728516
        ],
        [
          1780078800000,
          26963.949219
        ],
        [
          1780079100000,
          26975.271484
        ],
        [
          1780079400000,
          26987.136719
        ],
        [
          1780079700000,
          26969.244141
        ],
        [
          1780080000000,
          26974.820312
        ],
        [
          1780080300000,
          26944.197266
        ],
        [
          1780080600000,
          26938.835938
        ],
        [
          1780080900000,
          26923.603516
        ],
        [
          1780081200000,
          26941.636719
        ],
        [
          1780081500000,
          26961.390625
        ],
        [
          1780081800000,
          26967.123047
        ],
        [
          1780082100000,
          26959.238281
        ],
        [
          1780082400000,
          26968.570312
        ],
        [
          1780082700000,
          26980.201172
        ],
        [
          1780083000000,
          26993.298828
        ],
        [
          1780083300000,
          27016.373047
        ],
        [
          1780083600000,
          27010.285156
        ],
        [
          1780083900000,
          27008.433594
        ],
        [
          1780084200000,
          26986.523438
        ],
        [
          1780084500000,
          26976.353516
        ],
        [
          1780084800000,
          26972.619141
        ]
      ],
      "marketState": "UNKNOWN",
      "marketTime": "2026-05-30 06:15 KST",
      "marketTimestamp": 1780089359
    },
    {
      "id": "dow",
      "label": "DOW",
      "symbol": "^DJI",
      "group": "해외 지수",
      "kind": "equity",
      "decimals": 2,
      "price": 51032.46,
      "previousClose": 50669.0,
      "change": 363.46,
      "changePercent": 0.7173,
      "tone": "up",
      "direction": "상승",
      "series": [
        [
          1780061400000,
          50814.320312
        ],
        [
          1780061700000,
          50843.300781
        ],
        [
          1780062000000,
          50867.140625
        ],
        [
          1780062300000,
          50868.078125
        ],
        [
          1780062600000,
          50870.550781
        ],
        [
          1780062900000,
          50849.371094
        ],
        [
          1780063200000,
          50822.488281
        ],
        [
          1780063500000,
          50834.109375
        ],
        [
          1780063800000,
          50896.589844
        ],
        [
          1780064100000,
          50898.800781
        ],
        [
          1780064400000,
          50878.429688
        ],
        [
          1780064700000,
          50898.058594
        ],
        [
          1780065000000,
          50909.0
        ],
        [
          1780065300000,
          50885.011719
        ],
        [
          1780065600000,
          50893.230469
        ],
        [
          1780065900000,
          50866.179688
        ],
        [
          1780066200000,
          50967.101562
        ],
        [
          1780066500000,
          50978.261719
        ],
        [
          1780066800000,
          51005.589844
        ],
        [
          1780067100000,
          51002.769531
        ],
        [
          1780067400000,
          51061.558594
        ],
        [
          1780067700000,
          51067.300781
        ],
        [
          1780068000000,
          51066.179688
        ],
        [
          1780068300000,
          51041.488281
        ],
        [
          1780068600000,
          51054.238281
        ],
        [
          1780068900000,
          51051.851562
        ],
        [
          1780069200000,
          51050.128906
        ],
        [
          1780069500000,
          51035.878906
        ],
        [
          1780069800000,
          51044.960938
        ],
        [
          1780070100000,
          51058.730469
        ],
        [
          1780070400000,
          51038.460938
        ],
        [
          1780070700000,
          51038.480469
        ],
        [
          1780071000000,
          51009.390625
        ],
        [
          1780071300000,
          50992.308594
        ],
        [
          1780071600000,
          50998.789062
        ],
        [
          1780071900000,
          51004.761719
        ],
        [
          1780072200000,
          51049.570312
        ],
        [
          1780072500000,
          51080.761719
        ],
        [
          1780072800000,
          51055.570312
        ],
        [
          1780073100000,
          51025.609375
        ],
        [
          1780073400000,
          51029.351562
        ],
        [
          1780073700000,
          50996.550781
        ],
        [
          1780074000000,
          50967.539062
        ],
        [
          1780074300000,
          50974.621094
        ],
        [
          1780074600000,
          50981.839844
        ],
        [
          1780074900000,
          51025.71875
        ],
        [
          1780075200000,
          51025.589844
        ],
        [
          1780075500000,
          51025.929688
        ],
        [
          1780075800000,
          51016.761719
        ],
        [
          1780076100000,
          51001.710938
        ],
        [
          1780076400000,
          50982.140625
        ],
        [
          1780076700000,
          50981.46875
        ],
        [
          1780077000000,
          50971.46875
        ],
        [
          1780077300000,
          50926.941406
        ],
        [
          1780077600000,
          50946.671875
        ],
        [
          1780077900000,
          50953.578125
        ],
        [
          1780078200000,
          50956.699219
        ],
        [
          1780078500000,
          50965.96875
        ],
        [
          1780078800000,
          50974.191406
        ],
        [
          1780079100000,
          50973.941406
        ],
        [
          1780079400000,
          51022.410156
        ],
        [
          1780079700000,
          51030.289062
        ],
        [
          1780080000000,
          50996.820312
        ],
        [
          1780080300000,
          50973.738281
        ],
        [
          1780080600000,
          50959.519531
        ],
        [
          1780080900000,
          50957.46875
        ],
        [
          1780081200000,
          50978.730469
        ],
        [
          1780081500000,
          50995.820312
        ],
        [
          1780081800000,
          51000.101562
        ],
        [
          1780082100000,
          51018.960938
        ],
        [
          1780082400000,
          51038.769531
        ],
        [
          1780082700000,
          51066.789062
        ],
        [
          1780083000000,
          51089.808594
        ],
        [
          1780083300000,
          51060.128906
        ],
        [
          1780083600000,
          51047.53125
        ],
        [
          1780083900000,
          51025.351562
        ],
        [
          1780084200000,
          51005.890625
        ],
        [
          1780084500000,
          51032.449219
        ],
        [
          1780084800000,
          51032.460938
        ]
      ],
      "marketState": "UNKNOWN",
      "marketTime": "2026-05-30 06:03 KST",
      "marketTimestamp": 1780088624
    },
    {
      "id": "usdkrw",
      "label": "USD/KRW",
      "symbol": "KRW=X",
      "group": "거시 자산",
      "kind": "fx",
      "decimals": 2,
      "price": 1505.18,
      "previousClose": 1507.13,
      "change": -1.95,
      "changePercent": -0.1294,
      "tone": "flat",
      "direction": "보합",
      "series": [
        [
          1780272000000,
          1507.380005
        ],
        [
          1780272300000,
          1507.219971
        ],
        [
          1780272600000,
          1508.380005
        ],
        [
          1780272900000,
          1508.97998
        ],
        [
          1780273200000,
          1509.079956
        ],
        [
          1780273500000,
          1510.079956
        ],
        [
          1780273800000,
          1510.079956
        ],
        [
          1780274100000,
          1510.47998
        ],
        [
          1780274400000,
          1510.52002
        ],
        [
          1780274700000,
          1511.579956
        ],
        [
          1780275000000,
          1511.97998
        ],
        [
          1780275300000,
          1513.380005
        ],
        [
          1780275600000,
          1513.579956
        ],
        [
          1780275900000,
          1513.119995
        ],
        [
          1780276200000,
          1513.280029
        ],
        [
          1780276500000,
          1513.699951
        ],
        [
          1780276800000,
          1513.630005
        ],
        [
          1780277100000,
          1513.719971
        ],
        [
          1780277400000,
          1513.180054
        ],
        [
          1780277700000,
          1515.880005
        ],
        [
          1780278000000,
          1515.97998
        ],
        [
          1780278300000,
          1516.449951
        ],
        [
          1780278600000,
          1514.579956
        ],
        [
          1780278900000,
          1514.680054
        ],
        [
          1780279200000,
          1515.030029
        ],
        [
          1780279500000,
          1514.579956
        ],
        [
          1780279800000,
          1515.97998
        ],
        [
          1780280100000,
          1516.180054
        ],
        [
          1780280400000,
          1516.219971
        ],
        [
          1780280700000,
          1516.380005
        ],
        [
          1780281000000,
          1516.530029
        ],
        [
          1780281300000,
          1517.380005
        ],
        [
          1780281600000,
          1517.609985
        ],
        [
          1780281900000,
          1517.170044
        ],
        [
          1780282200000,
          1516.180054
        ],
        [
          1780282500000,
          1516.359985
        ],
        [
          1780282800000,
          1515.579956
        ],
        [
          1780283100000,
          1515.47998
        ],
        [
          1780283400000,
          1516.560059
        ],
        [
          1780283700000,
          1516.880005
        ],
        [
          1780284000000,
          1516.959961
        ],
        [
          1780284300000,
          1516.180054
        ],
        [
          1780284600000,
          1515.280029
        ],
        [
          1780284900000,
          1516.280029
        ],
        [
          1780285200000,
          1516.52002
        ],
        [
          1780285500000,
          1516.180054
        ],
        [
          1780285800000,
          1515.910034
        ],
        [
          1780286100000,
          1515.839966
        ],
        [
          1780286400000,
          1515.079956
        ],
        [
          1780286700000,
          1513.829956
        ],
        [
          1780287000000,
          1513.969971
        ],
        [
          1780287300000,
          1513.800049
        ],
        [
          1780287600000,
          1513.880005
        ],
        [
          1780287900000,
          1513.72998
        ],
        [
          1780288200000,
          1513.939941
        ],
        [
          1780288500000,
          1514.469971
        ],
        [
          1780288800000,
          1514.459961
        ],
        [
          1780289100000,
          1514.280029
        ],
        [
          1780289400000,
          1514.530029
        ],
        [
          1780289700000,
          1513.680054
        ],
        [
          1780290000000,
          1512.880005
        ],
        [
          1780290300000,
          1512.310059
        ],
        [
          1780290600000,
          1512.569946
        ],
        [
          1780290900000,
          1512.079956
        ],
        [
          1780291200000,
          1511.530029
        ],
        [
          1780291500000,
          1512.280029
        ],
        [
          1780291800000,
          1511.579956
        ],
        [
          1780292100000,
          1512.079956
        ],
        [
          1780292400000,
          1510.209961
        ],
        [
          1780292700000,
          1507.680054
        ],
        [
          1780293000000,
          1503.780029
        ],
        [
          1780293300000,
          1504.880005
        ],
        [
          1780293600000,
          1504.380005
        ],
        [
          1780293900000,
          1503.880005
        ],
        [
          1780294200000,
          1503.079956
        ],
        [
          1780294500000,
          1503.849976
        ],
        [
          1780294800000,
          1504.540039
        ],
        [
          1780295100000,
          1503.780029
        ],
        [
          1780295400000,
          1503.680054
        ],
        [
          1780295700000,
          1504.119995
        ],
        [
          1780296000000,
          1503.280029
        ],
        [
          1780296300000,
          1503.75
        ],
        [
          1780296600000,
          1504.160034
        ],
        [
          1780296900000,
          1505.079956
        ],
        [
          1780297200000,
          1505.459961
        ],
        [
          1780297445000,
          1505.180054
        ]
      ],
      "marketState": "UNKNOWN",
      "marketTime": "2026-06-01 16:04 KST",
      "marketTimestamp": 1780297445
    },
    {
      "id": "us10y",
      "label": "미국 10Y",
      "symbol": "^TNX",
      "group": "거시 자산",
      "kind": "yield",
      "decimals": 3,
      "price": 4.453,
      "previousClose": 4.455,
      "change": -0.002,
      "changePercent": -0.0449,
      "tone": "flat",
      "direction": "보합",
      "series": [
        [
          1780057200000,
          4.441
        ],
        [
          1780057500000,
          4.443
        ],
        [
          1780057800000,
          4.447
        ],
        [
          1780058100000,
          4.445
        ],
        [
          1780058400000,
          4.443
        ],
        [
          1780058700000,
          4.443
        ],
        [
          1780059000000,
          4.441
        ],
        [
          1780059300000,
          4.445
        ],
        [
          1780059600000,
          4.441
        ],
        [
          1780059900000,
          4.445
        ],
        [
          1780060200000,
          4.449
        ],
        [
          1780060500000,
          4.443
        ],
        [
          1780060800000,
          4.445
        ],
        [
          1780061100000,
          4.443
        ],
        [
          1780061400000,
          4.445
        ],
        [
          1780061700000,
          4.447
        ],
        [
          1780062000000,
          4.449
        ],
        [
          1780062300000,
          4.457
        ],
        [
          1780062600000,
          4.451
        ],
        [
          1780062900000,
          4.455
        ],
        [
          1780063200000,
          4.449
        ],
        [
          1780063500000,
          4.449
        ],
        [
          1780063800000,
          4.453
        ],
        [
          1780064100000,
          4.449
        ],
        [
          1780064400000,
          4.449
        ],
        [
          1780064700000,
          4.451
        ],
        [
          1780065000000,
          4.449
        ],
        [
          1780065300000,
          4.453
        ],
        [
          1780065600000,
          4.447
        ],
        [
          1780065900000,
          4.445
        ],
        [
          1780066200000,
          4.439
        ],
        [
          1780066500000,
          4.437
        ],
        [
          1780066800000,
          4.441
        ],
        [
          1780067100000,
          4.436
        ],
        [
          1780067400000,
          4.432
        ],
        [
          1780067700000,
          4.43
        ],
        [
          1780068000000,
          4.428
        ],
        [
          1780068300000,
          4.43
        ],
        [
          1780068600000,
          4.43
        ],
        [
          1780068900000,
          4.434
        ],
        [
          1780069200000,
          4.439
        ],
        [
          1780069500000,
          4.437
        ],
        [
          1780069800000,
          4.437
        ],
        [
          1780070100000,
          4.437
        ],
        [
          1780070400000,
          4.437
        ],
        [
          1780070700000,
          4.439
        ],
        [
          1780071000000,
          4.437
        ],
        [
          1780071300000,
          4.437
        ],
        [
          1780071600000,
          4.436
        ],
        [
          1780071900000,
          4.434
        ],
        [
          1780072200000,
          4.434
        ],
        [
          1780072500000,
          4.43
        ],
        [
          1780072800000,
          4.43
        ],
        [
          1780073100000,
          4.434
        ],
        [
          1780073400000,
          4.434
        ],
        [
          1780073700000,
          4.434
        ],
        [
          1780074000000,
          4.434
        ],
        [
          1780074300000,
          4.437
        ],
        [
          1780074600000,
          4.437
        ],
        [
          1780074900000,
          4.436
        ],
        [
          1780075200000,
          4.437
        ],
        [
          1780075500000,
          4.439
        ],
        [
          1780075800000,
          4.439
        ],
        [
          1780076100000,
          4.441
        ],
        [
          1780076400000,
          4.443
        ],
        [
          1780076700000,
          4.443
        ],
        [
          1780077000000,
          4.447
        ],
        [
          1780077300000,
          4.445
        ],
        [
          1780077600000,
          4.445
        ],
        [
          1780077900000,
          4.445
        ],
        [
          1780078200000,
          4.443
        ],
        [
          1780078500000,
          4.437
        ],
        [
          1780078800000,
          4.439
        ],
        [
          1780079100000,
          4.439
        ],
        [
          1780079400000,
          4.437
        ],
        [
          1780079700000,
          4.439
        ],
        [
          1780080000000,
          4.439
        ],
        [
          1780080300000,
          4.443
        ],
        [
          1780080600000,
          4.445
        ],
        [
          1780080900000,
          4.453
        ]
      ],
      "marketState": "UNKNOWN",
      "marketTime": "2026-05-30 03:59 KST",
      "marketTimestamp": 1780081195
    },
    {
      "id": "wti",
      "label": "WTI",
      "symbol": "CL=F",
      "group": "거시 자산",
      "kind": "commodity",
      "decimals": 2,
      "price": 90.34,
      "previousClose": 87.36,
      "change": 2.98,
      "changePercent": 3.4112,
      "tone": "up",
      "direction": "상승",
      "series": [
        [
          1780286400000,
          89.75
        ],
        [
          1780286700000,
          89.800003
        ],
        [
          1780287000000,
          89.870003
        ],
        [
          1780287300000,
          89.790001
        ],
        [
          1780287600000,
          89.769997
        ],
        [
          1780287900000,
          89.720001
        ],
        [
          1780288200000,
          89.650002
        ],
        [
          1780288500000,
          89.610001
        ],
        [
          1780288800000,
          89.389999
        ],
        [
          1780289100000,
          89.629997
        ],
        [
          1780289400000,
          89.599998
        ],
        [
          1780289700000,
          89.650002
        ],
        [
          1780290000000,
          89.610001
        ],
        [
          1780290300000,
          89.57
        ],
        [
          1780290600000,
          89.629997
        ],
        [
          1780290900000,
          89.669998
        ],
        [
          1780291200000,
          89.699997
        ],
        [
          1780291500000,
          89.730003
        ],
        [
          1780291800000,
          89.93
        ],
        [
          1780292100000,
          89.870003
        ],
        [
          1780292400000,
          89.800003
        ],
        [
          1780292700000,
          89.910004
        ],
        [
          1780293000000,
          89.809998
        ],
        [
          1780293300000,
          89.75
        ],
        [
          1780293600000,
          89.82
        ],
        [
          1780293900000,
          89.830002
        ],
        [
          1780294200000,
          90.019997
        ],
        [
          1780294500000,
          90.029999
        ],
        [
          1780294800000,
          90.080002
        ],
        [
          1780295100000,
          90.019997
        ],
        [
          1780295400000,
          89.940002
        ],
        [
          1780295700000,
          90.18
        ],
        [
          1780296000000,
          90.260002
        ],
        [
          1780296300000,
          90.230003
        ],
        [
          1780296600000,
          90.32
        ],
        [
          1780296845000,
          90.339996
        ]
      ],
      "marketState": "UNKNOWN",
      "marketTime": "2026-06-01 15:54 KST",
      "marketTimestamp": 1780296845
    },
    {
      "id": "gold",
      "label": "Gold",
      "symbol": "GC=F",
      "group": "거시 자산",
      "kind": "commodity",
      "decimals": 2,
      "price": 4532.8,
      "previousClose": 4593.0,
      "change": -60.2,
      "changePercent": -1.3107,
      "tone": "down",
      "direction": "하락",
      "series": [
        [
          1780286400000,
          4546.899902
        ],
        [
          1780286700000,
          4544.700195
        ],
        [
          1780287000000,
          4545.100098
        ],
        [
          1780287300000,
          4546.899902
        ],
        [
          1780287600000,
          4547.899902
        ],
        [
          1780287900000,
          4546.100098
        ],
        [
          1780288200000,
          4544.700195
        ],
        [
          1780288500000,
          4545.200195
        ],
        [
          1780288800000,
          4545.0
        ],
        [
          1780289100000,
          4540.899902
        ],
        [
          1780289400000,
          4544.600098
        ],
        [
          1780289700000,
          4544.700195
        ],
        [
          1780290000000,
          4546.5
        ],
        [
          1780290300000,
          4546.5
        ],
        [
          1780290600000,
          4548.700195
        ],
        [
          1780290900000,
          4551.799805
        ],
        [
          1780291200000,
          4552.700195
        ],
        [
          1780291500000,
          4550.799805
        ],
        [
          1780291800000,
          4544.100098
        ],
        [
          1780292100000,
          4550.299805
        ],
        [
          1780292400000,
          4549.700195
        ],
        [
          1780292700000,
          4554.299805
        ],
        [
          1780293000000,
          4553.200195
        ],
        [
          1780293300000,
          4548.200195
        ],
        [
          1780293600000,
          4545.899902
        ],
        [
          1780293900000,
          4546.700195
        ],
        [
          1780294200000,
          4544.299805
        ],
        [
          1780294500000,
          4541.299805
        ],
        [
          1780294800000,
          4536.5
        ],
        [
          1780295100000,
          4544.299805
        ],
        [
          1780295400000,
          4540.700195
        ],
        [
          1780295700000,
          4534.799805
        ],
        [
          1780296000000,
          4535.0
        ],
        [
          1780296300000,
          4534.600098
        ],
        [
          1780296600000,
          4533.600098
        ],
        [
          1780296841000,
          4532.799805
        ]
      ],
      "marketState": "UNKNOWN",
      "marketTime": "2026-06-01 15:54 KST",
      "marketTimestamp": 1780296841
    },
    {
      "id": "bitcoin",
      "label": "Bitcoin",
      "symbol": "BTC-USD",
      "group": "거시 자산",
      "kind": "crypto",
      "decimals": 0,
      "price": 72991.04,
      "previousClose": 73568.4,
      "change": -577.36,
      "changePercent": -0.7848,
      "tone": "down",
      "direction": "하락",
      "series": [
        [
          1780272000000,
          73757.992188
        ],
        [
          1780272300000,
          73645.570312
        ],
        [
          1780272600000,
          73698.007812
        ],
        [
          1780272900000,
          73626.0
        ],
        [
          1780273200000,
          73691.367188
        ],
        [
          1780273500000,
          73844.648438
        ],
        [
          1780273800000,
          73777.4375
        ],
        [
          1780274100000,
          73790.976562
        ],
        [
          1780274400000,
          73831.148438
        ],
        [
          1780274700000,
          73852.523438
        ],
        [
          1780275000000,
          73812.296875
        ],
        [
          1780275300000,
          73781.070312
        ],
        [
          1780275600000,
          73631.039062
        ],
        [
          1780275900000,
          73485.421875
        ],
        [
          1780276200000,
          73463.15625
        ],
        [
          1780276500000,
          73489.179688
        ],
        [
          1780276800000,
          73496.023438
        ],
        [
          1780277100000,
          73485.796875
        ],
        [
          1780277400000,
          73510.960938
        ],
        [
          1780277700000,
          73501.476562
        ],
        [
          1780278000000,
          73397.453125
        ],
        [
          1780278300000,
          73468.0
        ],
        [
          1780278600000,
          73271.851562
        ],
        [
          1780278900000,
          73188.0
        ],
        [
          1780279200000,
          73267.40625
        ],
        [
          1780279500000,
          73414.773438
        ],
        [
          1780279800000,
          73447.75
        ],
        [
          1780280100000,
          73359.867188
        ],
        [
          1780280400000,
          73395.929688
        ],
        [
          1780280700000,
          73424.6875
        ],
        [
          1780281000000,
          73390.25
        ],
        [
          1780281300000,
          73474.65625
        ],
        [
          1780281600000,
          73671.320312
        ],
        [
          1780281900000,
          73701.15625
        ],
        [
          1780282200000,
          73683.992188
        ],
        [
          1780282500000,
          73686.148438
        ],
        [
          1780282800000,
          73865.210938
        ],
        [
          1780283100000,
          73866.9375
        ],
        [
          1780283400000,
          73780.46875
        ],
        [
          1780283700000,
          73812.890625
        ],
        [
          1780284000000,
          73845.960938
        ],
        [
          1780284300000,
          73814.0
        ],
        [
          1780284600000,
          73841.617188
        ],
        [
          1780284900000,
          73782.859375
        ],
        [
          1780285200000,
          73753.882812
        ],
        [
          1780285500000,
          73785.171875
        ],
        [
          1780285800000,
          73649.109375
        ],
        [
          1780286100000,
          73661.742188
        ],
        [
          1780286400000,
          73683.59375
        ],
        [
          1780286700000,
          73566.078125
        ],
        [
          1780287000000,
          73501.953125
        ],
        [
          1780287300000,
          73403.992188
        ],
        [
          1780287600000,
          73329.828125
        ],
        [
          1780287900000,
          73299.960938
        ],
        [
          1780288200000,
          73334.710938
        ],
        [
          1780288500000,
          73337.007812
        ],
        [
          1780288800000,
          73378.0
        ],
        [
          1780289100000,
          73308.0
        ],
        [
          1780289400000,
          73410.0
        ],
        [
          1780289700000,
          73419.492188
        ],
        [
          1780290000000,
          73402.007812
        ],
        [
          1780290300000,
          73381.820312
        ],
        [
          1780290600000,
          73428.898438
        ],
        [
          1780290900000,
          73360.679688
        ],
        [
          1780291200000,
          73356.117188
        ],
        [
          1780291500000,
          73242.601562
        ],
        [
          1780291800000,
          73301.726562
        ],
        [
          1780292100000,
          73293.992188
        ],
        [
          1780292400000,
          73324.007812
        ],
        [
          1780292700000,
          73322.59375
        ],
        [
          1780293000000,
          73300.0
        ],
        [
          1780293300000,
          73249.742188
        ],
        [
          1780293600000,
          73212.242188
        ],
        [
          1780293900000,
          73148.671875
        ],
        [
          1780294200000,
          73193.9375
        ],
        [
          1780294500000,
          73171.992188
        ],
        [
          1780294800000,
          73135.171875
        ],
        [
          1780295100000,
          73091.007812
        ],
        [
          1780295400000,
          73092.679688
        ],
        [
          1780295700000,
          73044.648438
        ],
        [
          1780296000000,
          72914.28125
        ],
        [
          1780296300000,
          73072.851562
        ],
        [
          1780296600000,
          73015.953125
        ],
        [
          1780296900000,
          73037.25
        ],
        [
          1780297200000,
          72991.226562
        ],
        [
          1780297442000,
          72991.039062
        ]
      ],
      "marketState": "UNKNOWN",
      "marketTime": "2026-06-01 16:04 KST",
      "marketTimestamp": 1780297442
    }
  ],
  "mainCharts": [
    {
      "id": "kospi",
      "label": "KOSPI",
      "symbol": "^KS11",
      "group": "국내 지수",
      "kind": "equity",
      "decimals": 2,
      "price": 8788.38,
      "previousClose": 8476.15,
      "change": 312.23,
      "changePercent": 3.6836,
      "tone": "up",
      "direction": "상승",
      "series": [
        [
          1780272000000,
          8585.730469
        ],
        [
          1780272300000,
          8583.5
        ],
        [
          1780272600000,
          8587.080078
        ],
        [
          1780272900000,
          8552.799805
        ],
        [
          1780273200000,
          8613.459961
        ],
        [
          1780273500000,
          8628.80957
        ],
        [
          1780273800000,
          8640.209961
        ],
        [
          1780274100000,
          8691.830078
        ],
        [
          1780274400000,
          8689.419922
        ],
        [
          1780274700000,
          8672.570312
        ],
        [
          1780275000000,
          8647.740234
        ],
        [
          1780275300000,
          8672.169922
        ],
        [
          1780275600000,
          8708.070312
        ],
        [
          1780275900000,
          8712.080078
        ],
        [
          1780276200000,
          8715.629883
        ],
        [
          1780276500000,
          8726.860352
        ],
        [
          1780276800000,
          8741.419922
        ],
        [
          1780277100000,
          8747.110352
        ],
        [
          1780277400000,
          8765.969727
        ],
        [
          1780277700000,
          8785.580078
        ],
        [
          1780278000000,
          8795.200195
        ],
        [
          1780278300000,
          8821.870117
        ],
        [
          1780278600000,
          8826.610352
        ],
        [
          1780278900000,
          8837.290039
        ],
        [
          1780279200000,
          8835.25
        ],
        [
          1780279500000,
          8846.650391
        ],
        [
          1780279800000,
          8850.389648
        ],
        [
          1780280100000,
          8845.290039
        ],
        [
          1780280400000,
          8844.209961
        ],
        [
          1780280700000,
          8866.639648
        ],
        [
          1780281000000,
          8842.089844
        ],
        [
          1780281300000,
          8869.230469
        ],
        [
          1780281600000,
          8847.790039
        ],
        [
          1780281900000,
          8828.919922
        ],
        [
          1780282200000,
          8825.05957
        ],
        [
          1780282500000,
          8849.19043
        ],
        [
          1780282800000,
          8863.759766
        ],
        [
          1780283100000,
          8865.469727
        ],
        [
          1780283400000,
          8864.360352
        ],
        [
          1780283700000,
          8864.269531
        ],
        [
          1780284000000,
          8860.650391
        ],
        [
          1780284300000,
          8860.530273
        ],
        [
          1780284600000,
          8860.400391
        ],
        [
          1780284900000,
          8859.740234
        ],
        [
          1780285200000,
          8835.839844
        ],
        [
          1780285500000,
          8841.459961
        ],
        [
          1780285800000,
          8822.889648
        ],
        [
          1780286100000,
          8820.219727
        ],
        [
          1780286400000,
          8840.30957
        ],
        [
          1780286700000,
          8838.320312
        ],
        [
          1780287000000,
          8850.080078
        ],
        [
          1780287300000,
          8848.860352
        ],
        [
          1780287600000,
          8844.049805
        ],
        [
          1780287900000,
          8848.94043
        ],
        [
          1780288200000,
          8852.049805
        ],
        [
          1780288500000,
          8851.849609
        ],
        [
          1780288800000,
          8855.080078
        ],
        [
          1780289100000,
          8852.669922
        ],
        [
          1780289400000,
          8856.700195
        ],
        [
          1780289700000,
          8863.730469
        ],
        [
          1780290000000,
          8853.990234
        ],
        [
          1780290300000,
          8842.480469
        ],
        [
          1780290600000,
          8834.370117
        ],
        [
          1780290900000,
          8823.009766
        ],
        [
          1780291200000,
          8801.269531
        ],
        [
          1780291500000,
          8739.769531
        ],
        [
          1780291800000,
          8748.860352
        ],
        [
          1780292100000,
          8776.929688
        ],
        [
          1780292400000,
          8810.049805
        ],
        [
          1780292700000,
          8826.450195
        ],
        [
          1780293000000,
          8811.759766
        ],
        [
          1780293300000,
          8820.05957
        ],
        [
          1780293600000,
          8788.379883
        ]
      ],
      "marketState": "UNKNOWN",
      "marketTime": "2026-06-01 15:33 KST",
      "marketTimestamp": 1780295580
    },
    {
      "id": "kosdaq",
      "label": "KOSDAQ",
      "symbol": "^KQ11",
      "group": "국내 지수",
      "kind": "equity",
      "decimals": 2,
      "price": 1050.03,
      "previousClose": 1074.8,
      "change": -24.77,
      "changePercent": -2.3046,
      "tone": "down",
      "direction": "하락",
      "series": [
        [
          1780272000000,
          1055.890015
        ],
        [
          1780272300000,
          1052.849976
        ],
        [
          1780272600000,
          1050.439941
        ],
        [
          1780272900000,
          1068.75
        ],
        [
          1780273200000,
          1073.530029
        ],
        [
          1780273500000,
          1081.400024
        ],
        [
          1780273800000,
          1077.699951
        ],
        [
          1780274100000,
          1070.829956
        ],
        [
          1780274400000,
          1068.130005
        ],
        [
          1780274700000,
          1064.959961
        ],
        [
          1780275000000,
          1063.199951
        ],
        [
          1780275300000,
          1067.180054
        ],
        [
          1780275600000,
          1061.52002
        ],
        [
          1780275900000,
          1059.560059
        ],
        [
          1780276200000,
          1057.890015
        ],
        [
          1780276500000,
          1056.920044
        ],
        [
          1780276800000,
          1059.560059
        ],
        [
          1780277100000,
          1058.310059
        ],
        [
          1780277400000,
          1054.76001
        ],
        [
          1780277700000,
          1056.079956
        ],
        [
          1780278000000,
          1056.0
        ],
        [
          1780278300000,
          1052.47998
        ],
        [
          1780278600000,
          1052.069946
        ],
        [
          1780278900000,
          1050.140015
        ],
        [
          1780279200000,
          1050.180054
        ],
        [
          1780279500000,
          1051.709961
        ],
        [
          1780279800000,
          1050.880005
        ],
        [
          1780280100000,
          1052.27002
        ],
        [
          1780280400000,
          1054.060059
        ],
        [
          1780280700000,
          1052.349976
        ],
        [
          1780281000000,
          1052.089966
        ],
        [
          1780281300000,
          1051.02002
        ],
        [
          1780281600000,
          1050.97998
        ],
        [
          1780281900000,
          1052.630005
        ],
        [
          1780282200000,
          1053.73999
        ],
        [
          1780282500000,
          1052.189941
        ],
        [
          1780282800000,
          1050.699951
        ],
        [
          1780283100000,
          1050.810059
        ],
        [
          1780283400000,
          1050.98999
        ],
        [
          1780283700000,
          1050.619995
        ],
        [
          1780284000000,
          1050.079956
        ],
        [
          1780284300000,
          1049.099976
        ],
        [
          1780284600000,
          1050.699951
        ],
        [
          1780284900000,
          1049.099976
        ],
        [
          1780285200000,
          1049.5
        ],
        [
          1780285500000,
          1050.599976
        ],
        [
          1780285800000,
          1050.079956
        ],
        [
          1780286100000,
          1049.23999
        ],
        [
          1780286400000,
          1048.439941
        ],
        [
          1780286700000,
          1047.790039
        ],
        [
          1780287000000,
          1048.0
        ],
        [
          1780287300000,
          1046.97998
        ],
        [
          1780287600000,
          1046.630005
        ],
        [
          1780287900000,
          1046.589966
        ],
        [
          1780288200000,
          1046.829956
        ],
        [
          1780288500000,
          1046.01001
        ],
        [
          1780288800000,
          1048.290039
        ],
        [
          1780289100000,
          1046.680054
        ],
        [
          1780289400000,
          1045.630005
        ],
        [
          1780289700000,
          1044.839966
        ],
        [
          1780290000000,
          1044.319946
        ],
        [
          1780290300000,
          1047.959961
        ],
        [
          1780290600000,
          1050.069946
        ],
        [
          1780290900000,
          1047.890015
        ],
        [
          1780291200000,
          1051.76001
        ],
        [
          1780291500000,
          1050.76001
        ],
        [
          1780291800000,
          1051.280029
        ],
        [
          1780292100000,
          1051.530029
        ],
        [
          1780292400000,
          1049.949951
        ],
        [
          1780292700000,
          1050.339966
        ],
        [
          1780293000000,
          1049.280029
        ],
        [
          1780293300000,
          1048.47998
        ],
        [
          1780293600000,
          1050.030029
        ]
      ],
      "marketState": "UNKNOWN",
      "marketTime": "2026-06-01 15:33 KST",
      "marketTimestamp": 1780295580
    },
    {
      "id": "sp500",
      "label": "S&P 500",
      "symbol": "^GSPC",
      "group": "해외 지수",
      "kind": "equity",
      "decimals": 2,
      "price": 7580.06,
      "previousClose": 7563.63,
      "change": 16.43,
      "changePercent": 0.2172,
      "tone": "up",
      "direction": "상승",
      "series": [
        [
          1780061400000,
          7578.290039
        ],
        [
          1780061700000,
          7585.27002
        ],
        [
          1780062000000,
          7593.390137
        ],
        [
          1780062300000,
          7594.939941
        ],
        [
          1780062600000,
          7597.069824
        ],
        [
          1780062900000,
          7596.390137
        ],
        [
          1780063200000,
          7595.25
        ],
        [
          1780063500000,
          7590.660156
        ],
        [
          1780063800000,
          7590.350098
        ],
        [
          1780064100000,
          7585.330078
        ],
        [
          1780064400000,
          7579.919922
        ],
        [
          1780064700000,
          7583.740234
        ],
        [
          1780065000000,
          7587.140137
        ],
        [
          1780065300000,
          7573.450195
        ],
        [
          1780065600000,
          7568.529785
        ],
        [
          1780065900000,
          7567.080078
        ],
        [
          1780066200000,
          7575.52002
        ],
        [
          1780066500000,
          7577.660156
        ],
        [
          1780066800000,
          7580.77002
        ],
        [
          1780067100000,
          7584.529785
        ],
        [
          1780067400000,
          7591.029785
        ],
        [
          1780067700000,
          7586.379883
        ],
        [
          1780068000000,
          7586.629883
        ],
        [
          1780068300000,
          7587.160156
        ],
        [
          1780068600000,
          7587.859863
        ],
        [
          1780068900000,
          7588.490234
        ],
        [
          1780069200000,
          7584.379883
        ],
        [
          1780069500000,
          7584.049805
        ],
        [
          1780069800000,
          7584.140137
        ],
        [
          1780070100000,
          7581.200195
        ],
        [
          1780070400000,
          7586.390137
        ],
        [
          1780070700000,
          7590.040039
        ],
        [
          1780071000000,
          7590.700195
        ],
        [
          1780071300000,
          7585.470215
        ],
        [
          1780071600000,
          7587.220215
        ],
        [
          1780071900000,
          7584.359863
        ],
        [
          1780072200000,
          7589.75
        ],
        [
          1780072500000,
          7593.919922
        ],
        [
          1780072800000,
          7591.950195
        ],
        [
          1780073100000,
          7589.350098
        ],
        [
          1780073400000,
          7586.839844
        ],
        [
          1780073700000,
          7585.620117
        ],
        [
          1780074000000,
          7583.419922
        ],
        [
          1780074300000,
          7585.22998
        ],
        [
          1780074600000,
          7584.430176
        ],
        [
          1780074900000,
          7585.399902
        ],
        [
          1780075200000,
          7584.029785
        ],
        [
          1780075500000,
          7583.319824
        ],
        [
          1780075800000,
          7582.660156
        ],
        [
          1780076100000,
          7580.759766
        ],
        [
          1780076400000,
          7577.669922
        ],
        [
          1780076700000,
          7577.839844
        ],
        [
          1780077000000,
          7575.970215
        ],
        [
          1780077300000,
          7569.919922
        ],
        [
          1780077600000,
          7574.629883
        ],
        [
          1780077900000,
          7576.759766
        ],
        [
          1780078200000,
          7574.390137
        ],
        [
          1780078500000,
          7576.950195
        ],
        [
          1780078800000,
          7579.359863
        ],
        [
          1780079100000,
          7580.609863
        ],
        [
          1780079400000,
          7584.52002
        ],
        [
          1780079700000,
          7583.02002
        ],
        [
          1780080000000,
          7581.640137
        ],
        [
          1780080300000,
          7575.299805
        ],
        [
          1780080600000,
          7574.540039
        ],
        [
          1780080900000,
          7572.0
        ],
        [
          1780081200000,
          7575.720215
        ],
        [
          1780081500000,
          7580.22998
        ],
        [
          1780081800000,
          7581.27002
        ],
        [
          1780082100000,
          7579.52002
        ],
        [
          1780082400000,
          7582.72998
        ],
        [
          1780082700000,
          7586.049805
        ],
        [
          1780083000000,
          7589.049805
        ],
        [
          1780083300000,
          7592.080078
        ],
        [
          1780083600000,
          7589.950195
        ],
        [
          1780083900000,
          7588.72998
        ],
        [
          1780084200000,
          7582.799805
        ],
        [
          1780084500000,
          7581.25
        ],
        [
          1780084800000,
          7580.060059
        ]
      ],
      "marketState": "UNKNOWN",
      "marketTime": "2026-05-30 06:03 KST",
      "marketTimestamp": 1780088617
    },
    {
      "id": "nasdaq",
      "label": "NASDAQ",
      "symbol": "^IXIC",
      "group": "해외 지수",
      "kind": "equity",
      "decimals": 2,
      "price": 26972.62,
      "previousClose": 26917.5,
      "change": 55.12,
      "changePercent": 0.2048,
      "tone": "up",
      "direction": "상승",
      "series": [
        [
          1780061400000,
          26948.324219
        ],
        [
          1780061700000,
          27004.226562
        ],
        [
          1780062000000,
          27058.679688
        ],
        [
          1780062300000,
          27065.632812
        ],
        [
          1780062600000,
          27066.587891
        ],
        [
          1780062900000,
          27073.699219
        ],
        [
          1780063200000,
          27073.953125
        ],
        [
          1780063500000,
          27043.253906
        ],
        [
          1780063800000,
          27016.048828
        ],
        [
          1780064100000,
          26978.080078
        ],
        [
          1780064400000,
          26952.291016
        ],
        [
          1780064700000,
          26967.972656
        ],
        [
          1780065000000,
          26988.941406
        ],
        [
          1780065300000,
          26919.898438
        ],
        [
          1780065600000,
          26875.951172
        ],
        [
          1780065900000,
          26889.816406
        ],
        [
          1780066200000,
          26926.265625
        ],
        [
          1780066500000,
          26937.181641
        ],
        [
          1780066800000,
          26953.978516
        ],
        [
          1780067100000,
          26979.351562
        ],
        [
          1780067400000,
          27012.904297
        ],
        [
          1780067700000,
          26986.683594
        ],
        [
          1780068000000,
          26984.330078
        ],
        [
          1780068300000,
          26989.722656
        ],
        [
          1780068600000,
          26998.705078
        ],
        [
          1780068900000,
          26998.359375
        ],
        [
          1780069200000,
          26969.347656
        ],
        [
          1780069500000,
          26972.451172
        ],
        [
          1780069800000,
          26973.013672
        ],
        [
          1780070100000,
          26962.53125
        ],
        [
          1780070400000,
          26996.544922
        ],
        [
          1780070700000,
          27019.542969
        ],
        [
          1780071000000,
          27025.615234
        ],
        [
          1780071300000,
          27007.884766
        ],
        [
          1780071600000,
          27016.177734
        ],
        [
          1780071900000,
          26992.951172
        ],
        [
          1780072200000,
          27011.779297
        ],
        [
          1780072500000,
          27031.796875
        ],
        [
          1780072800000,
          27022.316406
        ],
        [
          1780073100000,
          27010.072266
        ],
        [
          1780073400000,
          26999.613281
        ],
        [
          1780073700000,
          26993.0625
        ],
        [
          1780074000000,
          26985.464844
        ],
        [
          1780074300000,
          26995.869141
        ],
        [
          1780074600000,
          26992.236328
        ],
        [
          1780074900000,
          26989.9375
        ],
        [
          1780075200000,
          26982.310547
        ],
        [
          1780075500000,
          26975.044922
        ],
        [
          1780075800000,
          26971.46875
        ],
        [
          1780076100000,
          26966.988281
        ],
        [
          1780076400000,
          26955.529297
        ],
        [
          1780076700000,
          26955.396484
        ],
        [
          1780077000000,
          26947.322266
        ],
        [
          1780077300000,
          26915.394531
        ],
        [
          1780077600000,
          26934.931641
        ],
        [
          1780077900000,
          26951.394531
        ],
        [
          1780078200000,
          26939.0625
        ],
        [
          1780078500000,
          26952.728516
        ],
        [
          1780078800000,
          26963.949219
        ],
        [
          1780079100000,
          26975.271484
        ],
        [
          1780079400000,
          26987.136719
        ],
        [
          1780079700000,
          26969.244141
        ],
        [
          1780080000000,
          26974.820312
        ],
        [
          1780080300000,
          26944.197266
        ],
        [
          1780080600000,
          26938.835938
        ],
        [
          1780080900000,
          26923.603516
        ],
        [
          1780081200000,
          26941.636719
        ],
        [
          1780081500000,
          26961.390625
        ],
        [
          1780081800000,
          26967.123047
        ],
        [
          1780082100000,
          26959.238281
        ],
        [
          1780082400000,
          26968.570312
        ],
        [
          1780082700000,
          26980.201172
        ],
        [
          1780083000000,
          26993.298828
        ],
        [
          1780083300000,
          27016.373047
        ],
        [
          1780083600000,
          27010.285156
        ],
        [
          1780083900000,
          27008.433594
        ],
        [
          1780084200000,
          26986.523438
        ],
        [
          1780084500000,
          26976.353516
        ],
        [
          1780084800000,
          26972.619141
        ]
      ],
      "marketState": "UNKNOWN",
      "marketTime": "2026-05-30 06:15 KST",
      "marketTimestamp": 1780089359
    }
  ],
  "headlines": [
    {
      "title": "李대통령 “반도체 빼고도 한국 증시 무려 4100 이라고 해야”",
      "source": "서울신문",
      "link": "https://news.google.com/rss/articles/CBMifkFVX3lxTE5NTHktaHEwQWhrMmpUTkhYSVhLSnJQLVB6TnJlUzYxeWo3Y21WajVVYXhvUkdPdXJFTkxheWpVWDhJeEhOVERjU25VTUVwN1V2eFl4Qm5DWHRCVXkydEFWSUREcnRUbXh4ZGZ3QUYxZDkybE1nUFZLazFnX0RXdw?oc=5",
      "publishedAt": "Mon, 01 Jun 2026 02:55:08 GMT"
    },
    {
      "title": "“지방선거 끝나면 하락장 온다?”…증시 속설 따져보니 [잇슈 머니]",
      "source": "KBS 뉴스",
      "link": "https://news.google.com/rss/articles/CBMiW0FVX3lxTE52a1gwVmtOcWIzcXNWWHNPdi1NTzdoMmJpYnppMEhXb0lNS01uRmd5ZmNnVW5JakhILXQ3U09URHI3TjNkNDdmVVhOVURtQ19IWGo5bWNEYVdFQTA?oc=5",
      "publishedAt": "Sun, 31 May 2026 21:50:00 GMT"
    },
    {
      "title": "[마켓뷰] '사상 최고치' 코스피, '9천피' 도전 여부 주목",
      "source": "연합뉴스",
      "link": "https://news.google.com/rss/articles/CBMiYEFVX3lxTE9adWR5ZzhYSFNKWnViMzFLMkNrMnpWWTNIUXhFX2ZGUHNCTkJVX0p3VnRDZHdFWTNfbWM2ekZRRHpkU0V2ekJET2daUkZlSGJiNE9DQk90cm5uY1VZb3ZvcNIBYEFVX3lxTE9adWR5ZzhYSFNKWnViMzFLMkNrMnpWWTNIUXhFX2ZGUHNCTkJVX0p3VnRDZHdFWTNfbWM2ekZRRHpkU0V2ekJET2daUkZlSGJiNE9DQk90cm5uY1VZb3ZvcA?oc=5",
      "publishedAt": "Sun, 31 May 2026 23:16:54 GMT"
    },
    {
      "title": "성공투자 오후증시",
      "source": "한국경제TV",
      "link": "https://news.google.com/rss/articles/CBMiowFBVV95cUxNR3Q2TlIwWU4wdkxZZk9XbEI0Q3FSdDBYYVdKcEdSOE1ZRm00aFhwVFdjUWc2cUkycVRIVjdBMkIyWUdlTFp4QUxSOURYX1ViZXhvZGgyZmtsMTJjZ3ozOVFyalF3eWw4RnVRSEVmZkE2MlFaVDhDekpDYWFUV1NMd1AtZjRuSE52MmJGbFdTWTEyUzVxLXJCZy1GcVVscy0zVDdz?oc=5",
      "publishedAt": "Mon, 01 Jun 2026 06:56:43 GMT"
    },
    {
      "title": "[증시 레이더] 코스피 8,788선 질주⋯삼성전자 35만원 돌파, 시총 7천조 시대 열었다",
      "source": "포커스온경제",
      "link": "https://news.google.com/rss/articles/CBMiXkFVX3lxTE16bHgxTTkwTzdLVDBXeVliemZaZ2dKQ1dXRGtPMGExSUhka2FjWFVwVDJuY1F3d2RseFB4Y1lFWE1ncG9aeUEwRWlkdjFRZFRZdks4UVdPWkZmVFR2Qnc?oc=5",
      "publishedAt": "Mon, 01 Jun 2026 06:49:10 GMT"
    },
    {
      "title": "시중자금 블랙홀 된 증시…은행권 방어 총력전",
      "source": "ntoday.co.kr",
      "link": "https://news.google.com/rss/articles/CBMib0FVX3lxTFAtWHloMDd1SFBQWTRSN1A1cWswMFh6WG95ZEJHQ0w4aVFRU3FiNV96RVhub2NLSDdhblNSX0wtb0NycmFTMi1DQ3V4SGZhenV6TFBQOHljbmh0TWtDNjhkRDdSeGVRNlJnXzNYTlgxVdIBb0FVX3lxTFAtWHloMDd1SFBQWTRSN1A1cWswMFh6WG95ZEJHQ0w4aVFRU3FiNV96RVhub2NLSDdhblNSX0wtb0NycmFTMi1DQ3V4SGZhenV6TFBQOHljbmh0TWtDNjhkRDdSeGVRNlJnXzNYTlgxVQ?oc=5",
      "publishedAt": "Mon, 01 Jun 2026 01:15:30 GMT"
    },
    {
      "title": "코스피 새 역사 썼다… 증시 활황에 증권주 '들썩'",
      "source": "인포스탁데일리",
      "link": "https://news.google.com/rss/articles/CBMidkFVX3lxTE0tRGVhdWVWQzl3eWlad3l5TGpmaWFQUVFaMHdXSTZNcjlHT3pmMjVmR1hOSmpDLU9EMzVzdGJHUEpqN21BeGxBVk5HSVFkTTdQa0pLZjl6RzFJd0VWVjlzX2RJUjBMellBWnl1dlRWWnEwWUYzSEE?oc=5",
      "publishedAt": "Mon, 01 Jun 2026 02:16:54 GMT"
    },
    {
      "title": "1분기 기관 보유 해외 주식·채권 42.6억달러 감소… 중동 전쟁으로 증시 하락 영향 - 조선비즈",
      "source": "Chosunbiz",
      "link": "https://news.google.com/rss/articles/CBMihgFBVV95cUxPaTcwb0NFRWdxLVhNeG11dmVPRG94OUVlWE9LWEJmd050c2N6SGZHd0JEdmlVT1VRVmRSd3EwTGcyNDRCYmVoM3c5R2Npdzg0emlnZWEzejV3d19wSEdBNDJRbWc0Y0RKWnBiakllbVRaQmwyalJ2LVFpdE4xYnVuQ2UwMm9Gd9IBmgFBVV95cUxNRmxVWTBPTGxWdHVXaXVqNlFTWjZtUEp2SmtrVWRJZUNFR2NqNk1TX3kxVTk5Z3lEZTZjU1lRUVJaell5Z2NtQXdlV1gzUTBzMy1nNmVQZm5IUjZ5Y0NGZ0NkbXpwd2VseWJKU3VabWlRM1FuZ3RXUjBpcHB3UldNamFVOHd3VFk2c1Z0ZzFybWg0M0FScDZjMjJn?oc=5",
      "publishedAt": "Mon, 01 Jun 2026 03:00:00 GMT"
    }
  ],
  "summary": {
    "signal": {
      "label": "Risk-On",
      "tone": "up",
      "message": "주식과 위험자산 강세가 우세합니다."
    },
    "overview": [
      "국내장은 KOSPI 상승, KOSDAQ 하락 흐름입니다.",
      "해외는 S&P 500 +0.22%, NASDAQ +0.20%로 확인됩니다.",
      "매크로 변수는 USD/KRW -0.13%, 미 10년물 -0.04%입니다."
    ],
    "checkpoints": [
      "KOSPI +3.68% 상승",
      "KOSDAQ -2.30% 하락",
      "미국 증시 상승 / 나스닥 +0.20%",
      "원달러 -0.13% (-1.95)",
      "미 10년물 -0.002p (-0.04%)"
    ],
    "leaders": [
      {
        "label": "KOSPI",
        "changePercent": 3.6836,
        "direction": "상승"
      },
      {
        "label": "WTI",
        "changePercent": 3.4112,
        "direction": "상승"
      },
      {
        "label": "DOW",
        "changePercent": 0.7173,
        "direction": "상승"
      }
    ],
    "laggards": [
      {
        "label": "KOSDAQ",
        "changePercent": -2.3046,
        "direction": "하락"
      },
      {
        "label": "Gold",
        "changePercent": -1.3107,
        "direction": "하락"
      },
      {
        "label": "Bitcoin",
        "changePercent": -0.7848,
        "direction": "하락"
      }
    ]
  },
  "errors": []
}